{
  "type": "Feature",
  "properties": {
    "gn:admin1_code":"01",
    "gn:asciiname":"Biyaq",
    "gn:country_code":"OM",
    "gn:dem":524,
    "gn:feature_class":"P",
    "gn:feature_code":"PPL",
    "gn:name":"Biy\u0101q",
    "gn:population":0,
    "gn:timezone":"Asia/Muscat",
    "iso:country":"OM",
    "name:ara_x_preferred":[
        "Biy\u0101\u1e11"
    ],
    "name:ara_x_variant":[
        "\u0628\u064a\u0627\u0642"
    ],
    "name:und_x_variant":[
        "Biy\u0101q"
    ],
    "wof:name":"Biyaq",
    "wof:placetype":"locality"
},
  "geometry": {"coordinates":[57.86909,23.17765],"type":"Point"}
}