{
  "type": "Feature",
  "properties": {
    "gn:admin1_code":"01",
    "gn:asciiname":"Salaylah",
    "gn:country_code":"OM",
    "gn:dem":2175,
    "gn:feature_class":"P",
    "gn:feature_code":"PPL",
    "gn:name":"Salaylah",
    "gn:population":0,
    "gn:timezone":"Asia/Muscat",
    "iso:country":"OM",
    "wof:name":"Salaylah",
    "wof:placetype":"locality"
},
  "geometry": {"coordinates":[57.54111,23.1125],"type":"Point"}
}