{
  "type": "Feature",
  "properties": {
    "gn:admin1_code":"11",
    "gn:asciiname":"Sallan",
    "gn:country_code":"OM",
    "gn:dem":3,
    "gn:feature_class":"P",
    "gn:feature_code":"PPL",
    "gn:name":"\u015eall\u0101n",
    "gn:population":0,
    "gn:timezone":"Asia/Muscat",
    "iso:country":"OM",
    "name:ara_x_preferred":[
        "\u0635\u0644\u0651\u0627\u0646"
    ],
    "name:und_x_variant":[
        "\u015eall\u0101n",
        "\u1e62all\u0101n"
    ],
    "wof:name":"Sallan",
    "wof:placetype":"locality"
},
  "geometry": {"coordinates":[56.72721,24.3937],"type":"Point"}
}