{
  "type": "Feature",
  "properties": {
    "gn:admin1_code":"06",
    "gn:asciiname":"Al Mazari`",
    "gn:country_code":"OM",
    "gn:dem":122,
    "gn:feature_class":"P",
    "gn:feature_code":"PPL",
    "gn:name":"Al Maz\u0101ri\u2018",
    "gn:population":0,
    "gn:timezone":"Asia/Muscat",
    "iso:country":"OM",
    "name:ara_x_preferred":[
        "\u0627\u0644\u0645\u0632\u0627\u0631\u0639"
    ],
    "name:und_x_variant":[
        "Ghab\u012brah",
        "Al Maz\u0101ri\u2018"
    ],
    "wof:name":"Al Mazari`",
    "wof:placetype":"locality"
},
  "geometry": {"coordinates":[58.86279,23.09179],"type":"Point"}
}