{
  "type": "Feature",
  "properties": {
    "gn:admin1_code":"09",
    "gn:asciiname":"Al Furfarah",
    "gn:country_code":"OM",
    "gn:dem":488,
    "gn:feature_class":"P",
    "gn:feature_code":"PPL",
    "gn:name":"Al Furf\u0101rah",
    "gn:population":0,
    "gn:timezone":"Asia/Muscat",
    "iso:country":"OM",
    "name:ara_x_preferred":[
        "\u0627\u0644\u0641\u0631\u0641\u0627\u0631\u0629"
    ],
    "name:und_x_variant":[
        "\u1e28ayl al Farf\u0101r",
        "Al Furf\u0101rah"
    ],
    "wof:name":"Al Furfarah",
    "wof:placetype":"locality"
},
  "geometry": {"coordinates":[56.19006,23.84783],"type":"Point"}
}