{
  "type": "Feature",
  "properties": {
    "gn:admin1_code":"08",
    "gn:asciiname":"Ambaruf",
    "gn:country_code":"OM",
    "gn:dem":549,
    "gn:feature_class":"P",
    "gn:feature_code":"PPL",
    "gn:name":"Ambar\u016bf",
    "gn:population":0,
    "gn:timezone":"Asia/Muscat",
    "iso:country":"OM",
    "name:ara_x_preferred":[
        "\u0623\u0645\u0628\u0631\u0648\u0641"
    ],
    "name:und_x_variant":[
        "Umbarawf",
        "Ambar\u016bf",
        "Ambr\u016bf"
    ],
    "wof:name":"Ambaruf",
    "wof:placetype":"locality"
},
  "geometry": {"coordinates":[53.33807,16.755],"type":"Point"}
}