{
  "type": "Feature",
  "properties": {
    "gn:admin1_code":"10",
    "gn:asciiname":"Ajran",
    "gn:country_code":"OM",
    "gn:dem":613,
    "gn:feature_class":"P",
    "gn:feature_code":"PPL",
    "gn:name":"Ajr\u0101n",
    "gn:population":0,
    "gn:timezone":"Asia/Muscat",
    "iso:country":"OM",
    "name:ara_x_preferred":[
        "Ajr\u0101n"
    ],
    "wof:name":"Ajran",
    "wof:placetype":"locality"
},
  "geometry": {"coordinates":[56.16667,24.03333],"type":"Point"}
}