{
  "type": "Feature",
  "properties": {
    "gn:admin1_code":"11",
    "gn:asciiname":"As Sayh",
    "gn:country_code":"OM",
    "gn:dem":12,
    "gn:feature_class":"P",
    "gn:feature_code":"PPLL",
    "gn:name":"A\u015f \u015eay\u1e29",
    "gn:population":0,
    "gn:timezone":"Asia/Muscat",
    "iso:country":"OM",
    "name:und_x_variant":[
        "A\u015f \u015eay\u1e29"
    ],
    "wof:name":"As Sayh",
    "wof:placetype":"locality"
},
  "geometry": {"coordinates":[56.8275,24.21583],"type":"Point"}
}