{
  "type": "Feature",
  "properties": {
    "gn:admin1_code":"01",
    "gn:asciiname":"Al Haqq",
    "gn:country_code":"OM",
    "gn:dem":1331,
    "gn:feature_class":"P",
    "gn:feature_code":"PPL",
    "gn:name":"Al \u1e28aqq",
    "gn:population":0,
    "gn:timezone":"Asia/Muscat",
    "iso:country":"OM",
    "name:und_x_variant":[
        "Al \u1e28aqq"
    ],
    "wof:name":"Al Haqq",
    "wof:placetype":"locality"
},
  "geometry": {"coordinates":[57.75861,23.09611],"type":"Point"}
}