{
  "type": "Feature",
  "properties": {
    "iso:country":"OM",
    "qs:gn_pop":0,
    "qs:name":"\u0627\u0634\u0647\u064a\u062a",
    "qs:name_adm0":"\u0639\u0645\u0627\u0646",
    "qs:name_adm1":"\u0638\u0641\u0627\u0631",
    "qs:photos":83,
    "qs:photos_1k":17,
    "qs:photos_9k":1,
    "qs:photos_9r":3,
    "qs:photos_all":83,
    "qs:photos_sr":3,
    "qs:placetype":"Town",
    "qs:pop_sr":"0",
    "qs:woe_adm0":23424898,
    "wof:name":"\u0627\u0634\u0647\u064a\u062a",
    "wof:placetype":"locality"
},
  "geometry": {"coordinates":[54.425511,17.116839],"type":"Point"}
}