{
  "type": "Feature",
  "properties": {
    "gn:admin1_code":"08",
    "gn:asciiname":"Eerdeent",
    "gn:country_code":"OM",
    "gn:dem":799,
    "gn:feature_class":"P",
    "gn:feature_code":"PPL",
    "gn:name":"Eerdeent",
    "gn:population":0,
    "gn:timezone":"Asia/Muscat",
    "iso:country":"OM",
    "name:nno_x_preferred":[
        "Eerdeent"
    ],
    "wof:name":"Eerdeent",
    "wof:placetype":"locality"
},
  "geometry": {"coordinates":[53.99472,17.13222],"type":"Point"}
}