{
  "type": "Feature",
  "properties": {
    "gn:admin1_code":"01",
    "gn:asciiname":"Hayl",
    "gn:country_code":"OM",
    "gn:dem":1095,
    "gn:feature_class":"P",
    "gn:feature_code":"PPL",
    "gn:name":"\u1e28ayl",
    "gn:population":0,
    "gn:timezone":"Asia/Muscat",
    "iso:country":"OM",
    "name:und_x_variant":[
        "\u1e28ayl"
    ],
    "wof:name":"Hayl",
    "wof:placetype":"locality"
},
  "geometry": {"coordinates":[57.51667,23.08333],"type":"Point"}
}