{
  "type": "Feature",
  "properties": {
    "gn:admin1_code":"02",
    "gn:asciiname":"Saqlah",
    "gn:country_code":"OM",
    "gn:dem":1021,
    "gn:feature_class":"P",
    "gn:feature_code":"PPL",
    "gn:name":"Saqlah",
    "gn:population":0,
    "gn:timezone":"Asia/Muscat",
    "iso:country":"OM",
    "name:ara_x_preferred":[
        "\u0633\u0642\u0644\u0629"
    ],
    "wof:name":"Saqlah",
    "wof:placetype":"locality"
},
  "geometry": {"coordinates":[57.64458000000001,23.22734],"type":"Point"}
}