{
  "type": "Feature",
  "properties": {
    "gn:admin1_code":"08",
    "gn:asciiname":"A` Tayrit",
    "gn:country_code":"OM",
    "gn:dem":749,
    "gn:feature_class":"P",
    "gn:feature_code":"PPL",
    "gn:name":"A\u2018 \u0162ayr\u012bt",
    "gn:population":0,
    "gn:timezone":"Asia/Muscat",
    "iso:country":"OM",
    "name:ara_x_preferred":[
        "\u0623\u0639\u0637\u064a\u0631\u064a\u062a"
    ],
    "name:und_x_variant":[
        "A\u2018 \u0162ayr\u012bt",
        "A\u2018a\u0163ayr\u012bt"
    ],
    "wof:name":"A` Tayrit",
    "wof:placetype":"locality"
},
  "geometry": {"coordinates":[54.41353,17.17189],"type":"Point"}
}