{
  "type": "Feature",
  "properties": {
    "gn:admin1_code":"04",
    "gn:asciiname":"Juwaybi",
    "gn:country_code":"OM",
    "gn:dem":53,
    "gn:feature_class":"P",
    "gn:feature_code":"PPL",
    "gn:name":"Juwayb\u012b",
    "gn:population":0,
    "gn:timezone":"Asia/Muscat",
    "iso:country":"OM",
    "name:und_x_variant":[
        "Juwayb\u012b"
    ],
    "wof:name":"Juwaybi",
    "wof:placetype":"locality"
},
  "geometry": {"coordinates":[59.45074,22.05837],"type":"Point"}
}