{
  "type": "Feature",
  "properties": {
    "gn:admin1_code":"12",
    "gn:asciiname":"Lizq",
    "gn:country_code":"OM",
    "gn:dem":480,
    "gn:feature_class":"P",
    "gn:feature_code":"PPL",
    "gn:name":"Lizq",
    "gn:population":0,
    "gn:timezone":"Asia/Muscat",
    "iso:country":"OM",
    "name:ara_x_preferred":[
        "\u0644\u0632\u0642"
    ],
    "wof:name":"Lizq",
    "wof:placetype":"locality"
},
  "geometry": {"coordinates":[58.17262,22.71557],"type":"Point"}
}