{
  "type": "Feature",
  "properties": {
    "gn:admin1_code":"10",
    "gn:asciiname":"Al Ashqar",
    "gn:country_code":"OM",
    "gn:dem":639,
    "gn:feature_class":"P",
    "gn:feature_code":"PPL",
    "gn:name":"Al Ashqar",
    "gn:population":0,
    "gn:timezone":"Asia/Muscat",
    "iso:country":"OM",
    "name:und_x_variant":[
        "Lishgar",
        "Al Ashqar"
    ],
    "wof:name":"Al Ashqar",
    "wof:placetype":"locality"
},
  "geometry": {"coordinates":[56.12908,24.31564],"type":"Point"}
}