{
  "type": "Feature",
  "properties": {
    "gn:admin1_code":"08",
    "gn:asciiname":"Hadsha`ab",
    "gn:country_code":"OM",
    "gn:dem":512,
    "gn:feature_class":"P",
    "gn:feature_code":"PPL",
    "gn:name":"Hadsha\u2018ab",
    "gn:population":0,
    "gn:timezone":"Asia/Muscat",
    "iso:country":"OM",
    "name:ara_x_preferred":[
        "\u0623\u0631\u0645\u0633\u0639\u0648\u062f"
    ],
    "name:und_x_variant":[
        "Hadsha\u2018ab",
        "Armsu\u2018\u016bd"
    ],
    "wof:name":"Hadsha`ab",
    "wof:placetype":"locality"
},
  "geometry": {"coordinates":[54.04917,17.15833],"type":"Point"}
}