{
  "type": "Feature",
  "properties": {
    "gn:admin1_code":"01",
    "gn:asciiname":"Al Fulayj",
    "gn:country_code":"OM",
    "gn:dem":359,
    "gn:feature_class":"P",
    "gn:feature_code":"PPL",
    "gn:name":"Al Fulayj",
    "gn:population":0,
    "gn:timezone":"Asia/Muscat",
    "iso:country":"OM",
    "name:ara_x_preferred":[
        "\u0627\u0644\u0641\u0644\u064a\u062c"
    ],
    "name:und_x_variant":[
        "Fulayy",
        "Falai",
        "Fulayj",
        "Al Fulayj",
        "Al Filayj"
    ],
    "wof:name":"Al Fulayj",
    "wof:placetype":"locality"
},
  "geometry": {"coordinates":[57.35919000000001,22.66366],"type":"Point"}
}