{
  "type": "Feature",
  "properties": {
    "gn:admin1_code":"08",
    "gn:asciiname":"Shibub",
    "gn:country_code":"OM",
    "gn:dem":828,
    "gn:feature_class":"P",
    "gn:feature_code":"PPL",
    "gn:name":"Sh\u012bb\u016bb",
    "gn:population":0,
    "gn:timezone":"Asia/Muscat",
    "iso:country":"OM",
    "name:ara_x_preferred":[
        "Sh\u012bb\u016bb"
    ],
    "name:ara_x_variant":[
        "\u0634\u0628\u0648\u0628"
    ],
    "name:und_x_variant":[
        "Shibob",
        "Shub\u016bb"
    ],
    "wof:name":"Shibub",
    "wof:placetype":"locality"
},
  "geometry": {"coordinates":[53.99472,17.17178],"type":"Point"}
}