{
  "type": "Feature",
  "properties": {
    "gn:admin1_code":"01",
    "gn:asciiname":"Rassah",
    "gn:country_code":"OM",
    "gn:dem":708,
    "gn:feature_class":"P",
    "gn:feature_code":"PPL",
    "gn:name":"Rassah",
    "gn:population":0,
    "gn:timezone":"Asia/Muscat",
    "iso:country":"OM",
    "wof:name":"Rassah",
    "wof:placetype":"locality"
},
  "geometry": {"coordinates":[56.87644,23.38498],"type":"Point"}
}