{
  "type": "Feature",
  "properties": {
    "gn:admin1_code":"12",
    "gn:asciiname":"Mazra` Zarka`",
    "gn:country_code":"OM",
    "gn:dem":360,
    "gn:feature_class":"P",
    "gn:feature_code":"PPL",
    "gn:name":"Mazra\u2018 Zark\u0101\u2018",
    "gn:population":0,
    "gn:timezone":"Asia/Muscat",
    "iso:country":"OM",
    "name:und_x_variant":[
        "Mazra\u2018 Zark\u0101\u2018"
    ],
    "wof:name":"Mazra` Zarka`",
    "wof:placetype":"locality"
},
  "geometry": {"coordinates":[58.60179,23.06728],"type":"Point"}
}