{
  "type": "Feature",
  "properties": {
    "gn:admin1_code":"06",
    "gn:asciiname":"Sa`al",
    "gn:country_code":"OM",
    "gn:dem":202,
    "gn:feature_class":"P",
    "gn:feature_code":"PPL",
    "gn:name":"Sa\u2018\u0101l",
    "gn:population":0,
    "gn:timezone":"Asia/Muscat",
    "iso:country":"OM",
    "name:und_x_variant":[
        "Sa\u2018\u0101l"
    ],
    "wof:name":"Sa`al",
    "wof:placetype":"locality"
},
  "geometry": {"coordinates":[58.21974,23.45016],"type":"Point"}
}