{
  "type": "Feature",
  "properties": {
    "gn:admin1_code":"06",
    "gn:asciiname":"Al Ansab",
    "gn:country_code":"OM",
    "gn:dem":59,
    "gn:feature_class":"P",
    "gn:feature_code":"PPL",
    "gn:name":"Al An\u015fab",
    "gn:population":0,
    "gn:timezone":"Asia/Muscat",
    "iso:country":"OM",
    "name:ara_x_preferred":[
        "\u0627\u0644\u0623\u0646\u0635\u0628"
    ],
    "name:nno_x_preferred":[
        "Lansab"
    ],
    "name:und_x_variant":[
        "Lan\u015fab",
        "Al An\u015fab",
        "Al An\u1e63ab"
    ],
    "name:urd_x_preferred":[
        "\u0644\u0627\u0646\u0633\u0627\u0628"
    ],
    "wof:name":"Al Ansab",
    "wof:placetype":"locality"
},
  "geometry": {"coordinates":[58.35449000000001,23.538],"type":"Point"}
}