{
  "type": "Feature",
  "properties": {
    "gn:admin1_code":"11",
    "gn:asciiname":"Al `Aqli",
    "gn:country_code":"OM",
    "gn:dem":367,
    "gn:feature_class":"P",
    "gn:feature_code":"PPL",
    "gn:name":"Al \u2018Aql\u012b",
    "gn:population":0,
    "gn:timezone":"Asia/Muscat",
    "iso:country":"OM",
    "name:ara_x_preferred":[
        "\u0627\u0644\u0639\u0642\u0644\u064a"
    ],
    "name:und_x_variant":[
        "Al Aqli",
        "Al \u2018Aql\u012b"
    ],
    "wof:name":"Al `Aqli",
    "wof:placetype":"locality"
},
  "geometry": {"coordinates":[56.76922,23.80814],"type":"Point"}
}