{
  "type": "Feature",
  "properties": {
    "gn:admin1_code":"11",
    "gn:asciiname":"As Sayrasah",
    "gn:country_code":"OM",
    "gn:dem":18,
    "gn:feature_class":"P",
    "gn:feature_code":"PPL",
    "gn:name":"As Sayrasah",
    "gn:population":0,
    "gn:timezone":"Asia/Muscat",
    "iso:country":"OM",
    "wof:name":"As Sayrasah",
    "wof:placetype":"locality"
},
  "geometry": {"coordinates":[57.35556,23.82972],"type":"Point"}
}