{
  "type": "Feature",
  "properties": {
    "gn:admin1_code":"11",
    "gn:asciiname":"Sihlat",
    "gn:country_code":"OM",
    "gn:dem":163,
    "gn:feature_class":"P",
    "gn:feature_code":"PPLL",
    "gn:name":"Sihl\u0101t",
    "gn:population":0,
    "gn:timezone":"Asia/Muscat",
    "iso:country":"OM",
    "name:ara_x_preferred":[
        "Sihl\u0101t"
    ],
    "wof:name":"Sihlat",
    "wof:placetype":"locality"
},
  "geometry": {"coordinates":[56.5155,24.33173],"type":"Point"}
}