{
  "type": "Feature",
  "properties": {
    "gn:admin1_code":"01",
    "gn:asciiname":"Ghumrah",
    "gn:country_code":"OM",
    "gn:dem":611,
    "gn:feature_class":"P",
    "gn:feature_code":"PPL",
    "gn:name":"Ghumrah",
    "gn:population":0,
    "gn:timezone":"Asia/Muscat",
    "iso:country":"OM",
    "name:und_x_variant":[
        "Ghumra",
        "Ghumrah"
    ],
    "wof:name":"Ghumrah",
    "wof:placetype":"locality"
},
  "geometry": {"coordinates":[57.32021,23.0009],"type":"Point"}
}