{
  "type": "Feature",
  "properties": {
    "gn:admin1_code":"11",
    "gn:asciiname":"Tawi Bedi Guish",
    "gn:country_code":"OM",
    "gn:dem":8,
    "gn:feature_class":"P",
    "gn:feature_code":"PPL",
    "gn:name":"\u0162aw\u012b Bedi Guish",
    "gn:population":0,
    "gn:timezone":"Asia/Muscat",
    "iso:country":"OM",
    "name:und_x_variant":[
        "\u0162aw\u012b Bedi Guish"
    ],
    "wof:name":"Tawi Bedi Guish",
    "wof:placetype":"locality"
},
  "geometry": {"coordinates":[57.37361,23.86722],"type":"Point"}
}