{
  "type": "Feature",
  "properties": {
    "gn:admin1_code":"11",
    "gn:asciiname":"Al Hushaymiyah",
    "gn:country_code":"OM",
    "gn:dem":668,
    "gn:feature_class":"P",
    "gn:feature_code":"PPL",
    "gn:name":"Al Hushaym\u012byah",
    "gn:population":0,
    "gn:timezone":"Asia/Muscat",
    "iso:country":"OM",
    "name:ara_x_preferred":[
        "\u0627\u0644\u0647\u0634\u064a\u0645\u064a\u0629"
    ],
    "name:und_x_variant":[
        "Al Hishmah",
        "Al Hushaym\u012byah",
        "Al Hishaymiyyah"
    ],
    "wof:name":"Al Hushaymiyah",
    "wof:placetype":"locality"
},
  "geometry": {"coordinates":[56.42004,23.93293],"type":"Point"}
}