{
  "type": "Feature",
  "properties": {
    "gn:admin1_code":"08",
    "gn:asciiname":"Jibjat",
    "gn:country_code":"OM",
    "gn:dem":941,
    "gn:feature_class":"P",
    "gn:feature_code":"PPL",
    "gn:name":"Jibj\u0101t",
    "gn:population":0,
    "gn:timezone":"Asia/Muscat",
    "iso:country":"OM",
    "name:ara_x_preferred":[
        "Jibj\u0101t"
    ],
    "name:ara_x_variant":[
        "\u062c\u0628\u062c\u0627\u062a"
    ],
    "name:nno_x_preferred":[
        "Jibjat"
    ],
    "name:und_x_variant":[
        "Jibjaat"
    ],
    "wof:name":"Jibjat",
    "wof:placetype":"locality"
},
  "geometry": {"coordinates":[54.49803000000001,17.24731],"type":"Point"}
}