{
  "type": "Feature",
  "properties": {
    "iso:country":"OM",
    "name:ara_x_preferred":[
        "\u0648\u0644\u0627\u064a\u0629 \u0645\u0631\u0628\u0627\u0637"
    ],
    "name:ces_x_preferred":[
        "Mirbat"
    ],
    "name:deu_x_preferred":[
        "Mirbat"
    ],
    "name:fas_x_preferred":[
        "\u0645\u0631\u0628\u0627\u0637"
    ],
    "name:fra_x_preferred":[
        "Mirbat"
    ],
    "name:ita_x_preferred":[
        "Mirbat"
    ],
    "name:jpn_x_preferred":[
        "\u30df\u30eb\u30d0\u30c8"
    ],
    "name:msa_x_preferred":[
        "Mirbat"
    ],
    "name:nno_x_preferred":[
        "Mirbat"
    ],
    "name:rus_x_preferred":[
        "\u041c\u0438\u0440\u0431\u0430\u0442"
    ],
    "name:tur_x_preferred":[
        "Marbat"
    ],
    "ne:ADM0CAP":0.0,
    "ne:ADM0NAME":"Oman",
    "ne:ADM0_A3":"OMN",
    "ne:ADM1NAME":"Dhofar",
    "ne:ADMIN1_COD":0,
    "ne:CAPALT":0,
    "ne:CHANGED":0,
    "ne:CHECKME":0,
    "ne:COMPARE":0,
    "ne:DIFFASCII":0,
    "ne:ELEVATION":0.0,
    "ne:FEATURECLA":"Populated place",
    "ne:GEONAMEID":-1,
    "ne:GEONAMESNO":"No GeoNames match due to small population, not in GeoNames, or poor NEV placement.",
    "ne:GN_POP":0,
    "ne:GTOPO30":0.0,
    "ne:ISO_A2":"OM",
    "ne:LABELRANK":8,
    "ne:LATITUDE":16.992437,
    "ne:LONGITUDE":54.691793,
    "ne:LS_MATCH":1,
    "ne:LS_NAME":"Mirbat",
    "ne:MAX_AREAKM":1.0,
    "ne:MAX_AREAMI":0.0,
    "ne:MAX_BBXMAX":54.7,
    "ne:MAX_BBXMIN":54.691667,
    "ne:MAX_BBYMAX":16.991667,
    "ne:MAX_BBYMIN":16.983333,
    "ne:MAX_NATSCA":20.0,
    "ne:MAX_PERKM":4.0,
    "ne:MAX_PERMI":2.0,
    "ne:MAX_POP10":1120,
    "ne:MAX_POP20":1120,
    "ne:MAX_POP300":0,
    "ne:MAX_POP310":0,
    "ne:MAX_POP50":0,
    "ne:MEAN_BBXC":54.695833,
    "ne:MEAN_BBYC":16.9875,
    "ne:MEGACITY":0,
    "ne:MIN_AREAKM":1.0,
    "ne:MIN_AREAMI":0.0,
    "ne:MIN_BBXMAX":54.7,
    "ne:MIN_BBXMIN":54.691667,
    "ne:MIN_BBYMAX":16.991667,
    "ne:MIN_BBYMIN":16.983333,
    "ne:MIN_PERKM":4.0,
    "ne:MIN_PERMI":2.0,
    "ne:NAME":"Mirbat",
    "ne:NAMEASCII":"Mirbat",
    "ne:NAMEDIFF":0,
    "ne:NATSCALE":20,
    "ne:POP1950":0,
    "ne:POP1955":0,
    "ne:POP1960":0,
    "ne:POP1965":0,
    "ne:POP1970":0,
    "ne:POP1975":0,
    "ne:POP1980":0,
    "ne:POP1985":0,
    "ne:POP1990":0,
    "ne:POP1995":0,
    "ne:POP2000":0,
    "ne:POP2005":0,
    "ne:POP2010":0,
    "ne:POP2015":0,
    "ne:POP2020":0,
    "ne:POP2025":0,
    "ne:POP2050":0,
    "ne:POP_MAX":1120,
    "ne:POP_MIN":1120,
    "ne:POP_OTHER":0,
    "ne:RANK_MAX":3,
    "ne:RANK_MIN":3,
    "ne:SCALERANK":7,
    "ne:SOV0NAME":"Oman",
    "ne:SOV_A3":"OMN",
    "ne:UN_FID":0,
    "ne:UN_LAT":0.0,
    "ne:UN_LONG":0.0,
    "ne:WORLDCITY":0,
    "ne:min_zoom":6.7,
    "wof:name":"Mirbat",
    "wof:placetype":"locality"
},
  "geometry": {"coordinates":[54.69179317100475,16.99243694962871],"type":"Point"}
}