{
  "type": "Feature",
  "properties": {
    "gn:admin1_code":"11",
    "gn:asciiname":"Muntayfah",
    "gn:country_code":"OM",
    "gn:dem":5,
    "gn:feature_class":"P",
    "gn:feature_code":"PPL",
    "gn:name":"Mun\u0163ayfah",
    "gn:population":0,
    "gn:timezone":"Asia/Muscat",
    "iso:country":"OM",
    "name:und_x_variant":[
        "Mun\u0163ayfah"
    ],
    "wof:name":"Muntayfah",
    "wof:placetype":"locality"
},
  "geometry": {"coordinates":[57.01608,24.05203],"type":"Point"}
}