{
  "type": "Feature",
  "properties": {
    "gn:admin1_code":"01",
    "gn:asciiname":"At Tuwayyah",
    "gn:country_code":"OM",
    "gn:dem":450,
    "gn:feature_class":"P",
    "gn:feature_code":"PPL",
    "gn:name":"A\u0163 \u0162uwayyah",
    "gn:population":0,
    "gn:timezone":"Asia/Muscat",
    "iso:country":"OM",
    "name:ara_x_preferred":[
        "\u0627\u0644\u0637\u0648\u064a\u0651\u0629"
    ],
    "name:und_x_variant":[
        "\u0162aw\u012byah",
        "A\u0163 \u0162uwayyah",
        "A\u1e6d \u1e6cuwayyah"
    ],
    "wof:name":"At Tuwayyah",
    "wof:placetype":"locality"
},
  "geometry": {"coordinates":[58.07802,23.21644],"type":"Point"}
}