{
  "type": "Feature",
  "properties": {
    "gn:admin1_code":"12",
    "gn:asciiname":"Hadi Thabil",
    "gn:country_code":"OM",
    "gn:dem":436,
    "gn:feature_class":"P",
    "gn:feature_code":"PPL",
    "gn:name":"H\u0101d\u012b Th\u0101bil",
    "gn:population":0,
    "gn:timezone":"Asia/Muscat",
    "iso:country":"OM",
    "name:ara_x_preferred":[
        "H\u0101d\u012b Th\u0101bil"
    ],
    "wof:name":"Hadi Thabil",
    "wof:placetype":"locality"
},
  "geometry": {"coordinates":[58.81032,22.96158],"type":"Point"}
}