{
  "type": "Feature",
  "properties": {
    "gn:admin1_code":"04",
    "gn:asciiname":"Halam",
    "gn:country_code":"OM",
    "gn:dem":852,
    "gn:feature_class":"P",
    "gn:feature_code":"PPL",
    "gn:name":"\u1e28alam",
    "gn:population":0,
    "gn:timezone":"Asia/Muscat",
    "iso:country":"OM",
    "name:ara_x_preferred":[
        "\u1e28ilm"
    ],
    "name:ara_x_variant":[
        "\u062d\u0644\u0645"
    ],
    "name:ceb_x_preferred":[
        "Halam"
    ],
    "name:swe_x_preferred":[
        "Halam"
    ],
    "name:und_x_variant":[
        "\u1e28alam",
        "\u1e24alam"
    ],
    "wof:name":"Halam",
    "wof:placetype":"locality"
},
  "geometry": {"coordinates":[59.21989,22.65652],"type":"Point"}
}