{
  "type": "Feature",
  "properties": {
    "gn:admin1_code":"06",
    "gn:asciiname":"Dhiqdah",
    "gn:country_code":"OM",
    "gn:dem":197,
    "gn:feature_class":"P",
    "gn:feature_code":"PPL",
    "gn:name":"Dh\u012bqdah",
    "gn:population":0,
    "gn:timezone":"Asia/Muscat",
    "iso:country":"OM",
    "name:und_x_variant":[
        "Dh\u012bqdah"
    ],
    "wof:name":"Dhiqdah",
    "wof:placetype":"locality"
},
  "geometry": {"coordinates":[58.75278,23.39222],"type":"Point"}
}