{
  "type": "Feature",
  "properties": {
    "gn:admin1_code":"01",
    "gn:asciiname":"Bima",
    "gn:country_code":"OM",
    "gn:dem":862,
    "gn:feature_class":"P",
    "gn:feature_code":"PPL",
    "gn:name":"B\u012bm\u0101",
    "gn:population":0,
    "gn:timezone":"Asia/Muscat",
    "iso:country":"OM",
    "name:ara_x_preferred":[
        "\u0628\u064a\u0645\u0627"
    ],
    "name:und_x_variant":[
        "B\u012bm\u0101",
        "B\u012bmah",
        "B\u012bma"
    ],
    "wof:name":"Bima",
    "wof:placetype":"locality"
},
  "geometry": {"coordinates":[57.38139,23.20806],"type":"Point"}
}