{
  "type": "Feature",
  "properties": {
    "gn:admin1_code":"12",
    "gn:asciiname":"Al Ghabbi",
    "gn:country_code":"OM",
    "gn:dem":297,
    "gn:feature_class":"P",
    "gn:feature_code":"PPL",
    "gn:name":"Al Ghabb\u012b",
    "gn:population":0,
    "gn:timezone":"Asia/Muscat",
    "iso:country":"OM",
    "name:und_x_variant":[
        "Al Ghabb\u012b"
    ],
    "wof:name":"Al Ghabbi",
    "wof:placetype":"locality"
},
  "geometry": {"coordinates":[58.81213,22.44821],"type":"Point"}
}