{
  "type": "Feature",
  "properties": {
    "gn:admin1_code":"07",
    "gn:asciiname":"Wadi al Fahl",
    "gn:country_code":"OM",
    "gn:dem":349,
    "gn:feature_class":"P",
    "gn:feature_code":"PPL",
    "gn:name":"W\u0101d\u012b al Fa\u1e29l",
    "gn:population":0,
    "gn:timezone":"Asia/Muscat",
    "iso:country":"OM",
    "name:ara_x_preferred":[
        "\u0648\u0627\u062f\u064a \u0627\u0644\u0641\u062d\u0644"
    ],
    "name:und_x_variant":[
        "Wa\u2018b al Fa\u1e29l",
        "W\u0101d\u012b al Fa\u1e29l",
        "W\u0101d\u012b al Fa\u1e25al"
    ],
    "wof:name":"Wadi al Fahl",
    "wof:placetype":"locality"
},
  "geometry": {"coordinates":[56.31423,25.80556],"type":"Point"}
}