{
  "type": "Feature",
  "properties": {
    "gn:admin1_code":"09",
    "gn:asciiname":"Mushir",
    "gn:country_code":"OM",
    "gn:dem":593,
    "gn:feature_class":"P",
    "gn:feature_code":"PPL",
    "gn:name":"Mush\u012br",
    "gn:population":0,
    "gn:timezone":"Asia/Muscat",
    "iso:country":"OM",
    "name:ara_x_preferred":[
        "Mush\u012br"
    ],
    "name:fra_x_preferred":[
        "Mushir"
    ],
    "name:ind_x_preferred":[
        "Mushir"
    ],
    "name:ita_x_preferred":[
        "Mush\u012br"
    ],
    "name:msa_x_preferred":[
        "Mushir"
    ],
    "name:spa_x_preferred":[
        "Mushir"
    ],
    "name:srp_x_preferred":[
        "\u041c\u0443\u0448\u0438\u0440"
    ],
    "name:swe_x_preferred":[
        "Muschir"
    ],
    "name:tur_x_preferred":[
        "M\u00fc\u015f\u00eer"
    ],
    "wof:name":"Mushir",
    "wof:placetype":"locality"
},
  "geometry": {"coordinates":[56.4914,23.63152],"type":"Point"}
}