{
  "type": "Feature",
  "properties": {
    "gn:country":"OM",
    "gn:fcode":"PPL",
    "gn:population":25265,
    "iso:country":"OM",
    "name:ara_x_preferred":[
        "Ibr\u0101"
    ],
    "name:ara_x_variant":[
        "Ibr\u0101\u2019",
        "\u0625\u0628\u0631\u0627\u0621"
    ],
    "name:rus_x_preferred":[
        "\u0418\u0431\u0440\u0430"
    ],
    "name:und_x_variant":[
        "Bira"
    ],
    "qs_pg:aaroncc":"OM",
    "qs_pg:gn_country":"OM",
    "qs_pg:gn_fcode":"PPL",
    "qs_pg:gn_pop":25265,
    "qs_pg:name":"Ibr\u0101\u2019",
    "qs_pg:photos_9r":0,
    "qs_pg:photos_sr":0,
    "qs_pg:pop_sr":7,
    "qs_pg:qs_pg_placetype":"locality",
    "wof:name":"Ibr\u0101\u2019",
    "wof:placetype":"locality",
    "wof:population":25265
},
  "geometry": {"coordinates":[58.53337,22.69057],"type":"Point"}
}