{
  "type": "Feature",
  "properties": {
    "gn:admin1_code":"08",
    "gn:asciiname":"Dhayd Rasm",
    "gn:cc2":"OM",
    "gn:country_code":"OM",
    "gn:dem":395,
    "gn:feature_class":"P",
    "gn:feature_code":"PPL",
    "gn:name":"Dhayd Rasm",
    "gn:population":0,
    "gn:timezone":"Asia/Muscat",
    "iso:country":"OM",
    "name:und_x_variant":[
        "Dhaid Rasm",
        "Dhayd Rasm"
    ],
    "wof:name":"Dhayd Rasm",
    "wof:placetype":"locality"
},
  "geometry": {"coordinates":[54.04417,17.14167],"type":"Point"}
}