{
  "type": "Feature",
  "properties": {
    "gn:admin1_code":"11",
    "gn:asciiname":"Fayyah",
    "gn:country_code":"OM",
    "gn:dem":457,
    "gn:feature_class":"P",
    "gn:feature_code":"PPL",
    "gn:name":"Fayyah",
    "gn:population":0,
    "gn:timezone":"Asia/Muscat",
    "iso:country":"OM",
    "name:ara_x_preferred":[
        "\u0641\u064a\u0629"
    ],
    "wof:name":"Fayyah",
    "wof:placetype":"locality"
},
  "geometry": {"coordinates":[56.6725,23.91833],"type":"Point"}
}