{
  "type": "Feature",
  "properties": {
    "gn:admin1_code":"12",
    "gn:asciiname":"Al Qufaysi",
    "gn:country_code":"OM",
    "gn:dem":572,
    "gn:feature_class":"P",
    "gn:feature_code":"PPL",
    "gn:name":"Al Qufay\u015f\u012b",
    "gn:population":0,
    "gn:timezone":"Asia/Muscat",
    "iso:country":"OM",
    "name:ara_x_preferred":[
        "\u0627\u0644\u0642\u0641\u064a\u0635\u064a"
    ],
    "name:und_x_variant":[
        "Qaf\u012bs",
        "Al Qufay\u015f\u012b",
        "Al Qifay\u1e63\u012b"
    ],
    "wof:name":"Al Qufaysi",
    "wof:placetype":"locality"
},
  "geometry": {"coordinates":[58.77516,22.87944],"type":"Point"}
}