{
  "type": "Feature",
  "properties": {
    "gn:admin1_code":"08",
    "gn:asciiname":"Hakab",
    "gn:country_code":"OM",
    "gn:dem":652,
    "gn:feature_class":"P",
    "gn:feature_code":"PPL",
    "gn:name":"\u1e28\u0101k\u0101b",
    "gn:population":0,
    "gn:timezone":"Asia/Muscat",
    "iso:country":"OM",
    "name:ara_x_preferred":[
        "\u1e28\u0101k\u0101b"
    ],
    "name:ara_x_variant":[
        "\u062d\u0627\u0643\u0627\u0628"
    ],
    "wof:name":"Hakab",
    "wof:placetype":"locality"
},
  "geometry": {"coordinates":[54.49589,17.15054],"type":"Point"}
}