{
  "type": "Feature",
  "properties": {
    "gn:country":"OM",
    "gn:fcode":"PPLA",
    "gn:population":108274,
    "iso:country":"OM",
    "name:ara_x_preferred":[
        "A\u015f \u015eu\u1e29\u0101r"
    ],
    "name:ara_x_variant":[
        "\u015eu\u1e29\u0101r",
        "\u0635\u062d\u0627\u0631",
        "\u0648\u0644\u0627\u064a\u0629 \u0635\u062d\u0627\u0631"
    ],
    "name:cat_x_preferred":[
        "Suhar"
    ],
    "name:ces_x_preferred":[
        "Suh\u00e1r"
    ],
    "name:deu_x_preferred":[
        "Suhar"
    ],
    "name:eng_x_preferred":[
        "Sohar"
    ],
    "name:epo_x_preferred":[
        "Suhar"
    ],
    "name:fas_x_preferred":[
        "\u0635\u062d\u0627\u0631"
    ],
    "name:jpn_x_preferred":[
        "\u30bd\u30cf\u30fc\u30eb"
    ],
    "name:kor_x_preferred":[
        "\uc18c\ud558\ub974"
    ],
    "name:lit_x_preferred":[
        "Soharas"
    ],
    "name:nor_x_preferred":[
        "Suhar"
    ],
    "name:pol_x_preferred":[
        "Suhar"
    ],
    "name:rus_x_preferred":[
        "\u0421\u0443\u0445\u0430\u0440"
    ],
    "name:tur_x_preferred":[
        "Sahar"
    ],
    "name:urd_x_preferred":[
        "\u0635\u062d\u0627\u0631"
    ],
    "name:zho_x_preferred":[
        "\u82cf\u54c8\u5c14"
    ],
    "ne:ADM0CAP":0.0,
    "ne:ADM0NAME":"Oman",
    "ne:ADM0_A3":"OMN",
    "ne:ADM1NAME":"Al Batnah",
    "ne:ADMIN1_COD":2,
    "ne:CAPALT":0,
    "ne:CHANGED":1,
    "ne:CHECKME":0,
    "ne:COMPARE":0,
    "ne:DIFFASCII":0,
    "ne:DIFFNOTE":"Location adjusted. Changed scale rank.",
    "ne:ELEVATION":0.0,
    "ne:FEATURECLA":"Populated place",
    "ne:FEATURE_CL":"P",
    "ne:FEATURE_CO":"PPL",
    "ne:GEONAMEID":286282,
    "ne:GEONAMESNO":"Geonames ascii name + lat.d + long.d matching.",
    "ne:GN_ASCII":"Suhar",
    "ne:GN_POP":108274,
    "ne:GTOPO30":4.0,
    "ne:ISO_A2":"OM",
    "ne:LABELRANK":8,
    "ne:LATITUDE":24.361973,
    "ne:LONGITUDE":56.734419,
    "ne:LS_MATCH":1,
    "ne:LS_NAME":"Suhar",
    "ne:MAX_AREAKM":79.0,
    "ne:MAX_AREAMI":30.0,
    "ne:MAX_BBXMAX":56.783333,
    "ne:MAX_BBXMIN":56.608333,
    "ne:MAX_BBYMAX":24.466667,
    "ne:MAX_BBYMIN":24.3,
    "ne:MAX_NATSCA":20.0,
    "ne:MAX_PERKM":108.0,
    "ne:MAX_PERMI":67.0,
    "ne:MAX_POP10":151349,
    "ne:MAX_POP20":151349,
    "ne:MAX_POP300":0,
    "ne:MAX_POP310":0,
    "ne:MAX_POP50":0,
    "ne:MEAN_BBXC":56.692203,
    "ne:MEAN_BBYC":24.392946,
    "ne:MEGACITY":0,
    "ne:MIN_AREAKM":79.0,
    "ne:MIN_AREAMI":30.0,
    "ne:MIN_BBXMAX":56.783333,
    "ne:MIN_BBXMIN":56.608333,
    "ne:MIN_BBYMAX":24.466667,
    "ne:MIN_BBYMIN":24.3,
    "ne:MIN_PERKM":108.0,
    "ne:MIN_PERMI":67.0,
    "ne:NAME":"Suhar",
    "ne:NAMEASCII":"Suhar",
    "ne:NAMEDIFF":0,
    "ne:NATSCALE":30,
    "ne:POP1950":0,
    "ne:POP1955":0,
    "ne:POP1960":0,
    "ne:POP1965":0,
    "ne:POP1970":0,
    "ne:POP1975":0,
    "ne:POP1980":0,
    "ne:POP1985":0,
    "ne:POP1990":0,
    "ne:POP1995":0,
    "ne:POP2000":0,
    "ne:POP2005":0,
    "ne:POP2010":0,
    "ne:POP2015":0,
    "ne:POP2020":0,
    "ne:POP2025":0,
    "ne:POP2050":0,
    "ne:POP_MAX":151349,
    "ne:POP_MIN":108274,
    "ne:POP_OTHER":0,
    "ne:RANK_MAX":9,
    "ne:RANK_MIN":9,
    "ne:SCALERANK":6,
    "ne:SOV0NAME":"Oman",
    "ne:SOV_A3":"OMN",
    "ne:TIMEZONE":"Asia/Muscat",
    "ne:UN_FID":0,
    "ne:UN_LAT":0.0,
    "ne:UN_LONG":0.0,
    "ne:WORLDCITY":0,
    "qs:name":"Al Sohar",
    "qs:photos_9r":0,
    "qs:photos_sr":0,
    "qs:pop_sr":"9",
    "wof:name":"Al Sohar",
    "wof:placetype":"locality",
    "wof:population":108274
},
  "geometry": {"coordinates":[56.74681,24.3643],"type":"Point"}
}