{
  "type": "Feature",
  "properties": {
    "gn:admin1_code":"01",
    "gn:asciiname":"Wadi `Indam",
    "gn:country_code":"OM",
    "gn:dem":321,
    "gn:feature_class":"P",
    "gn:feature_code":"PPL",
    "gn:name":"W\u0101d\u012b \u2018Ind\u0101m",
    "gn:population":0,
    "gn:timezone":"Asia/Muscat",
    "iso:country":"OM",
    "name:ara_x_preferred":[
        "W\u0101d\u012b \u2018And\u0101m"
    ],
    "name:und_x_variant":[
        "W\u0101d\u012b \u2018Ind\u0101m"
    ],
    "wof:name":"Wadi `Indam",
    "wof:placetype":"locality"
},
  "geometry": {"coordinates":[57.98017,22.47905],"type":"Point"}
}