{
  "type": "Feature",
  "properties": {
    "gn:admin1_code":"02",
    "gn:asciiname":"Al Misfah",
    "gn:country_code":"OM",
    "gn:dem":206,
    "gn:feature_class":"P",
    "gn:feature_code":"PPL",
    "gn:name":"Al Misf\u0101h",
    "gn:population":0,
    "gn:timezone":"Asia/Muscat",
    "iso:country":"OM",
    "name:ara_x_preferred":[
        "Misf\u0101h"
    ],
    "name:ara_x_variant":[
        "\u0627\u0644\u0645\u0633\u0641\u0627\u0629"
    ],
    "name:und_x_variant":[
        "Mizf\u0101r",
        "Al Misf\u0101h"
    ],
    "wof:name":"Al Misfah",
    "wof:placetype":"locality"
},
  "geometry": {"coordinates":[57.4847,23.52135],"type":"Point"}
}