{
  "type": "Feature",
  "properties": {
    "gn:admin1_code":"01",
    "gn:asciiname":"Kubarah",
    "gn:country_code":"OM",
    "gn:dem":482,
    "gn:feature_class":"P",
    "gn:feature_code":"PPL",
    "gn:name":"Kub\u0101rah",
    "gn:population":0,
    "gn:timezone":"Asia/Muscat",
    "iso:country":"OM",
    "name:ara_x_preferred":[
        "\u0643\u0628\u0627\u0631\u0629"
    ],
    "name:und_x_variant":[
        "Kubara",
        "Kubb\u0101rah",
        "Kub\u0101rah"
    ],
    "wof:name":"Kubarah",
    "wof:placetype":"locality"
},
  "geometry": {"coordinates":[56.82101,23.0833],"type":"Point"}
}