{
  "type": "Feature",
  "properties": {
    "gn:admin1_code":"08",
    "gn:asciiname":"Qafa`",
    "gn:country_code":"OM",
    "gn:dem":438,
    "gn:feature_class":"P",
    "gn:feature_code":"PPL",
    "gn:name":"Qafa\u2018",
    "gn:population":0,
    "gn:timezone":"Asia/Muscat",
    "iso:country":"OM",
    "name:ara_x_preferred":[
        "\u0642\u0641\u0639"
    ],
    "name:und_x_variant":[
        "Qaf\u0101",
        "Qafa\u2019",
        "Qafa\u2018"
    ],
    "wof:name":"Qafa`",
    "wof:placetype":"locality"
},
  "geometry": {"coordinates":[53.07398000000001,17.8679],"type":"Point"}
}