{
  "type": "Feature",
  "properties": {
    "gn:admin1_code":"08",
    "gn:asciiname":"Dankor",
    "gn:country_code":"OM",
    "gn:dem":513,
    "gn:feature_class":"P",
    "gn:feature_code":"PPL",
    "gn:name":"Dankor",
    "gn:population":0,
    "gn:timezone":"Asia/Muscat",
    "iso:country":"OM",
    "wof:name":"Dankor",
    "wof:placetype":"locality"
},
  "geometry": {"coordinates":[54.13389,17.18917],"type":"Point"}
}