{
  "type": "Feature",
  "properties": {
    "gn:admin1_code":"12",
    "gn:asciiname":"Masrun",
    "gn:country_code":"OM",
    "gn:dem":388,
    "gn:feature_class":"P",
    "gn:feature_code":"PPL",
    "gn:name":"Ma\u015fr\u016bn",
    "gn:population":0,
    "gn:timezone":"Asia/Muscat",
    "iso:country":"OM",
    "name:ara_x_preferred":[
        "\u0645\u0635\u0631\u0648\u0646"
    ],
    "name:und_x_variant":[
        "Masr\u016bn",
        "Ma\u015fr\u016bn",
        "Ma\u1e63r\u016bn"
    ],
    "wof:name":"Masrun",
    "wof:placetype":"locality"
},
  "geometry": {"coordinates":[58.53312,22.64612],"type":"Point"}
}