{
  "type": "Feature",
  "properties": {
    "gn:admin1_code":"07",
    "gn:asciiname":"`Aqabat",
    "gn:country_code":"OM",
    "gn:dem":1016,
    "gn:feature_class":"P",
    "gn:feature_code":"PPL",
    "gn:name":"\u2018Aqab\u0101t",
    "gn:population":0,
    "gn:timezone":"Asia/Muscat",
    "iso:country":"OM",
    "name:ara_x_preferred":[
        "\u0639\u0642\u0628\u0627\u062a"
    ],
    "name:und_x_variant":[
        "\u2018Aqabat",
        "\u2018Aqab\u0101t",
        "\u2018Aqb\u0101t"
    ],
    "wof:name":"`Aqabat",
    "wof:placetype":"locality"
},
  "geometry": {"coordinates":[56.24144,25.81159],"type":"Point"}
}