{
  "type": "Feature",
  "properties": {
    "gn:admin1_code":"01",
    "gn:asciiname":"Masirah",
    "gn:country_code":"OM",
    "gn:dem":917,
    "gn:feature_class":"P",
    "gn:feature_code":"PPLL",
    "gn:name":"Ma\u015f\u012brah",
    "gn:population":0,
    "gn:timezone":"Asia/Muscat",
    "iso:country":"OM",
    "name:ara_x_preferred":[
        "\u0645\u0635\u064a\u0631\u0629"
    ],
    "name:und_x_variant":[
        "Ma\u015f\u012brat Nakhr",
        "Ma\u015f\u012brah",
        "Ma\u1e63\u012brah"
    ],
    "wof:name":"Masirah",
    "wof:placetype":"locality"
},
  "geometry": {"coordinates":[57.21234000000001,23.19435],"type":"Point"}
}