{
  "type": "Feature",
  "properties": {
    "gn:admin1_code":"11",
    "gn:asciiname":"Khadra'",
    "gn:country_code":"OM",
    "gn:dem":2,
    "gn:feature_class":"P",
    "gn:feature_code":"PPL",
    "gn:name":"Kha\u1e11r\u0101\u2019",
    "gn:population":0,
    "gn:timezone":"Asia/Muscat",
    "iso:country":"OM",
    "name:und_x_variant":[
        "Kha\u1e11r\u0101\u2019"
    ],
    "wof:name":"Khadra'",
    "wof:placetype":"locality"
},
  "geometry": {"coordinates":[57.39832,23.85086],"type":"Point"}
}