{
  "type": "Feature",
  "properties": {
    "iso:country":"OM",
    "qs:gn_pop":0,
    "qs:name":"\u0635\u0644\u0627\u0644\u0629 \u0627\u0644\u0634\u0631\u0642\u064a\u0629",
    "qs:name_adm0":"\u0639\u0645\u0627\u0646",
    "qs:name_adm1":"\u0638\u0641\u0627\u0631",
    "qs:photos":774,
    "qs:photos_1k":157,
    "qs:photos_9k":6,
    "qs:photos_9r":7,
    "qs:photos_all":1275,
    "qs:photos_sr":9,
    "qs:placetype":"Town",
    "qs:pop_sr":"0",
    "qs:woe_adm0":23424898,
    "wof:name":"\u0635\u0644\u0627\u0644\u0629 \u0627\u0644\u0634\u0631\u0642\u064a\u0629",
    "wof:placetype":"locality"
},
  "geometry": {"coordinates":[54.1050905,17.01696],"type":"Point"}
}