{
  "type": "Feature",
  "properties": {
    "gn:admin1_code":"08",
    "gn:asciiname":"Ajayaa",
    "gn:country_code":"OM",
    "gn:dem":634,
    "gn:feature_class":"P",
    "gn:feature_code":"PPL",
    "gn:name":"Ajayaa",
    "gn:population":0,
    "gn:timezone":"Asia/Muscat",
    "iso:country":"OM",
    "wof:name":"Ajayaa",
    "wof:placetype":"locality"
},
  "geometry": {"coordinates":[54.22787,17.19886],"type":"Point"}
}