{
  "type": "Feature",
  "properties": {
    "gn:admin1_code":"08",
    "gn:asciiname":"Hakbit",
    "gn:country_code":"OM",
    "gn:dem":613,
    "gn:feature_class":"P",
    "gn:feature_code":"PPL",
    "gn:name":"\u1e28akb\u012bt",
    "gn:population":0,
    "gn:timezone":"Asia/Muscat",
    "iso:country":"OM",
    "name:ara_x_preferred":[
        "\u062d\u0643\u0628\u064a\u062a"
    ],
    "name:und_x_variant":[
        "\u1e28akb\u012bt"
    ],
    "wof:name":"Hakbit",
    "wof:placetype":"locality"
},
  "geometry": {"coordinates":[54.03035,17.39378],"type":"Point"}
}