{
  "type": "Feature",
  "properties": {
    "gn:admin1_code":"07",
    "gn:asciiname":"Ad Danah",
    "gn:country_code":"OM",
    "gn:dem":1000,
    "gn:feature_class":"P",
    "gn:feature_code":"PPL",
    "gn:name":"Ad D\u0101nah",
    "gn:population":0,
    "gn:timezone":"Asia/Muscat",
    "iso:country":"OM",
    "name:ara_x_preferred":[
        "\u0627\u0644\u062f\u0651\u0627\u0646\u0629"
    ],
    "name:und_x_variant":[
        "Dana",
        "Ad Da\u2018nah",
        "Ad D\u0101nah"
    ],
    "wof:name":"Ad Danah",
    "wof:placetype":"locality"
},
  "geometry": {"coordinates":[56.20542,25.77013],"type":"Point"}
}