{
  "type": "Feature",
  "properties": {
    "gn:admin1_code":"07",
    "gn:asciiname":"Ad Dirhi",
    "gn:country_code":"OM",
    "gn:dem":835,
    "gn:feature_class":"P",
    "gn:feature_code":"PPL",
    "gn:name":"Ad D\u012br\u1e29\u012b",
    "gn:population":0,
    "gn:timezone":"Asia/Muscat",
    "iso:country":"OM",
    "name:ara_x_preferred":[
        "Dirh\u012b"
    ],
    "name:ara_x_variant":[
        "\u0627\u0644\u062f\u0651\u064a\u0631\u062d\u064a"
    ],
    "name:und_x_variant":[
        "Umm \u015eaghra\u012bn",
        "Ad D\u012br\u1e29\u012b",
        "Ad D\u012br\u1e25\u012b"
    ],
    "wof:name":"Ad Dirhi",
    "wof:placetype":"locality"
},
  "geometry": {"coordinates":[56.17641,25.64945],"type":"Point"}
}