{
  "type": "Feature",
  "properties": {
    "gn:admin1_code":"10",
    "gn:asciiname":"Wadiyayn",
    "gn:country_code":"OM",
    "gn:dem":426,
    "gn:feature_class":"P",
    "gn:feature_code":"PPL",
    "gn:name":"W\u0101diyayn",
    "gn:population":0,
    "gn:timezone":"Asia/Muscat",
    "iso:country":"OM",
    "name:und_x_variant":[
        "W\u0101diyayn"
    ],
    "wof:name":"Wadiyayn",
    "wof:placetype":"locality"
},
  "geometry": {"coordinates":[55.95972,24.24861],"type":"Point"}
}