{
  "type": "Feature",
  "properties": {
    "gn:admin1_code":"08",
    "gn:asciiname":"Sumhuran",
    "gn:country_code":"OM",
    "gn:dem":16,
    "gn:feature_class":"P",
    "gn:feature_code":"PPL",
    "gn:name":"Sumhuran",
    "gn:population":0,
    "gn:timezone":"Asia/Muscat",
    "iso:country":"OM",
    "wof:name":"Sumhuran",
    "wof:placetype":"locality"
},
  "geometry": {"coordinates":[54.43139,17.04083],"type":"Point"}
}