{
  "type": "Feature",
  "properties": {
    "gn:admin1_code":"01",
    "gn:asciiname":"Ar Rahdayn",
    "gn:country_code":"OM",
    "gn:dem":2142,
    "gn:feature_class":"P",
    "gn:feature_code":"PPL",
    "gn:name":"Ar Rah\u1e11ayn",
    "gn:population":0,
    "gn:timezone":"Asia/Muscat",
    "iso:country":"OM",
    "name:ara_x_preferred":[
        "\u0627\u0644\u0631\u0647\u0636\u064a\u0646"
    ],
    "name:und_x_variant":[
        "Rukh\u1e11ayn",
        "Ar Rah\u1e11ayn",
        "Ar Rah\u1e0dayn"
    ],
    "wof:name":"Ar Rahdayn",
    "wof:placetype":"locality"
},
  "geometry": {"coordinates":[57.56822,23.12548],"type":"Point"}
}