{
  "type": "Feature",
  "properties": {
    "gn:admin1_code":"08",
    "gn:asciiname":"Zaynah",
    "gn:country_code":"OM",
    "gn:dem":502,
    "gn:feature_class":"P",
    "gn:feature_code":"PPL",
    "gn:name":"Zaynah",
    "gn:population":0,
    "gn:timezone":"Asia/Muscat",
    "iso:country":"OM",
    "name:ara_x_preferred":[
        "\u0632\u064a\u0646\u0629"
    ],
    "wof:name":"Zaynah",
    "wof:placetype":"locality"
},
  "geometry": {"coordinates":[52.63276,17.85959],"type":"Point"}
}