{
  "type": "Feature",
  "properties": {
    "gn:admin1_code":"11",
    "gn:asciiname":"Laslat",
    "gn:country_code":"OM",
    "gn:dem":715,
    "gn:feature_class":"P",
    "gn:feature_code":"PPL",
    "gn:name":"Lasl\u0101t",
    "gn:population":0,
    "gn:timezone":"Asia/Muscat",
    "iso:country":"OM",
    "name:ara_x_preferred":[
        "Al Isl\u0101t"
    ],
    "name:ara_x_variant":[
        "\u0644\u0633\u0644\u0627\u062a"
    ],
    "name:und_x_variant":[
        "Lislat",
        "Lasl\u0101t"
    ],
    "wof:name":"Laslat",
    "wof:placetype":"locality"
},
  "geometry": {"coordinates":[56.7535,23.70275],"type":"Point"}
}