{
  "type": "Feature",
  "properties": {
    "gn:admin1_code":"02",
    "gn:asciiname":"Al Hijar",
    "gn:country_code":"OM",
    "gn:dem":745,
    "gn:feature_class":"P",
    "gn:feature_code":"PPL",
    "gn:name":"Al Hij\u0101r",
    "gn:population":0,
    "gn:timezone":"Asia/Muscat",
    "iso:country":"OM",
    "name:ara_x_preferred":[
        "\u0627\u0644\u0647\u062c\u0627\u0631"
    ],
    "name:und_x_variant":[
        "H\u012bl \u1e28ij\u0101r",
        "Hayhar H\u012bl \u1e28ij\u0101r",
        "\u1e28ayjar",
        "Al Hij\u0101r"
    ],
    "wof:name":"Al Hijar",
    "wof:placetype":"locality"
},
  "geometry": {"coordinates":[57.57417,23.18806],"type":"Point"}
}