{
  "type": "Feature",
  "properties": {
    "gn:country":"OM",
    "gn:fcode":"PPL",
    "gn:population":16599,
    "iso:country":"OM",
    "name:ara_x_preferred":[
        "\u0648\u0644\u0627\u064a\u0629 \u064a\u0646\u0642\u0644"
    ],
    "name:ces_x_preferred":[
        "Jankul"
    ],
    "name:deu_x_preferred":[
        "Yanqul"
    ],
    "name:fas_x_preferred":[
        "\u06cc\u0646\u0642\u0644"
    ],
    "qs:name":"Yanqul",
    "qs:photos_9r":0,
    "qs:photos_sr":0,
    "qs:pop_sr":"6",
    "wof:name":"Yanqul",
    "wof:placetype":"locality",
    "wof:population":16599
},
  "geometry": {"coordinates":[56.55008,23.59051],"type":"Point"}
}