{
  "type": "Feature",
  "properties": {
    "gn:country":"OM",
    "gn:fcode":"PPL",
    "gn:pop":16599,
    "iso:country":"OM",
    "qs:name":"Yanqul",
    "qs:photos_9r":0,
    "qs:photos_sr":0,
    "qs:pop_sr":"6",
    "wof:name":"Yanqul",
    "wof:placetype":"locality",
    "wof:population":16599
},
  "geometry": {"coordinates":[56.55008,23.59051],"type":"Point"}
}