{
  "type": "Feature",
  "properties": {
    "gn:admin1_code":"07",
    "gn:asciiname":"Sima",
    "gn:cc2":"OM",
    "gn:country_code":"OM",
    "gn:dem":136,
    "gn:feature_class":"P",
    "gn:feature_code":"PPL",
    "gn:name":"S\u012bm\u0101",
    "gn:population":0,
    "gn:timezone":"Asia/Muscat",
    "iso:country":"OM",
    "name:ara_x_preferred":[
        "S\u012bm\u0101"
    ],
    "name:und_x_variant":[
        "S\u012bmah"
    ],
    "wof:name":"Sima",
    "wof:placetype":"locality"
},
  "geometry": {"coordinates":[56.30556,26.06444],"type":"Point"}
}