{
  "type": "Feature",
  "properties": {
    "gn:admin1_code":"01",
    "gn:asciiname":"Masirat ar Rawajih",
    "gn:country_code":"OM",
    "gn:dem":1143,
    "gn:feature_class":"P",
    "gn:feature_code":"PPL",
    "gn:name":"Ma\u015f\u012brat ar Raw\u0101ji\u1e29",
    "gn:population":0,
    "gn:timezone":"Asia/Muscat",
    "iso:country":"OM",
    "name:ara_x_preferred":[
        "\u0645\u0635\u064a\u0631\u0629 \u0627\u0644\u0631\u0651\u0648\u0627\u062c\u062d"
    ],
    "name:und_x_variant":[
        "Ma\u015f\u012brat Ruw\u0101ji\u1e29",
        "Ma\u015f\u012brat ar Raw\u0101ji\u1e29",
        "Ma\u1e63\u012brat at Raw\u0101ji\u1e25"
    ],
    "wof:name":"Masirat ar Rawajih",
    "wof:placetype":"locality"
},
  "geometry": {"coordinates":[57.67008000000001,23.04349],"type":"Point"}
}