{
  "type": "Feature",
  "properties": {
    "gn:admin1_code":"01",
    "gn:asciiname":"As Sayh",
    "gn:country_code":"OM",
    "gn:dem":695,
    "gn:feature_class":"P",
    "gn:feature_code":"PPL",
    "gn:name":"As Say\u1e29",
    "gn:population":0,
    "gn:timezone":"Asia/Muscat",
    "iso:country":"OM",
    "name:ara_x_preferred":[
        "\u0627\u0644\u0633\u0651\u064a\u062d"
    ],
    "name:und_x_variant":[
        "Say\u1e29",
        "As Say\u1e29",
        "As Say\u1e25"
    ],
    "wof:name":"As Sayh",
    "wof:placetype":"locality"
},
  "geometry": {"coordinates":[58.01145,23.02745],"type":"Point"}
}