{
  "type": "Feature",
  "properties": {
    "gn:admin1_code":"11",
    "gn:asciiname":"At Turayf",
    "gn:country_code":"OM",
    "gn:dem":16,
    "gn:feature_class":"P",
    "gn:feature_code":"PPL",
    "gn:name":"A\u0163 \u0162urayf",
    "gn:population":0,
    "gn:timezone":"Asia/Muscat",
    "iso:country":"OM",
    "name:ara_x_preferred":[
        "\u0627\u0644\u0637\u0651\u0631\u064a\u0641"
    ],
    "name:und_x_variant":[
        "\u0162ar\u012bf",
        "A\u0163 \u0162urayf",
        "A\u1e6d \u1e6curayf"
    ],
    "wof:name":"At Turayf",
    "wof:placetype":"locality"
},
  "geometry": {"coordinates":[57.6216,23.74641],"type":"Point"}
}