{
  "type": "Feature",
  "properties": {
    "gn:admin1_code":"01",
    "gn:asciiname":"Al Huwir",
    "gn:country_code":"OM",
    "gn:dem":1816,
    "gn:feature_class":"P",
    "gn:feature_code":"PPL",
    "gn:name":"Al \u1e28uw\u012br",
    "gn:population":0,
    "gn:timezone":"Asia/Muscat",
    "iso:country":"OM",
    "name:ara_x_preferred":[
        "Al \u1e28uw\u012br"
    ],
    "wof:name":"Al Huwir",
    "wof:placetype":"locality"
},
  "geometry": {"coordinates":[57.55,23.07417],"type":"Point"}
}