{
  "type": "Feature",
  "properties": {
    "gn:admin1_code":"04",
    "gn:asciiname":"Khawr al Jaramah",
    "gn:country_code":"OM",
    "gn:dem":5,
    "gn:feature_class":"P",
    "gn:feature_code":"PPL",
    "gn:name":"Khawr al Jar\u0101mah",
    "gn:population":0,
    "gn:timezone":"Asia/Muscat",
    "iso:country":"OM",
    "name:und_x_variant":[
        "Khawr al Jar\u0101mah"
    ],
    "wof:name":"Khawr al Jaramah",
    "wof:placetype":"locality"
},
  "geometry": {"coordinates":[59.71576,22.49387],"type":"Point"}
}