{
  "type": "Feature",
  "properties": {
    "gn:admin1_code":"01",
    "gn:asciiname":"Mazra` al Ghaf",
    "gn:country_code":"OM",
    "gn:dem":610,
    "gn:feature_class":"P",
    "gn:feature_code":"PPL",
    "gn:name":"Mazra\u2018 al Gh\u0101f",
    "gn:population":0,
    "gn:timezone":"Asia/Muscat",
    "iso:country":"OM",
    "name:und_x_variant":[
        "Mazra\u2018 al Gh\u0101f"
    ],
    "wof:name":"Mazra` al Ghaf",
    "wof:placetype":"locality"
},
  "geometry": {"coordinates":[58.23163,23.23425],"type":"Point"}
}