{
  "type": "Feature",
  "properties": {
    "gn:admin1_code":"10",
    "gn:asciiname":"Al Khubbayn",
    "gn:country_code":"OM",
    "gn:dem":639,
    "gn:feature_class":"P",
    "gn:feature_code":"PPL",
    "gn:name":"Al Khubbayn",
    "gn:population":0,
    "gn:timezone":"Asia/Muscat",
    "iso:country":"OM",
    "name:ara_x_preferred":[
        "\u0627\u0644\u062e\u0628\u0651\u064a\u0646"
    ],
    "name:und_x_variant":[
        "Kliatudh",
        "Khotudh",
        "Khatudh",
        "Khafudh",
        "Kha\u0163wah",
        "Al Khubbayn",
        "Al Khabbayn",
        "Khubayn",
        "Khubar",
        "Khubain",
        "Khabbayn",
        "Al Khubayn"
    ],
    "wof:name":"Al Khubbayn",
    "wof:placetype":"locality"
},
  "geometry": {"coordinates":[56.13043,24.31027000000001],"type":"Point"}
}