{
  "type": "Feature",
  "properties": {
    "gn:admin1_code":"12",
    "gn:asciiname":"Al Qillah",
    "gn:country_code":"OM",
    "gn:dem":451,
    "gn:feature_class":"P",
    "gn:feature_code":"PPL",
    "gn:name":"Al Qillah",
    "gn:population":0,
    "gn:timezone":"Asia/Muscat",
    "iso:country":"OM",
    "name:ara_x_preferred":[
        "\u0627\u0644\u0642\u0644\u0629"
    ],
    "name:und_x_variant":[
        "Ghayl",
        "Al Qillah"
    ],
    "wof:name":"Al Qillah",
    "wof:placetype":"locality"
},
  "geometry": {"coordinates":[58.54691999999999,22.69318],"type":"Point"}
}