{
  "type": "Feature",
  "properties": {
    "gn:admin1_code":"01",
    "gn:asciiname":"Disli",
    "gn:country_code":"OM",
    "gn:dem":468,
    "gn:feature_class":"P",
    "gn:feature_code":"PPL",
    "gn:name":"D\u012bsl\u012b",
    "gn:population":0,
    "gn:timezone":"Asia/Muscat",
    "iso:country":"OM",
    "name:ara_x_preferred":[
        "Disl\u012b"
    ],
    "name:ara_x_variant":[
        "\u062f\u064a\u0633\u0644\u064a"
    ],
    "name:und_x_variant":[
        "D\u012bsl\u012b"
    ],
    "wof:name":"Disli",
    "wof:placetype":"locality"
},
  "geometry": {"coordinates":[57.22417,23.51861],"type":"Point"}
}