{
  "type": "Feature",
  "properties": {
    "gn:admin1_code":"07",
    "gn:asciiname":"Marwani",
    "gn:country_code":"OM",
    "gn:dem":6,
    "gn:feature_class":"P",
    "gn:feature_code":"PPL",
    "gn:name":"Marwani",
    "gn:population":0,
    "gn:timezone":"Asia/Muscat",
    "iso:country":"OM",
    "wof:name":"Marwani",
    "wof:placetype":"locality"
},
  "geometry": {"coordinates":[56.44083000000001,26.31083],"type":"Point"}
}