{
  "type": "Feature",
  "properties": {
    "iso:country":"OM",
    "name:deu_x_preferred":[
        "Ar-Rusail"
    ],
    "name:dut_x_preferred":[
        "Rusayl"
    ],
    "name:eng_x_preferred":[
        "Rusayl"
    ],
    "name:fra_x_preferred":[
        "Rusayl"
    ],
    "name:fre_x_preferred":[
        "Rusayl"
    ],
    "name:ger_x_preferred":[
        "Ar-Rusail"
    ],
    "name:nno_x_preferred":[
        "Rusayl"
    ],
    "name:unk_x_variant":[
        "Rusayl"
    ],
    "qs:gn_country":"OM",
    "qs:gn_fcode":"PPL",
    "qs:gn_pop":0,
    "qs:name":"Rusail",
    "qs:name_adm0":"\u0639\u0645\u0627\u0646",
    "qs:name_adm1":"\u0645\u0633\u0642\u0637",
    "qs:photos":15,
    "qs:photos_1k":3,
    "qs:photos_9k":1,
    "qs:photos_9r":1,
    "qs:photos_all":15,
    "qs:photos_sr":1,
    "qs:placetype":"Town",
    "qs:pop_sr":"0",
    "qs:woe_adm0":23424898,
    "wd:wordcount":21,
    "wof:name":"Rusail",
    "wof:placetype":"locality"
},
  "geometry": {"coordinates":[58.19055,23.53658],"type":"Point"}
}