{
  "type": "Feature",
  "properties": {
    "gn:admin1_code":"07",
    "gn:asciiname":"Khuzaynuh",
    "gn:country_code":"OM",
    "gn:dem":95,
    "gn:feature_class":"P",
    "gn:feature_code":"PPL",
    "gn:name":"Khuzayn\u016bh",
    "gn:population":0,
    "gn:timezone":"Asia/Muscat",
    "iso:country":"OM",
    "name:ara_x_preferred":[
        "\u062e\u0632\u064a\u0646\u0648\u0647"
    ],
    "name:und_x_variant":[
        "Hayr Khazinaw",
        "Khuzayn\u016bh",
        "Khaz\u012bn\u016bh"
    ],
    "wof:name":"Khuzaynuh",
    "wof:placetype":"locality"
},
  "geometry": {"coordinates":[56.25851,26.09493],"type":"Point"}
}