{
  "type": "Feature",
  "properties": {
    "gn:admin1_code":"01",
    "gn:asciiname":"Ad Dahiyah",
    "gn:country_code":"OM",
    "gn:dem":689,
    "gn:feature_class":"P",
    "gn:feature_code":"PPL",
    "gn:name":"Ad Da\u1e29\u012byah",
    "gn:population":0,
    "gn:timezone":"Asia/Muscat",
    "iso:country":"OM",
    "name:ara_x_preferred":[
        "\u0627\u0644\u062f\u0651\u062d\u064a\u0629"
    ],
    "name:und_x_variant":[
        "D\u0101hiyah",
        "Ad Da\u1e29\u012byah",
        "Ad Da\u1e25yah"
    ],
    "wof:name":"Ad Dahiyah",
    "wof:placetype":"locality"
},
  "geometry": {"coordinates":[58.1537,23.08307000000001],"type":"Point"}
}