{
  "type": "Feature",
  "properties": {
    "iso:country":"OM",
    "name:ara_x_preferred":[
        "\u062f\u0627\u0631\u0633\u064a\u062a"
    ],
    "name:unk_x_variant":[
        "Mars\u00e1 D\u0101rsayt"
    ],
    "qs:gn_country":"OM",
    "qs:gn_fcode":"PPL",
    "qs:gn_pop":0,
    "qs:name":"\u062f\u0627\u0631\u0633\u064a\u062a",
    "qs:name_adm0":"\u0639\u0645\u0627\u0646",
    "qs:name_adm1":"\u0645\u0633\u0642\u0637",
    "qs:photos":2,
    "qs:photos_1k":1,
    "qs:photos_9k":1,
    "qs:photos_9r":1,
    "qs:photos_all":2,
    "qs:photos_sr":1,
    "qs:placetype":"Suburb",
    "qs:pop_sr":"0",
    "qs:woe_adm0":23424898,
    "wof:name":"\u062f\u0627\u0631\u0633\u064a\u062a",
    "wof:placetype":"neighbourhood"
},
  "geometry": {"coordinates":[58.53887,23.62241],"type":"Point"}
}