{
  "type": "Feature",
  "properties": {
    "gn:admin1_code":"11",
    "gn:asciiname":"Qufays",
    "gn:country_code":"OM",
    "gn:dem":767,
    "gn:feature_class":"P",
    "gn:feature_code":"PPL",
    "gn:name":"Qufay\u015f",
    "gn:population":0,
    "gn:timezone":"Asia/Muscat",
    "iso:country":"OM",
    "name:ara_x_preferred":[
        "\u0642\u0641\u064a\u0635"
    ],
    "name:und_x_variant":[
        "Al Qufay\u015f",
        "Qufay\u015f",
        "Qufay\u1e63"
    ],
    "wof:name":"Qufays",
    "wof:placetype":"locality"
},
  "geometry": {"coordinates":[56.43753,23.95651],"type":"Point"}
}