{
  "type": "Feature",
  "properties": {
    "gn:admin1_code":"09",
    "gn:asciiname":"Al Khubayb",
    "gn:country_code":"OM",
    "gn:dem":405,
    "gn:feature_class":"P",
    "gn:feature_code":"PPL",
    "gn:name":"Al Khubayb",
    "gn:population":0,
    "gn:timezone":"Asia/Muscat",
    "iso:country":"OM",
    "name:ara_x_preferred":[
        "\u0627\u0644\u062e\u0628\u064a\u0628"
    ],
    "wof:name":"Al Khubayb",
    "wof:placetype":"locality"
},
  "geometry": {"coordinates":[56.24053000000001,23.66846],"type":"Point"}
}