{
  "type": "Feature",
  "properties": {
    "gn:admin1_code":"06",
    "gn:asciiname":"Mazra` Ghulaylah",
    "gn:country_code":"OM",
    "gn:dem":278,
    "gn:feature_class":"P",
    "gn:feature_code":"PPL",
    "gn:name":"Mazra\u2018 Ghulaylah",
    "gn:population":0,
    "gn:timezone":"Asia/Muscat",
    "iso:country":"OM",
    "name:und_x_variant":[
        "Mazra\u2018 Ghulaylah"
    ],
    "wof:name":"Mazra` Ghulaylah",
    "wof:placetype":"locality"
},
  "geometry": {"coordinates":[58.29704,23.45631],"type":"Point"}
}