{
  "type": "Feature",
  "properties": {
    "gn:admin1_code":"11",
    "gn:asciiname":"Wayt",
    "gn:country_code":"OM",
    "gn:dem":645,
    "gn:feature_class":"P",
    "gn:feature_code":"PPL",
    "gn:name":"Wayt",
    "gn:population":0,
    "gn:timezone":"Asia/Muscat",
    "iso:country":"OM",
    "name:ara_x_preferred":[
        "\u0648\u064a\u062a"
    ],
    "wof:name":"Wayt",
    "wof:placetype":"locality"
},
  "geometry": {"coordinates":[56.52351,23.90374],"type":"Point"}
}