{
  "type": "Feature",
  "properties": {
    "gn:admin1_code":"06",
    "gn:asciiname":"Al Jurayfat",
    "gn:country_code":"OM",
    "gn:dem":210,
    "gn:feature_class":"P",
    "gn:feature_code":"PPL",
    "gn:name":"Al Jurayf\u0101t",
    "gn:population":0,
    "gn:timezone":"Asia/Muscat",
    "iso:country":"OM",
    "name:ara_x_preferred":[
        "\u0627\u0644\u062c\u0631\u064a\u0641\u0627\u062a"
    ],
    "name:und_x_variant":[
        "Al Jurayf\u0101t",
        "Al Jirayf\u0101t"
    ],
    "wof:name":"Al Jurayfat",
    "wof:placetype":"locality"
},
  "geometry": {"coordinates":[58.70928000000001,23.32691],"type":"Point"}
}