{
  "type": "Feature",
  "properties": {
    "gn:admin1_code":"08",
    "gn:asciiname":"Bal'as`ad",
    "gn:country_code":"OM",
    "gn:dem":673,
    "gn:feature_class":"P",
    "gn:feature_code":"PPL",
    "gn:name":"Bal\u2019as\u2018ad",
    "gn:population":0,
    "gn:timezone":"Asia/Muscat",
    "iso:country":"OM",
    "name:ara_x_preferred":[
        "\u0628\u0627\u0644\u0623\u0633\u0639\u062f"
    ],
    "name:und_x_variant":[
        "Bal\u2019as\u2018ad",
        "Balas\u2018ad"
    ],
    "wof:name":"Bal'as`ad",
    "wof:placetype":"locality"
},
  "geometry": {"coordinates":[53.14913000000001,16.69756],"type":"Point"}
}