{
  "type": "Feature",
  "properties": {
    "gn:admin1_code":"04",
    "gn:asciiname":"Safaij",
    "gn:country_code":"OM",
    "gn:dem":6,
    "gn:feature_class":"P",
    "gn:feature_code":"PPL",
    "gn:name":"Safaij",
    "gn:population":0,
    "gn:timezone":"Asia/Muscat",
    "iso:country":"OM",
    "name:und_x_variant":[
        "\u015eaf\u0101\u2019iq"
    ],
    "wof:name":"Safaij",
    "wof:placetype":"locality"
},
  "geometry": {"coordinates":[58.76943000000001,20.43215],"type":"Point"}
}