{
  "type": "Feature",
  "properties": {
    "iso:country":"OM",
    "name:ara_x_preferred":[
        "\u0645\u062f\u064a\u0646\u0629 \u0627\u0644\u0633\u0644\u0637\u0627\u0646 \u0642\u0627\u0628\u0648\u0633"
    ],
    "name:eng_x_preferred":[
        "Madinat Al Sultan Qaboos"
    ],
    "name:eng_x_variant":[
        "Madinat Al Sultan Qaboos"
    ],
    "name:unk_x_variant":[
        "\u0645\u062f\u064a\u0646\u0629 \u0627\u0644\u0633\u0644\u0637\u0627\u0646 \u0642\u0627\u0628\u0648\u0633"
    ],
    "qs:gn_adm0_cc":"OM",
    "qs:gn_local":287286,
    "qs:gn_nam_loc":"\u0645\u0633\u0642\u0637, \u0645\u0633\u0642\u0637, \u0645\u0633\u0642\u0637, OM",
    "qs:gn_namadm1":"06",
    "qs:local_max":1860,
    "qs:local_sum":6504,
    "qs:localhoods":14,
    "qs:name":"\u0645\u062f\u064a\u0646\u0629 \u0627\u0644\u0633\u0644\u0637\u0627\u0646 \u0642\u0627\u0628\u0648\u0633",
    "qs:name_adm0":"\u0639\u0645\u0627\u0646",
    "qs:name_adm1":"\u0645\u0633\u0642\u0637",
    "qs:name_adm2":"\u0645\u0637\u0631\u062d",
    "qs:name_en":"Madinat Al Sultan Qaboos",
    "qs:name_local":"\u0645\u0633\u0642\u0637",
    "qs:photo_max":46,
    "qs:photo_sum":147,
    "qs:placetype":"Suburb",
    "qs:quad_count":24,
    "qs:woe_adm0":23424898,
    "qs:woe_adm1":2346260,
    "qs:woe_adm2":55927054,
    "qs:woe_lau":0,
    "qs:woe_local":2268284,
    "qs:woe_ver":"7.10.0",
    "wof:lang":[
        "ara"
    ],
    "wof:name":"\u0645\u062f\u064a\u0646\u0629 \u0627\u0644\u0633\u0644\u0637\u0627\u0646 \u0642\u0627\u0628\u0648\u0633",
    "wof:placetype":"neighbourhood"
},
  "geometry": {"coordinates":[58.457612,23.601074],"type":"Point"}
}