{
  "type": "Feature",
  "properties": {
    "gn:admin1_code":"08",
    "gn:asciiname":"Masqrat",
    "gn:country_code":"OM",
    "gn:dem":950,
    "gn:feature_class":"P",
    "gn:feature_code":"PPL",
    "gn:name":"M\u0101sqr\u0101t",
    "gn:population":0,
    "gn:timezone":"Asia/Muscat",
    "iso:country":"OM",
    "name:ara_x_preferred":[
        "M\u0101sqr\u0101t"
    ],
    "wof:name":"Masqrat",
    "wof:placetype":"locality"
},
  "geometry": {"coordinates":[53.94655,17.1148],"type":"Point"}
}