{
  "type": "Feature",
  "properties": {
    "gn:admin1_code":"10",
    "gn:asciiname":"Bani Ka`b",
    "gn:country_code":"OM",
    "gn:dem":606,
    "gn:feature_class":"P",
    "gn:feature_code":"PPL",
    "gn:name":"Ban\u012b Ka\u2018b",
    "gn:population":0,
    "gn:timezone":"Asia/Muscat",
    "iso:country":"OM",
    "name:und_x_variant":[
        "Al Hothera",
        "Ban\u012b Ka\u2018b"
    ],
    "wof:name":"Bani Ka`b",
    "wof:placetype":"locality"
},
  "geometry": {"coordinates":[56.08333,24.53333],"type":"Point"}
}