{
  "type": "Feature",
  "properties": {
    "gn:admin1_code":"10",
    "gn:asciiname":"Abu Badi",
    "gn:country_code":"OM",
    "gn:dem":441,
    "gn:feature_class":"P",
    "gn:feature_code":"PPL",
    "gn:name":"Ab\u016b B\u0101d\u012b",
    "gn:population":0,
    "gn:timezone":"Asia/Muscat",
    "iso:country":"OM",
    "name:ara_x_preferred":[
        "B\u016bb\u0101d\u012b"
    ],
    "name:ara_x_variant":[
        "\u0623\u0628\u0648 \u0628\u0627\u062f\u064a"
    ],
    "name:und_x_variant":[
        "Ab\u016b B\u0101d\u012b"
    ],
    "wof:name":"Abu Badi",
    "wof:placetype":"locality"
},
  "geometry": {"coordinates":[55.95934000000001,24.83542000000001],"type":"Point"}
}