{
  "type": "Feature",
  "properties": {
    "gn:admin1_code":"06",
    "gn:asciiname":"Ad Dab`ani",
    "gn:country_code":"OM",
    "gn:dem":191,
    "gn:feature_class":"P",
    "gn:feature_code":"PPL",
    "gn:name":"A\u1e11 \u1e10ab\u2018\u0101n\u012b",
    "gn:population":0,
    "gn:timezone":"Asia/Muscat",
    "iso:country":"OM",
    "name:ara_x_preferred":[
        "\u0627\u0644\u0636\u0628\u0639\u0627\u0646\u064a"
    ],
    "name:und_x_variant":[
        "A\u1e11 \u1e10ab\u2018\u0101n\u012b"
    ],
    "wof:name":"Ad Dab`ani",
    "wof:placetype":"locality"
},
  "geometry": {"coordinates":[58.71742,23.31291],"type":"Point"}
}