{
  "type": "Feature",
  "properties": {
    "gn:admin1_code":"11",
    "gn:asciiname":"As Safa",
    "gn:country_code":"OM",
    "gn:dem":533,
    "gn:feature_class":"P",
    "gn:feature_code":"PPL",
    "gn:name":"A\u015f \u015eaf\u0101",
    "gn:population":0,
    "gn:timezone":"Asia/Muscat",
    "iso:country":"OM",
    "name:ara_x_preferred":[
        "\u0627\u0644\u0635\u0641\u0627"
    ],
    "name:und_x_variant":[
        "\u015eaf\u0101\u2019",
        "A\u015f \u015eaf\u0101",
        "A\u1e63 \u1e62af\u0101"
    ],
    "wof:name":"As Safa",
    "wof:placetype":"locality"
},
  "geometry": {"coordinates":[56.69615,23.79237],"type":"Point"}
}