{
  "type": "Feature",
  "properties": {
    "gn:admin1_code":"11",
    "gn:asciiname":"Ash Shuwaymirah",
    "gn:country_code":"OM",
    "gn:dem":435,
    "gn:feature_class":"P",
    "gn:feature_code":"PPL",
    "gn:name":"Ash Shuwaymirah",
    "gn:population":0,
    "gn:timezone":"Asia/Muscat",
    "iso:country":"OM",
    "name:ara_x_preferred":[
        "\u0627\u0644\u0634\u0651\u0648\u064a\u0645\u0631\u0629"
    ],
    "name:und_x_variant":[
        "Shuwaymirah",
        "Ash Shuwaymirah",
        "Ash Shiwaymrah"
    ],
    "wof:name":"Ash Shuwaymirah",
    "wof:placetype":"locality"
},
  "geometry": {"coordinates":[56.3263,24.37114],"type":"Point"}
}