{
  "type": "Feature",
  "properties": {
    "gn:admin1_code":"01",
    "gn:asciiname":"Al Buwayda'",
    "gn:country_code":"OM",
    "gn:dem":794,
    "gn:feature_class":"P",
    "gn:feature_code":"PPL",
    "gn:name":"Al Buway\u1e11\u0101\u2019",
    "gn:population":0,
    "gn:timezone":"Asia/Muscat",
    "iso:country":"OM",
    "name:ara_x_preferred":[
        "\u0627\u0644\u0628\u0648\u064a\u0636\u0627\u0621"
    ],
    "name:und_x_variant":[
        "Al Buwayz\u0327\u0101",
        "Al Buway\u1e11\u0101\u2019",
        "Al Buway\u1e0d\u0101\u2019"
    ],
    "wof:name":"Al Buwayda'",
    "wof:placetype":"locality"
},
  "geometry": {"coordinates":[57.95591999999999,23.05398],"type":"Point"}
}