{
  "type": "Feature",
  "properties": {
    "gn:admin1_code":"01",
    "gn:asciiname":"Al Huwayb",
    "gn:country_code":"OM",
    "gn:dem":1196,
    "gn:feature_class":"P",
    "gn:feature_code":"PPL",
    "gn:name":"Al Huwayb",
    "gn:population":0,
    "gn:timezone":"Asia/Muscat",
    "iso:country":"OM",
    "name:ara_x_preferred":[
        "Al \u1e28uw\u012bb"
    ],
    "name:ara_x_variant":[
        "\u0627\u0644\u0647\u0648\u064a\u0628"
    ],
    "name:und_x_variant":[
        "Al Hiwayb"
    ],
    "wof:name":"Al Huwayb",
    "wof:placetype":"locality"
},
  "geometry": {"coordinates":[57.33848,23.21032],"type":"Point"}
}