{
  "type": "Feature",
  "properties": {
    "gn:admin1_code":"10",
    "gn:asciiname":"Ar Ramthah",
    "gn:country_code":"OM",
    "gn:dem":607,
    "gn:feature_class":"P",
    "gn:feature_code":"PPL",
    "gn:name":"Ar Ramthah",
    "gn:population":0,
    "gn:timezone":"Asia/Muscat",
    "iso:country":"OM",
    "name:ara_x_preferred":[
        "\u0627\u0644\u0631\u0651\u0645\u062b\u0629"
    ],
    "name:und_x_variant":[
        "Rimthah",
        "Ar Ramthah"
    ],
    "wof:name":"Ar Ramthah",
    "wof:placetype":"locality"
},
  "geometry": {"coordinates":[56.06763,24.46545],"type":"Point"}
}