{
  "type": "Feature",
  "properties": {
    "iso:country":"OM",
    "name:ara_x_preferred":[
        "\u0646\u062e\u0644"
    ],
    "name:eng_x_preferred":[
        "Nakhel"
    ],
    "qs:gn_pop":0,
    "qs:name":"\u0646\u062e\u0644",
    "qs:name_adm0":"\u0639\u0645\u0627\u0646",
    "qs:name_adm1":"\u0627\u0644\u0628\u0627\u0637\u0646\u0629",
    "qs:photos":229,
    "qs:photos_1k":46,
    "qs:photos_9k":1,
    "qs:photos_9r":4,
    "qs:photos_all":229,
    "qs:photos_sr":4,
    "qs:placetype":"Town",
    "qs:pop_sr":"0",
    "qs:woe_adm0":23424898,
    "wof:name":"Nakhel",
    "wof:placetype":"locality"
},
  "geometry": {"coordinates":[57.829284,23.394939],"type":"Point"}
}