{
  "type": "Feature",
  "properties": {
    "gn:admin1_code":"11",
    "gn:asciiname":"Al Fujayj",
    "gn:country_code":"OM",
    "gn:dem":244,
    "gn:feature_class":"P",
    "gn:feature_code":"PPL",
    "gn:name":"Al Fujayj",
    "gn:population":0,
    "gn:timezone":"Asia/Muscat",
    "iso:country":"OM",
    "name:ara_x_preferred":[
        "\u0627\u0644\u0641\u062c\u064a\u062c"
    ],
    "name:und_x_variant":[
        "Fujayj",
        "Al Fujayj",
        "Al Fijayj"
    ],
    "wof:name":"Al Fujayj",
    "wof:placetype":"locality"
},
  "geometry": {"coordinates":[56.75491,23.91965],"type":"Point"}
}