{
  "type": "Feature",
  "properties": {
    "gn:admin1_code":"11",
    "gn:asciiname":"Burj Al Khamis",
    "gn:country_code":"OM",
    "gn:dem":13,
    "gn:feature_class":"P",
    "gn:feature_code":"PPL",
    "gn:name":"Burj \u0100l Kham\u012bs",
    "gn:population":0,
    "gn:timezone":"Asia/Muscat",
    "iso:country":"OM",
    "name:ara_x_preferred":[
        "\u0628\u0631\u062c \u0622\u0644 \u062e\u0645\u064a\u0633"
    ],
    "name:und_x_variant":[
        "S\u016br \u0100l B\u016b Kham\u012bs",
        "Burj \u0100l Kham\u012bs"
    ],
    "wof:name":"Burj Al Khamis",
    "wof:placetype":"locality"
},
  "geometry": {"coordinates":[57.63988000000001,23.75577],"type":"Point"}
}