{
  "type": "Feature",
  "properties": {
    "gn:admin1_code":"09",
    "gn:asciiname":"Hardi",
    "gn:country_code":"OM",
    "gn:dem":427,
    "gn:feature_class":"P",
    "gn:feature_code":"PPL",
    "gn:name":"\u1e28ar\u1e11\u012b",
    "gn:population":0,
    "gn:timezone":"Asia/Muscat",
    "iso:country":"OM",
    "name:ara_x_preferred":[
        "\u062d\u0631\u0636\u064a"
    ],
    "name:und_x_variant":[
        "Hardh\u012b",
        "\u1e28ar\u1e11\u012b",
        "\u1e24ar\u1e0d\u012b"
    ],
    "wof:name":"Hardi",
    "wof:placetype":"locality"
},
  "geometry": {"coordinates":[56.32578,23.53464],"type":"Point"}
}