{
  "type": "Feature",
  "properties": {
    "gn:admin1_code":"01",
    "gn:asciiname":"Kahf al Hamir",
    "gn:country_code":"OM",
    "gn:dem":1701,
    "gn:feature_class":"P",
    "gn:feature_code":"PPL",
    "gn:name":"Kahf al \u1e28am\u012br",
    "gn:population":0,
    "gn:timezone":"Asia/Muscat",
    "iso:country":"OM",
    "name:ara_x_preferred":[
        "\u0643\u0647\u0641 \u0627\u0644\u062d\u0645\u064a\u0631"
    ],
    "name:und_x_variant":[
        "Kahf al \u1e28am\u012br",
        "Kahf al \u1e24am\u012br"
    ],
    "wof:name":"Kahf al Hamir",
    "wof:placetype":"locality"
},
  "geometry": {"coordinates":[57.55483,23.08856],"type":"Point"}
}