{
  "type": "Feature",
  "properties": {
    "gn:admin1_code":"08",
    "gn:asciiname":"Khadrafi",
    "gn:country_code":"OM",
    "gn:dem":686,
    "gn:feature_class":"P",
    "gn:feature_code":"PPL",
    "gn:name":"Kha\u1e11raf\u012b",
    "gn:population":0,
    "gn:timezone":"Asia/Muscat",
    "iso:country":"OM",
    "name:ara_x_preferred":[
        "\u062e\u0636\u0631\u0641\u064a"
    ],
    "name:und_x_variant":[
        "Kha\u1e11raf\u012b",
        "Kha\u1e0draf\u012b"
    ],
    "wof:name":"Khadrafi",
    "wof:placetype":"locality"
},
  "geometry": {"coordinates":[53.15934,16.69603],"type":"Point"}
}