{
  "type": "Feature",
  "properties": {
    "gn:admin1_code":"03",
    "gn:asciiname":"Ghadw",
    "gn:country_code":"OM",
    "gn:dem":26,
    "gn:feature_class":"P",
    "gn:feature_code":"PPL",
    "gn:name":"Ghadw",
    "gn:population":0,
    "gn:timezone":"Asia/Muscat",
    "iso:country":"OM",
    "wof:name":"Ghadw",
    "wof:placetype":"locality"
},
  "geometry": {"coordinates":[58.05,20.46667],"type":"Point"}
}