{
  "type": "Feature",
  "properties": {
    "gn:admin1_code":"11",
    "gn:asciiname":"Rawdah",
    "gn:country_code":"OM",
    "gn:dem":101,
    "gn:feature_class":"P",
    "gn:feature_code":"PPL",
    "gn:name":"Raw\u1e11ah",
    "gn:population":0,
    "gn:timezone":"Asia/Muscat",
    "iso:country":"OM",
    "name:und_x_variant":[
        "Al Raudha",
        "Ar Raw\u1e11ah",
        "Ar Raudha",
        "Raw\u1e11ah"
    ],
    "wof:name":"Rawdah",
    "wof:placetype":"locality"
},
  "geometry": {"coordinates":[56.78661999999999,24.04765],"type":"Point"}
}