{
  "type": "Feature",
  "properties": {
    "gn:admin1_code":"11",
    "gn:asciiname":"Khushayshat al Milh",
    "gn:country_code":"OM",
    "gn:dem":100,
    "gn:feature_class":"P",
    "gn:feature_code":"PPL",
    "gn:name":"Khushayshat al Mil\u1e29",
    "gn:population":0,
    "gn:timezone":"Asia/Muscat",
    "iso:country":"OM",
    "name:ara_x_preferred":[
        "\u062e\u0634\u064a\u0634\u0629 \u0627\u0644\u0645\u0644\u062d"
    ],
    "name:und_x_variant":[
        "Khash\u012bshat al Mil\u1e29",
        "Khushayshat al Mil\u1e29",
        "Khishayshat al Mil\u1e25"
    ],
    "wof:name":"Khushayshat al Milh",
    "wof:placetype":"locality"
},
  "geometry": {"coordinates":[56.51759000000001,24.37441],"type":"Point"}
}