{
  "type": "Feature",
  "properties": {
    "gn:admin1_code":"01",
    "gn:asciiname":"Al Farra`ah",
    "gn:country_code":"OM",
    "gn:dem":912,
    "gn:feature_class":"P",
    "gn:feature_code":"PPL",
    "gn:name":"Al Farr\u0101\u2018ah",
    "gn:population":0,
    "gn:timezone":"Asia/Muscat",
    "iso:country":"OM",
    "name:ara_x_preferred":[
        "\u0627\u0644\u0641\u0631\u0627\u0639\u0629"
    ],
    "name:und_x_variant":[
        "Fir\u0101\u2018ah",
        "Al Farr\u0101\u2018ah"
    ],
    "wof:name":"Al Farra`ah",
    "wof:placetype":"locality"
},
  "geometry": {"coordinates":[57.31649,23.22051],"type":"Point"}
}