{
  "type": "Feature",
  "properties": {
    "gn:admin1_code":"04",
    "gn:asciiname":"Qasah",
    "gn:country_code":"OM",
    "gn:dem":167,
    "gn:feature_class":"P",
    "gn:feature_code":"PPL",
    "gn:name":"Qasah",
    "gn:population":0,
    "gn:timezone":"Asia/Muscat",
    "iso:country":"OM",
    "wof:name":"Qasah",
    "wof:placetype":"locality"
},
  "geometry": {"coordinates":[59.41311999999999,22.43045],"type":"Point"}
}