{
  "type": "Feature",
  "properties": {
    "gn:admin1_code":"11",
    "gn:asciiname":"Al Haymali",
    "gn:country_code":"OM",
    "gn:dem":334,
    "gn:feature_class":"P",
    "gn:feature_code":"PPL",
    "gn:name":"Al \u1e28aymal\u012b",
    "gn:population":0,
    "gn:timezone":"Asia/Muscat",
    "iso:country":"OM",
    "name:ara_x_preferred":[
        "\u0627\u0644\u062d\u064a\u0645\u0644\u064a"
    ],
    "name:und_x_variant":[
        "\u1e28aymit\u012byah",
        "\u1e28aymil\u012byah",
        "Al \u1e28aymal\u012b",
        "Al \u1e24ayml\u012b"
    ],
    "wof:name":"Al Haymali",
    "wof:placetype":"locality"
},
  "geometry": {"coordinates":[57.22888,23.58706],"type":"Point"}
}