{
  "type": "Feature",
  "properties": {
    "gn:admin1_code":"01",
    "gn:asciiname":"Al Janah",
    "gn:country_code":"OM",
    "gn:dem":562,
    "gn:feature_class":"P",
    "gn:feature_code":"PPL",
    "gn:name":"Al Jan\u0101h",
    "gn:population":0,
    "gn:timezone":"Asia/Muscat",
    "iso:country":"OM",
    "name:ara_x_preferred":[
        "Jin\u0101h"
    ],
    "name:ara_x_variant":[
        "\u0627\u0644\u062c\u0646\u0627\u0629"
    ],
    "name:und_x_variant":[
        "Al Jan\u0101h"
    ],
    "wof:name":"Al Janah",
    "wof:placetype":"locality"
},
  "geometry": {"coordinates":[57.8517,23.14712],"type":"Point"}
}