{
  "type": "Feature",
  "properties": {
    "iso:country":"OM",
    "name:ara_x_preferred":[
        "\u0648\u0644\u0627\u064a\u0629 \u0623\u062f\u0645"
    ],
    "name:ceb_x_preferred":[
        "\u0100dam"
    ],
    "name:deu_x_preferred":[
        "Adam"
    ],
    "name:eng_x_preferred":[
        "Adam"
    ],
    "name:fas_x_preferred":[
        "\u0627\u062f\u0645"
    ],
    "name:fra_x_preferred":[
        "Adam"
    ],
    "name:ita_x_preferred":[
        "Adam"
    ],
    "name:jpn_x_preferred":[
        "\u30a2\u30c0\u30e0"
    ],
    "name:nld_x_preferred":[
        "Adam"
    ],
    "name:por_x_preferred":[
        "Ad\u00e3o"
    ],
    "name:swe_x_preferred":[
        "Adam"
    ],
    "name:urd_x_preferred":[
        "\u0627\u062f\u0645"
    ],
    "name:zho_x_preferred":[
        "\u4e9e\u7576"
    ],
    "qs:gn_country":"OM",
    "qs:gn_fcode":"PPL",
    "qs:gn_pop":17283,
    "qs:name":"\u0627\u062f\u0645",
    "qs:name_adm0":"\u0639\u0645\u0627\u0646",
    "qs:name_adm1":"\u0627\u0644\u062f\u0627\u062e\u0644\u064a\u0629",
    "qs:photos":0,
    "qs:photos_1k":0,
    "qs:photos_9k":1,
    "qs:photos_9r":1,
    "qs:photos_all":1,
    "qs:photos_sr":0,
    "qs:placetype":"Town",
    "qs:pop_sr":"6",
    "qs:woe_adm0":23424898,
    "wof:name":"\u0627\u062f\u0645",
    "wof:placetype":"locality",
    "wof:population":17283
},
  "geometry": {"coordinates":[57.52334,22.3756],"type":"Point"}
}