{
  "type": "Feature",
  "properties": {
    "gn:admin1_code":"08",
    "gn:asciiname":"Ghar",
    "gn:country_code":"OM",
    "gn:dem":164,
    "gn:feature_class":"P",
    "gn:feature_code":"PPLL",
    "gn:name":"Gh\u0101r",
    "gn:population":0,
    "gn:timezone":"Asia/Muscat",
    "iso:country":"OM",
    "name:ara_x_preferred":[
        "\u063a\u0627\u0631"
    ],
    "name:und_x_variant":[
        "Gh\u0101r"
    ],
    "wof:name":"Ghar",
    "wof:placetype":"locality"
},
  "geometry": {"coordinates":[53.26207,16.71461],"type":"Point"}
}