{
  "type": "Feature",
  "properties": {
    "gn:admin1_code":"11",
    "gn:asciiname":"Al `Umayrah",
    "gn:country_code":"OM",
    "gn:dem":572,
    "gn:feature_class":"P",
    "gn:feature_code":"PPL",
    "gn:name":"Al \u2018Umayrah",
    "gn:population":0,
    "gn:timezone":"Asia/Muscat",
    "iso:country":"OM",
    "name:ara_x_preferred":[
        "\u0627\u0644\u0639\u0645\u064a\u0631\u0629"
    ],
    "name:und_x_variant":[
        "Al \u2018Am\u012brah",
        "Al \u2018Umayrah"
    ],
    "wof:name":"Al `Umayrah",
    "wof:placetype":"locality"
},
  "geometry": {"coordinates":[56.4273,24.15542],"type":"Point"}
}