{
  "type": "Feature",
  "properties": {
    "gn:admin1_code":"06",
    "gn:asciiname":"Al `Awabi",
    "gn:country_code":"OM",
    "gn:dem":142,
    "gn:feature_class":"P",
    "gn:feature_code":"PPL",
    "gn:name":"Al \u2018Aw\u0101b\u012b",
    "gn:population":0,
    "gn:timezone":"Asia/Muscat",
    "iso:country":"OM",
    "name:ara_x_preferred":[
        "\u2018Aw\u0101b\u012b"
    ],
    "name:ara_x_variant":[
        "\u0627\u0644\u0639\u0648\u0627\u0628\u064a"
    ],
    "name:und_x_variant":[
        "Al \u2018Aw\u0101b\u012b"
    ],
    "wof:name":"Al `Awabi",
    "wof:placetype":"locality"
},
  "geometry": {"coordinates":[58.28527,23.4887],"type":"Point"}
}