{
  "type": "Feature",
  "properties": {
    "gn:admin1_code":"07",
    "gn:asciiname":"Al Harrat",
    "gn:country_code":"OM",
    "gn:dem":453,
    "gn:feature_class":"P",
    "gn:feature_code":"PPL",
    "gn:name":"Al \u1e28\u0101rr\u0101t",
    "gn:population":0,
    "gn:timezone":"Asia/Muscat",
    "iso:country":"OM",
    "name:ara_x_preferred":[
        "Al \u1e28\u0101r\u0101t"
    ],
    "name:ara_x_variant":[
        "\u0627\u0644\u062d\u0627\u0631\u0651\u0627\u062a"
    ],
    "name:und_x_variant":[
        "\u1e28ar\u0101t",
        "Al \u1e28\u0101rr\u0101t",
        "Al \u1e24\u0101rr\u0101t"
    ],
    "wof:name":"Al Harrat",
    "wof:placetype":"locality"
},
  "geometry": {"coordinates":[56.20769,26.16921],"type":"Point"}
}