{
  "type": "Feature",
  "properties": {
    "gn:admin1_code":"12",
    "gn:asciiname":"Al Qaryah",
    "gn:country_code":"OM",
    "gn:dem":596,
    "gn:feature_class":"P",
    "gn:feature_code":"PPL",
    "gn:name":"Al Qaryah",
    "gn:population":0,
    "gn:timezone":"Asia/Muscat",
    "iso:country":"OM",
    "name:ara_x_preferred":[
        "\u0627\u0644\u0642\u0631\u064a\u0629"
    ],
    "wof:name":"Al Qaryah",
    "wof:placetype":"locality"
},
  "geometry": {"coordinates":[58.53647,22.98175],"type":"Point"}
}