{
  "type": "Feature",
  "properties": {
    "gn:admin1_code":"03",
    "gn:asciiname":"Sawqarah",
    "gn:country_code":"OM",
    "gn:dem":1,
    "gn:feature_class":"P",
    "gn:feature_code":"PPL",
    "gn:name":"\u015eawqarah",
    "gn:population":0,
    "gn:timezone":"Asia/Muscat",
    "iso:country":"OM",
    "name:ara_x_preferred":[
        "\u0635\u0648\u0642\u0631\u0629"
    ],
    "name:und_x_variant":[
        "\u015eawqarah",
        "Sauqara",
        "\u015eawqirah",
        "\u1e62awqrah"
    ],
    "wof:name":"Sawqarah",
    "wof:placetype":"locality"
},
  "geometry": {"coordinates":[56.53858,18.15782],"type":"Point"}
}