{
  "type": "Feature",
  "properties": {
    "gn:admin1_code":"07",
    "gn:asciiname":"Sawt",
    "gn:country_code":"OM",
    "gn:dem":6,
    "gn:feature_class":"P",
    "gn:feature_code":"PPL",
    "gn:name":"Saw\u0163",
    "gn:population":0,
    "gn:timezone":"Asia/Muscat",
    "iso:country":"OM",
    "name:und_x_variant":[
        "Saw\u0163"
    ],
    "wof:name":"Sawt",
    "wof:placetype":"locality"
},
  "geometry": {"coordinates":[56.26221999999999,25.65639],"type":"Point"}
}