{
  "type": "Feature",
  "properties": {
    "gn:admin1_code":"08",
    "gn:asciiname":"Kharas",
    "gn:country_code":"OM",
    "gn:dem":774,
    "gn:feature_class":"P",
    "gn:feature_code":"PPL",
    "gn:name":"Kh\u0101ras",
    "gn:population":0,
    "gn:timezone":"Asia/Muscat",
    "iso:country":"OM",
    "name:ara_x_preferred":[
        "\u062e\u0627\u0631\u0633"
    ],
    "name:ara_x_variant":[
        "\u062e\u0627\u0631\u0627\u0633"
    ],
    "name:cat_x_preferred":[
        "Kharas"
    ],
    "name:ceb_x_preferred":[
        "Kh\u0101r\u0101s"
    ],
    "name:heb_x_preferred":[
        "\u05d7'\u05e8\u05d0\u05e1"
    ],
    "name:nno_x_preferred":[
        "Kharas"
    ],
    "name:pol_x_preferred":[
        "Kharas"
    ],
    "name:und_x_variant":[
        "Kh\u0101ras",
        "Kh\u0101ris"
    ],
    "wof:name":"Kharas",
    "wof:placetype":"locality"
},
  "geometry": {"coordinates":[54.25805,17.22184],"type":"Point"}
}