{
  "type": "Feature",
  "properties": {
    "gn:admin1_code":"04",
    "gn:asciiname":"Dafiyat",
    "gn:country_code":"OM",
    "gn:dem":7,
    "gn:feature_class":"P",
    "gn:feature_code":"PPL",
    "gn:name":"Daf\u012by\u0101t",
    "gn:population":0,
    "gn:timezone":"Asia/Muscat",
    "iso:country":"OM",
    "name:ara_x_preferred":[
        "\u062f\u0641\u064a\u0627\u062a"
    ],
    "name:und_x_variant":[
        "Daf\u012by\u0101t",
        "Dafiyy\u0101t",
        "Qaryat Daf\u012by\u0101t"
    ],
    "wof:name":"Dafiyat",
    "wof:placetype":"locality"
},
  "geometry": {"coordinates":[58.85103,20.59914],"type":"Point"}
}