{
  "type": "Feature",
  "properties": {
    "gn:admin1_code":"08",
    "gn:asciiname":"Wadi Nahiz",
    "gn:country_code":"OM",
    "gn:dem":530,
    "gn:feature_class":"P",
    "gn:feature_code":"PPL",
    "gn:name":"W\u0101d\u012b Nahiz",
    "gn:population":0,
    "gn:timezone":"Asia/Muscat",
    "iso:country":"OM",
    "name:ara_x_preferred":[
        "\u0648\u0627\u062f\u064a \u0646\u062d\u064a\u0632"
    ],
    "name:und_x_variant":[
        "W\u0101d\u012b Nahiz",
        "W\u0101d\u012b Na\u1e29\u012bz"
    ],
    "wof:name":"Wadi Nahiz",
    "wof:placetype":"locality"
},
  "geometry": {"coordinates":[54.09929,17.18305],"type":"Point"}
}