{
  "type": "Feature",
  "properties": {
    "gn:admin1_code":"02",
    "gn:asciiname":"At Tikhah",
    "gn:country_code":"OM",
    "gn:dem":334,
    "gn:feature_class":"P",
    "gn:feature_code":"PPL",
    "gn:name":"A\u0163 \u0162\u012bkhah",
    "gn:population":0,
    "gn:timezone":"Asia/Muscat",
    "iso:country":"OM",
    "name:ara_x_preferred":[
        "\u0627\u0644\u0637\u064a\u062e\u0629"
    ],
    "name:und_x_variant":[
        "\u0162akham",
        "A\u0163 \u0162\u012bkhah",
        "A\u1e6d \u1e6c\u012bkhah"
    ],
    "wof:name":"At Tikhah",
    "wof:placetype":"locality"
},
  "geometry": {"coordinates":[57.44091,23.42881],"type":"Point"}
}