{
  "type": "Feature",
  "properties": {
    "gn:admin1_code":"08",
    "gn:asciiname":"Agyaan",
    "gn:country_code":"OM",
    "gn:dem":524,
    "gn:feature_class":"P",
    "gn:feature_code":"PPL",
    "gn:name":"Agyaan",
    "gn:population":0,
    "gn:timezone":"Asia/Muscat",
    "iso:country":"OM",
    "name:ara_x_preferred":[
        "Agy\u0101n"
    ],
    "wof:name":"Agyaan",
    "wof:placetype":"locality"
},
  "geometry": {"coordinates":[54.21666999999999,17.16917],"type":"Point"}
}