{
  "type": "Feature",
  "properties": {
    "gn:admin1_code":"07",
    "gn:asciiname":"Ash Shawari`",
    "gn:country_code":"OM",
    "gn:dem":69,
    "gn:feature_class":"P",
    "gn:feature_code":"PPL",
    "gn:name":"Ash Shaw\u0101ri\u2018",
    "gn:population":0,
    "gn:timezone":"Asia/Muscat",
    "iso:country":"OM",
    "name:ara_x_preferred":[
        "\u0627\u0644\u0634\u0651\u0648\u0627\u0631\u0639"
    ],
    "name:und_x_variant":[
        "Al Shuwara",
        "Ash Shaw\u0101ri\u2018",
        "Ash Shaw\u0101ra\u2018"
    ],
    "wof:name":"Ash Shawari`",
    "wof:placetype":"locality"
},
  "geometry": {"coordinates":[56.28056,26.14636],"type":"Point"}
}