{
  "type": "Feature",
  "properties": {
    "gn:admin1_code":"06",
    "gn:asciiname":"Al Misfah ash Sharqiyah",
    "gn:country_code":"OM",
    "gn:dem":162,
    "gn:feature_class":"P",
    "gn:feature_code":"PPL",
    "gn:name":"Al Misf\u0101h ash Sharq\u012byah",
    "gn:population":0,
    "gn:timezone":"Asia/Muscat",
    "iso:country":"OM",
    "name:ara_x_preferred":[
        "\u0627\u0644\u0645\u0633\u0641\u0627\u0629 \u0627\u0644\u0634\u0651\u0631\u0642\u064a\u0651\u0629"
    ],
    "name:und_x_variant":[
        "Misf\u0101h al \u2018\u0100l\u012b",
        "Al Misf\u0101h ash Sharq\u012byah",
        "Al Misf\u0101h ash Sharqiyyah"
    ],
    "wof:name":"Al Misfah ash Sharqiyah",
    "wof:placetype":"locality"
},
  "geometry": {"coordinates":[58.2821,23.47695],"type":"Point"}
}