{
  "type": "Feature",
  "properties": {
    "gn:admin1_code":"09",
    "gn:asciiname":"Al Khaburah",
    "gn:country_code":"OM",
    "gn:dem":519,
    "gn:feature_class":"P",
    "gn:feature_code":"PPL",
    "gn:name":"Al Kh\u0101b\u016brah",
    "gn:population":0,
    "gn:timezone":"Asia/Muscat",
    "iso:country":"OM",
    "name:ara_x_preferred":[
        "\u0627\u0644\u062e\u0627\u0628\u0648\u0631\u0629"
    ],
    "name:und_x_variant":[
        "Al Kh\u0101b\u016brah",
        "Yanqul",
        "Yanqal",
        "Kh\u0101b\u016brat Yanqul"
    ],
    "wof:name":"Al Khaburah",
    "wof:placetype":"locality"
},
  "geometry": {"coordinates":[56.53179,23.55801],"type":"Point"}
}