{
  "type": "Feature",
  "properties": {
    "gn:admin1_code":"09",
    "gn:asciiname":"Dank",
    "gn:country_code":"OM",
    "gn:dem":341,
    "gn:feature_class":"P",
    "gn:feature_code":"PPL",
    "gn:name":"\u1e10ank",
    "gn:population":0,
    "gn:timezone":"Asia/Muscat",
    "iso:country":"OM",
    "name:ara_x_preferred":[
        "\u0636\u0646\u0643"
    ],
    "name:deu_x_preferred":[
        "Dank"
    ],
    "name:und_x_variant":[
        "\u1e10anak",
        "Dhank",
        "\u1e10ank",
        "\u1e0cank"
    ],
    "wof:name":"Dank",
    "wof:placetype":"locality"
},
  "geometry": {"coordinates":[56.25725,23.55054],"type":"Point"}
}