{
  "type": "Feature",
  "properties": {
    "gn:admin1_code":"08",
    "gn:asciiname":"Sahnawt",
    "gn:country_code":"OM",
    "gn:dem":714,
    "gn:feature_class":"P",
    "gn:feature_code":"PPL",
    "gn:name":"\u015ea\u1e29nawt",
    "gn:population":0,
    "gn:timezone":"Asia/Muscat",
    "iso:country":"OM",
    "name:ara_x_preferred":[
        "\u0635\u062d\u0644\u0646\u0648\u062a"
    ],
    "name:und_x_variant":[
        "\u015ea\u1e29nawt",
        "\u015eahalnawt"
    ],
    "wof:name":"Sahnawt",
    "wof:placetype":"locality"
},
  "geometry": {"coordinates":[54.17155,17.26872],"type":"Point"}
}