{
  "type": "Feature",
  "properties": {
    "gn:admin1_code":"00",
    "gn:asciiname":"Al Abyad",
    "gn:country_code":"OM",
    "gn:dem":217,
    "gn:feature_class":"P",
    "gn:feature_code":"PPL",
    "gn:name":"Al Abya\u1e11",
    "gn:population":0,
    "gn:timezone":"Asia/Muscat",
    "iso:country":"OM",
    "name:ara_x_preferred":[
        "\u0627\u0644\u0623\u0628\u064a\u0636"
    ],
    "name:und_x_variant":[
        "Al Abya\u1e11"
    ],
    "wof:name":"Al Abyad",
    "wof:placetype":"locality"
},
  "geometry": {"coordinates":[57.66611,23.46556],"type":"Point"}
}