{
  "type": "Feature",
  "properties": {
    "gn:admin1_code":"08",
    "gn:asciiname":"Fadhi",
    "gn:country_code":"OM",
    "gn:dem":8,
    "gn:feature_class":"P",
    "gn:feature_code":"PPL",
    "gn:name":"Fadh\u012b",
    "gn:population":0,
    "gn:timezone":"Asia/Muscat",
    "iso:country":"OM",
    "name:und_x_variant":[
        "Fadh\u012b"
    ],
    "wof:name":"Fadhi",
    "wof:placetype":"locality"
},
  "geometry": {"coordinates":[55.60204,17.89864],"type":"Point"}
}