{
  "type": "Feature",
  "properties": {
    "gn:admin1_code":"01",
    "gn:asciiname":"Qaryat Bani Subh",
    "gn:country_code":"OM",
    "gn:dem":651,
    "gn:feature_class":"P",
    "gn:feature_code":"PPL",
    "gn:name":"Qaryat Ban\u012b \u015eub\u1e29",
    "gn:population":0,
    "gn:timezone":"Asia/Muscat",
    "iso:country":"OM",
    "name:ara_x_preferred":[
        "\u0642\u0631\u064a\u0629 \u0628\u0646\u064a \u0635\u0628\u062d"
    ],
    "name:und_x_variant":[
        "Al Qaryah",
        "Qaryat Ban\u012b \u015eub\u1e29",
        "Qaryat Ban\u012b \u1e62ub\u1e25"
    ],
    "wof:name":"Qaryat Bani Subh",
    "wof:placetype":"locality"
},
  "geometry": {"coordinates":[57.30901,23.10083],"type":"Point"}
}