{
  "type": "Feature",
  "properties": {
    "gn:admin1_code":"09",
    "gn:asciiname":"Al Hijal",
    "gn:country_code":"OM",
    "gn:dem":498,
    "gn:feature_class":"P",
    "gn:feature_code":"PPL",
    "gn:name":"Al \u1e28ij\u0101l",
    "gn:population":0,
    "gn:timezone":"Asia/Muscat",
    "iso:country":"OM",
    "name:ara_x_preferred":[
        "Al \u1e28ij\u0101l"
    ],
    "wof:name":"Al Hijal",
    "wof:placetype":"locality"
},
  "geometry": {"coordinates":[56.62766,23.42666],"type":"Point"}
}