{
  "type": "Feature",
  "properties": {
    "gn:admin1_code":"02",
    "gn:asciiname":"Al Hayl",
    "gn:country_code":"OM",
    "gn:dem":221,
    "gn:feature_class":"P",
    "gn:feature_code":"PPL",
    "gn:name":"Al \u1e28ayl",
    "gn:population":0,
    "gn:timezone":"Asia/Muscat",
    "iso:country":"OM",
    "name:ara_x_preferred":[
        "\u0627\u0644\u062d\u064a\u0644"
    ],
    "name:und_x_variant":[
        "\u1e28ayi",
        "Al \u1e28ayl",
        "Al \u1e24ayl"
    ],
    "wof:name":"Al Hayl",
    "wof:placetype":"locality"
},
  "geometry": {"coordinates":[57.66273,23.45821],"type":"Point"}
}