{
  "type": "Feature",
  "properties": {
    "gn:admin1_code":"08",
    "gn:asciiname":"Aujeen",
    "gn:country_code":"OM",
    "gn:dem":868,
    "gn:feature_class":"P",
    "gn:feature_code":"PPL",
    "gn:name":"A\u016bjeen",
    "gn:population":0,
    "gn:timezone":"Asia/Muscat",
    "iso:country":"OM",
    "name:ara_x_preferred":[
        "A\u016bjeen"
    ],
    "name:ara_x_variant":[
        "\u0623\u0648\u062c\u064a\u0646"
    ],
    "name:und_x_variant":[
        "Awj\u012bn"
    ],
    "wof:name":"Aujeen",
    "wof:placetype":"locality"
},
  "geometry": {"coordinates":[54.48952,17.23021],"type":"Point"}
}