{
  "type": "Feature",
  "properties": {
    "gn:admin1_code":"01",
    "gn:asciiname":"Al Banah",
    "gn:country_code":"OM",
    "gn:dem":781,
    "gn:feature_class":"P",
    "gn:feature_code":"PPL",
    "gn:name":"Al B\u0101nah",
    "gn:population":0,
    "gn:timezone":"Asia/Muscat",
    "iso:country":"OM",
    "name:ara_x_preferred":[
        "\u0627\u0644\u0628\u0627\u0646\u0629"
    ],
    "name:und_x_variant":[
        "Al B\u0101nah"
    ],
    "wof:name":"Al Banah",
    "wof:placetype":"locality"
},
  "geometry": {"coordinates":[56.89503000000001,23.28369],"type":"Point"}
}