{
  "type": "Feature",
  "properties": {
    "gn:admin1_code":"04",
    "gn:asciiname":"Shubaykah",
    "gn:country_code":"OM",
    "gn:dem":399,
    "gn:feature_class":"P",
    "gn:feature_code":"PPL",
    "gn:name":"Shubaykah",
    "gn:population":0,
    "gn:timezone":"Asia/Muscat",
    "iso:country":"OM",
    "name:ara_x_preferred":[
        "\u0634\u0628\u064a\u0643\u0629"
    ],
    "name:und_x_variant":[
        "Ash Shubaykah",
        "Shubaykah",
        "Shibaykah"
    ],
    "wof:name":"Shubaykah",
    "wof:placetype":"locality"
},
  "geometry": {"coordinates":[59.2957,22.61727],"type":"Point"}
}