{
  "type": "Feature",
  "properties": {
    "gn:admin1_code":"08",
    "gn:asciiname":"Israwb",
    "gn:country_code":"OM",
    "gn:dem":701,
    "gn:feature_class":"P",
    "gn:feature_code":"PPL",
    "gn:name":"I\u015frawb",
    "gn:population":0,
    "gn:timezone":"Asia/Muscat",
    "iso:country":"OM",
    "name:ara_x_preferred":[
        "\u0625\u0635\u0631\u0648\u0628"
    ],
    "name:und_x_variant":[
        "I\u015frawb",
        "I\u1e63rawb"
    ],
    "wof:name":"Israwb",
    "wof:placetype":"locality"
},
  "geometry": {"coordinates":[53.15583,16.69685],"type":"Point"}
}