{
  "type": "Feature",
  "properties": {
    "gn:admin1_code":"04",
    "gn:asciiname":"Al Jiba`i",
    "gn:country_code":"OM",
    "gn:dem":111,
    "gn:feature_class":"P",
    "gn:feature_code":"PPL",
    "gn:name":"Al Jib\u0101\u2018\u012b",
    "gn:population":0,
    "gn:timezone":"Asia/Muscat",
    "iso:country":"OM",
    "name:ara_x_preferred":[
        "Al Jib\u0101\u2018\u012b"
    ],
    "wof:name":"Al Jiba`i",
    "wof:placetype":"locality"
},
  "geometry": {"coordinates":[59.38561,22.43551],"type":"Point"}
}