{
  "type": "Feature",
  "properties": {
    "gn:admin1_code":"07",
    "gn:asciiname":"Ruwaybah",
    "gn:country_code":"OM",
    "gn:dem":55,
    "gn:feature_class":"P",
    "gn:feature_code":"PPL",
    "gn:name":"Ruwaybah",
    "gn:population":0,
    "gn:timezone":"Asia/Muscat",
    "iso:country":"OM",
    "name:ara_x_preferred":[
        "\u0631\u0648\u064a\u0628\u0629"
    ],
    "name:und_x_variant":[
        "Arubi",
        "R\u016bbiyah",
        "Ruwaybah"
    ],
    "wof:name":"Ruwaybah",
    "wof:placetype":"locality"
},
  "geometry": {"coordinates":[56.23978,26.13527],"type":"Point"}
}