{
  "type": "Feature",
  "properties": {
    "gn:admin1_code":"09",
    "gn:asciiname":"Al Hashimah",
    "gn:country_code":"OM",
    "gn:dem":828,
    "gn:feature_class":"P",
    "gn:feature_code":"PPL",
    "gn:name":"Al Hash\u012bmah",
    "gn:population":0,
    "gn:timezone":"Asia/Muscat",
    "iso:country":"OM",
    "name:ara_x_preferred":[
        "\u0627\u0644\u0647\u0634\u064a\u0645\u0629"
    ],
    "name:und_x_variant":[
        "Al Hashim\u012b",
        "Al Hash\u012bmah",
        "Al Hishaymah"
    ],
    "wof:name":"Al Hashimah",
    "wof:placetype":"locality"
},
  "geometry": {"coordinates":[56.39272,23.94098],"type":"Point"}
}