{
  "type": "Feature",
  "properties": {
    "gn:admin1_code":"12",
    "gn:asciiname":"Ad Dariz",
    "gn:country_code":"OM",
    "gn:dem":346,
    "gn:feature_class":"P",
    "gn:feature_code":"PPL",
    "gn:name":"Ad Dar\u012bz",
    "gn:population":0,
    "gn:timezone":"Asia/Muscat",
    "iso:country":"OM",
    "name:ara_x_preferred":[
        "\u0627\u0644\u062f\u0631\u064a\u0632"
    ],
    "name:und_x_variant":[
        "Dar\u012bz",
        "Ad Dar\u012bz",
        "Ad Dir\u012bz"
    ],
    "wof:name":"Ad Dariz",
    "wof:placetype":"locality"
},
  "geometry": {"coordinates":[58.68375,22.584],"type":"Point"}
}