{
  "type": "Feature",
  "properties": {
    "gn:admin1_code":"10",
    "gn:asciiname":"Zab",
    "gn:country_code":"OM",
    "gn:dem":461,
    "gn:feature_class":"P",
    "gn:feature_code":"PPL",
    "gn:name":"Z\u0101b",
    "gn:population":0,
    "gn:timezone":"Asia/Muscat",
    "iso:country":"OM",
    "name:ara_x_preferred":[
        "Z\u0101b"
    ],
    "wof:name":"Zab",
    "wof:placetype":"locality"
},
  "geometry": {"coordinates":[55.98333,24.55],"type":"Point"}
}