{
  "type": "Feature",
  "properties": {
    "gn:admin1_code":"10",
    "gn:asciiname":"Zab",
    "gn:country_code":"OM",
    "gn:dem":461,
    "gn:feature_class":"P",
    "gn:feature_code":"PPL",
    "gn:name":"Z\u0101b",
    "gn:population":0,
    "gn:timezone":"Asia/Muscat",
    "iso:country":"OM",
    "name:ara_x_preferred":[
        "Z\u0101b"
    ],
    "name:ara_x_variant":[
        "\u0627\u0644\u0632\u0627\u0628"
    ],
    "name:ceb_x_preferred":[
        "Zab"
    ],
    "name:ces_x_preferred":[
        "Z\u00e1b"
    ],
    "name:deu_x_preferred":[
        "Zab"
    ],
    "name:eus_x_preferred":[
        "Zab"
    ],
    "name:fra_x_preferred":[
        "Zab"
    ],
    "name:lit_x_preferred":[
        "Zabas"
    ],
    "name:nld_x_preferred":[
        "Zab"
    ],
    "name:rus_x_preferred":[
        "\u0417\u0430\u0431"
    ],
    "name:spa_x_preferred":[
        "Zab"
    ],
    "wof:name":"Zab",
    "wof:placetype":"locality"
},
  "geometry": {"coordinates":[55.98333,24.55],"type":"Point"}
}