{
  "type": "Feature",
  "properties": {
    "iso:country":"OM",
    "qs:gn_pop":0,
    "qs:name":"\u062e\u0635\u0628",
    "qs:name_adm0":"\u0639\u0645\u0627\u0646",
    "qs:name_adm1":"\u0645\u0633\u0646\u062f\u0645",
    "qs:photos":86,
    "qs:photos_1k":17,
    "qs:photos_9k":1,
    "qs:photos_9r":3,
    "qs:photos_all":86,
    "qs:photos_sr":3,
    "qs:placetype":"Town",
    "qs:pop_sr":"0",
    "qs:woe_adm0":23424898,
    "wof:name":"\u062e\u0635\u0628",
    "wof:placetype":"locality"
},
  "geometry": {"coordinates":[56.246688,26.197854],"type":"Point"}
}