{
  "type": "Feature",
  "properties": {
    "gn:admin1_code":"11",
    "gn:asciiname":"Sham",
    "gn:country_code":"OM",
    "gn:dem":609,
    "gn:feature_class":"P",
    "gn:feature_code":"PPL",
    "gn:name":"Sh\u0101m",
    "gn:population":0,
    "gn:timezone":"Asia/Muscat",
    "iso:country":"OM",
    "name:ara_x_preferred":[
        "Sh\u0101m"
    ],
    "name:ara_x_variant":[
        "\u0634\u0627\u0645"
    ],
    "wof:name":"Sham",
    "wof:placetype":"locality"
},
  "geometry": {"coordinates":[56.54024,23.88933],"type":"Point"}
}