{
  "type": "Feature",
  "properties": {
    "gn:admin1_code":"11",
    "gn:asciiname":"Sham",
    "gn:country_code":"OM",
    "gn:dem":609,
    "gn:feature_class":"P",
    "gn:feature_code":"PPL",
    "gn:name":"Sh\u0101m",
    "gn:population":0,
    "gn:timezone":"Asia/Muscat",
    "iso:country":"OM",
    "name:ara_x_preferred":[
        "Sh\u0101m"
    ],
    "name:ara_x_variant":[
        "\u0634\u0627\u0645"
    ],
    "name:ceb_x_preferred":[
        "Sham"
    ],
    "name:deu_x_preferred":[
        "Sham"
    ],
    "name:fas_x_preferred":[
        "\u0634\u0627\u0645"
    ],
    "name:fra_x_preferred":[
        "Sham"
    ],
    "name:heb_x_preferred":[
        "\u05d0-\u05e9\u05d0\u05dd"
    ],
    "name:ita_x_preferred":[
        "Sham"
    ],
    "name:jpn_x_preferred":[
        "\u30b7\u30e3\u30e0"
    ],
    "name:ron_x_preferred":[
        "Sham"
    ],
    "name:spa_x_preferred":[
        "Sham"
    ],
    "name:swe_x_preferred":[
        "Sham"
    ],
    "wof:name":"Sham",
    "wof:placetype":"locality"
},
  "geometry": {"coordinates":[56.54024,23.88933],"type":"Point"}
}