{
  "type": "Feature",
  "properties": {
    "gn:admin1_code":"09",
    "gn:asciiname":"Dawt",
    "gn:country_code":"OM",
    "gn:dem":401,
    "gn:feature_class":"P",
    "gn:feature_code":"PPL",
    "gn:name":"Dawt",
    "gn:population":0,
    "gn:timezone":"Asia/Muscat",
    "iso:country":"OM",
    "name:ara_x_preferred":[
        "D\u016bt"
    ],
    "name:ara_x_variant":[
        "\u062f\u0648\u062a"
    ],
    "wof:name":"Dawt",
    "wof:placetype":"locality"
},
  "geometry": {"coordinates":[56.34332,23.53898],"type":"Point"}
}