{
  "type": "Feature",
  "properties": {
    "gn:admin1_code":"06",
    "gn:asciiname":"Ash Shihbari",
    "gn:country_code":"OM",
    "gn:dem":15,
    "gn:feature_class":"P",
    "gn:feature_code":"PPL",
    "gn:name":"Ash Shihb\u0101r\u012b",
    "gn:population":0,
    "gn:timezone":"Asia/Muscat",
    "iso:country":"OM",
    "name:ara_x_preferred":[
        "Af\u0101"
    ],
    "name:ara_x_variant":[
        "Ash Shihb\u0101r\u012b",
        "\u0627\u0644\u0634\u0647\u0628\u0627\u0631\u064a"
    ],
    "wof:name":"Ash Shihbari",
    "wof:placetype":"locality"
},
  "geometry": {"coordinates":[58.89741,23.22562000000001],"type":"Point"}
}