{
  "type": "Feature",
  "properties": {
    "gn:admin1_code":"10",
    "gn:asciiname":"Al Mudayli",
    "gn:country_code":"OM",
    "gn:dem":466,
    "gn:feature_class":"P",
    "gn:feature_code":"PPL",
    "gn:name":"Al Mudayl\u012b",
    "gn:population":0,
    "gn:timezone":"Asia/Muscat",
    "iso:country":"OM",
    "name:und_x_variant":[
        "Al Mudayl\u012b"
    ],
    "wof:name":"Al Mudayli",
    "wof:placetype":"locality"
},
  "geometry": {"coordinates":[56.01944,24.62194],"type":"Point"}
}