{
  "type": "Feature",
  "properties": {
    "gn:admin1_code":"11",
    "gn:asciiname":"Sur al Balush",
    "gn:country_code":"OM",
    "gn:dem":4,
    "gn:feature_class":"P",
    "gn:feature_code":"PPL",
    "gn:name":"S\u016br al Bal\u016bsh",
    "gn:population":0,
    "gn:timezone":"Asia/Muscat",
    "iso:country":"OM",
    "name:ara_x_preferred":[
        "\u0633\u0648\u0631 \u0627\u0644\u0628\u0644\u0648\u0634"
    ],
    "name:und_x_variant":[
        "S\u016br al Bal\u016bsh"
    ],
    "wof:name":"Sur al Balush",
    "wof:placetype":"locality"
},
  "geometry": {"coordinates":[56.52385,24.62182],"type":"Point"}
}