{
  "type": "Feature",
  "properties": {
    "gn:admin1_code":"11",
    "gn:asciiname":"Suri",
    "gn:country_code":"OM",
    "gn:dem":511,
    "gn:feature_class":"P",
    "gn:feature_code":"PPL",
    "gn:name":"S\u016br\u012b",
    "gn:population":0,
    "gn:timezone":"Asia/Muscat",
    "iso:country":"OM",
    "name:ara_x_preferred":[
        "S\u016br\u012b"
    ],
    "name:ara_x_variant":[
        "\u0633\u0648\u0631\u064a"
    ],
    "wof:name":"Suri",
    "wof:placetype":"locality"
},
  "geometry": {"coordinates":[56.96905,23.60641],"type":"Point"}
}