{
  "type": "Feature",
  "properties": {
    "gn:admin1_code":"06",
    "gn:asciiname":"Qaryah",
    "gn:country_code":"OM",
    "gn:dem":154,
    "gn:feature_class":"P",
    "gn:feature_code":"PPL",
    "gn:name":"Qaryah",
    "gn:population":0,
    "gn:timezone":"Asia/Muscat",
    "iso:country":"OM",
    "wof:name":"Qaryah",
    "wof:placetype":"locality"
},
  "geometry": {"coordinates":[58.86611,23.07417],"type":"Point"}
}