{
  "type": "Feature",
  "properties": {
    "gn:admin1_code":"11",
    "gn:asciiname":"Mukhaylif",
    "gn:country_code":"OM",
    "gn:dem":14,
    "gn:feature_class":"P",
    "gn:feature_code":"PPL",
    "gn:name":"Mukhayl\u012bf",
    "gn:population":0,
    "gn:timezone":"Asia/Muscat",
    "iso:country":"OM",
    "name:ara_x_preferred":[
        "\u0645\u062e\u064a\u0644\u064a\u0641"
    ],
    "name:und_x_variant":[
        "Mukhayl\u012bf",
        "Mikhayl\u012bf"
    ],
    "wof:name":"Mukhaylif",
    "wof:placetype":"locality"
},
  "geometry": {"coordinates":[56.5682,24.50918],"type":"Point"}
}