{
  "type": "Feature",
  "properties": {
    "gn:admin1_code":"08",
    "gn:asciiname":"Dalkut",
    "gn:country_code":"OM",
    "gn:dem":13,
    "gn:feature_class":"P",
    "gn:feature_code":"PPL",
    "gn:name":"\u1e10alk\u016bt",
    "gn:population":0,
    "gn:timezone":"Asia/Muscat",
    "iso:country":"OM",
    "name:ara_x_preferred":[
        "\u0636\u0644\u0643\u0648\u062a"
    ],
    "name:ara_x_variant":[
        "\u0638\u0644\u0643\u0648\u062a"
    ],
    "name:und_x_variant":[
        "Dhalqut",
        "Thalf\u016bt",
        "\u1e10alk\u016bt",
        "\u1e0calk\u016bt",
        "Z\u0327alk\u016bt"
    ],
    "wof:name":"Dalkut",
    "wof:placetype":"locality"
},
  "geometry": {"coordinates":[53.24219,16.70403],"type":"Point"}
}