{
  "type": "Feature",
  "properties": {
    "gn:admin1_code":"08",
    "gn:asciiname":"Mirbat",
    "gn:cc2":"OM",
    "gn:country_code":"OM",
    "gn:dem":2,
    "gn:feature_class":"P",
    "gn:feature_code":"PPL",
    "gn:name":"Mirb\u0101\u0163",
    "gn:population":0,
    "gn:timezone":"Asia/Muscat",
    "iso:country":"OM",
    "name:ara_x_preferred":[
        "\u0648\u0644\u0627\u064a\u0629 \u0645\u0631\u0628\u0627\u0637"
    ],
    "name:ben_x_preferred":[
        "\u09ae\u09bf\u09b0\u09ac\u09be\u09a4"
    ],
    "name:ces_x_preferred":[
        "Mirbat"
    ],
    "name:deu_x_preferred":[
        "Mirbat"
    ],
    "name:ell_x_preferred":[
        "\u039c\u03b9\u03c1\u03bc\u03c0\u03ac\u03c4"
    ],
    "name:fas_x_preferred":[
        "\u0645\u0631\u0628\u0627\u0637"
    ],
    "name:fra_x_preferred":[
        "Mirbat"
    ],
    "name:heb_x_preferred":[
        "\u05de\u05d9\u05e8\u05d1\u05d8"
    ],
    "name:hin_x_preferred":[
        "\u092e\u093f\u0930\u094d\u092c\u093e\u0924"
    ],
    "name:hun_x_preferred":[
        "Mirbat"
    ],
    "name:ind_x_preferred":[
        "Mirbat"
    ],
    "name:ita_x_preferred":[
        "Mirbat"
    ],
    "name:jpn_x_preferred":[
        "\u30df\u30eb\u30d0\u30c8"
    ],
    "name:kor_x_preferred":[
        "\ubbf8\ub974\ubc14\ud2b8"
    ],
    "name:msa_x_preferred":[
        "Mirbat"
    ],
    "name:nno_x_preferred":[
        "Mirbat"
    ],
    "name:pol_x_preferred":[
        "Mirbat"
    ],
    "name:por_x_preferred":[
        "Mirbat"
    ],
    "name:rus_x_preferred":[
        "\u041c\u0438\u0440\u0431\u0430\u0442"
    ],
    "name:spa_x_preferred":[
        "Mirbat"
    ],
    "name:swe_x_preferred":[
        "Mirbat"
    ],
    "name:tur_x_preferred":[
        "Marbat"
    ],
    "name:ukr_x_preferred":[
        "\u041c\u0456\u0440\u0431\u0430\u0442"
    ],
    "name:und_x_variant":[
        "Murb\u0101t",
        "Marb\u0101t",
        "Merbat"
    ],
    "name:urd_x_preferred":[
        "\u0645\u06cc\u0631\u0628\u0627\u062a"
    ],
    "name:vie_x_preferred":[
        "Mirbat"
    ],
    "name:zho_cn_x_preferred":[
        "\u7c73\u5c14\u5df4\u7279"
    ],
    "name:zho_tw_x_preferred":[
        "\u7c73\u723e\u5df4\u7279"
    ],
    "wof:name":"Mirbat",
    "wof:placetype":"locality"
},
  "geometry": {"coordinates":[54.69063,16.99638],"type":"Point"}
}