{
  "type": "Feature",
  "properties": {
    "gn:admin1_code":"08",
    "gn:asciiname":"Mirbat",
    "gn:cc2":"OM",
    "gn:country_code":"OM",
    "gn:dem":2,
    "gn:feature_class":"P",
    "gn:feature_code":"PPL",
    "gn:name":"Mirb\u0101\u0163",
    "gn:population":0,
    "gn:timezone":"Asia/Muscat",
    "iso:country":"OM",
    "name:und_x_variant":[
        "Murb\u0101t",
        "Marb\u0101t",
        "Merbat",
        "Mirbat"
    ],
    "wof:name":"Mirbat",
    "wof:placetype":"locality"
},
  "geometry": {"coordinates":[54.69063000000001,16.99638],"type":"Point"}
}