{
  "type": "Feature",
  "properties": {
    "gn:admin1_code":"08",
    "gn:asciiname":"Amneem",
    "gn:country_code":"OM",
    "gn:dem":881,
    "gn:feature_class":"P",
    "gn:feature_code":"PPL",
    "gn:name":"Amneem",
    "gn:population":0,
    "gn:timezone":"Asia/Muscat",
    "iso:country":"OM",
    "name:ara_x_preferred":[
        "\u0639\u0645\u0646\u064a\u0645"
    ],
    "name:und_x_variant":[
        "\u2018Amn\u012bm",
        "Amneem"
    ],
    "wof:name":"Amneem",
    "wof:placetype":"locality"
},
  "geometry": {"coordinates":[54.04621,17.23354],"type":"Point"}
}