{
  "type": "Feature",
  "properties": {
    "gn:admin1_code":"11",
    "gn:asciiname":"Al Masan",
    "gn:country_code":"OM",
    "gn:dem":773,
    "gn:feature_class":"P",
    "gn:feature_code":"PPL",
    "gn:name":"Al Masan",
    "gn:population":0,
    "gn:timezone":"Asia/Muscat",
    "iso:country":"OM",
    "name:ara_x_preferred":[
        "Al M\u016bsin"
    ],
    "name:ara_x_variant":[
        "\u0627\u0644\u0645\u0633\u0646"
    ],
    "name:und_x_variant":[
        "Al Mumsam",
        "Al Masan",
        "Al Misan"
    ],
    "wof:name":"Al Masan",
    "wof:placetype":"locality"
},
  "geometry": {"coordinates":[56.76667,23.73333],"type":"Point"}
}