{
  "type": "Feature",
  "properties": {
    "gn:admin1_code":"07",
    "gn:asciiname":"Arthaban",
    "gn:country_code":"OM",
    "gn:dem":403,
    "gn:feature_class":"P",
    "gn:feature_code":"PPL",
    "gn:name":"Arthaban",
    "gn:population":0,
    "gn:timezone":"Asia/Muscat",
    "iso:country":"OM",
    "wof:name":"Arthaban",
    "wof:placetype":"locality"
},
  "geometry": {"coordinates":[56.31606,25.78255],"type":"Point"}
}