{
  "type": "Feature",
  "properties": {
    "gn:admin1_code":"08",
    "gn:asciiname":"Adkham",
    "gn:country_code":"OM",
    "gn:dem":677,
    "gn:feature_class":"P",
    "gn:feature_code":"PPL",
    "gn:name":"Adkh\u0101m",
    "gn:population":0,
    "gn:timezone":"Asia/Muscat",
    "iso:country":"OM",
    "name:ara_x_preferred":[
        "Adkh\u0101m"
    ],
    "name:ara_x_variant":[
        "\u0623\u062f\u062e\u0627\u0645"
    ],
    "name:und_x_variant":[
        "Adanham",
        "Adaakham",
        "Ad\u0101kham"
    ],
    "wof:name":"Adkham",
    "wof:placetype":"locality"
},
  "geometry": {"coordinates":[54.35533,17.1482],"type":"Point"}
}