{
  "type": "Feature",
  "properties": {
    "gn:admin1_code":"08",
    "gn:asciiname":"Imbrat",
    "gn:country_code":"OM",
    "gn:dem":904,
    "gn:feature_class":"P",
    "gn:feature_code":"PPL",
    "gn:name":"Imbr\u0101t",
    "gn:population":0,
    "gn:timezone":"Asia/Muscat",
    "iso:country":"OM",
    "name:ara_x_preferred":[
        "Imbr\u0101t"
    ],
    "wof:name":"Imbrat",
    "wof:placetype":"locality"
},
  "geometry": {"coordinates":[54.25141,17.2757],"type":"Point"}
}