{
  "type": "Feature",
  "properties": {
    "gn:admin1_code":"02",
    "gn:asciiname":"Khubrah",
    "gn:country_code":"OM",
    "gn:dem":270,
    "gn:feature_class":"P",
    "gn:feature_code":"PPL",
    "gn:name":"Khubrah",
    "gn:population":0,
    "gn:timezone":"Asia/Muscat",
    "iso:country":"OM",
    "wof:name":"Khubrah",
    "wof:placetype":"locality"
},
  "geometry": {"coordinates":[57.88833,23.45583],"type":"Point"}
}