{
  "type": "Feature",
  "properties": {
    "gn:country":"OM",
    "iso:country":"OM",
    "qs:name":"\u0627\u0644\u062e\u0635\u0628",
    "qs:name_adm0":"\u0639\u0645\u0627\u0646",
    "qs:name_adm1":"\u0645\u0633\u0646\u062f\u0645",
    "qs:photos":53,
    "qs:photos_1k":11,
    "qs:photos_9k":1,
    "qs:photos_9r":2,
    "qs:photos_all":53,
    "qs:photos_sr":2,
    "qs:placetype":"Town",
    "qs:pop_sr":"0",
    "wof:name":"\u0627\u0644\u062e\u0635\u0628",
    "wof:placetype":"locality"
},
  "geometry": {"coordinates":[56.228885,26.208738],"type":"Point"}
}