{
  "type": "Feature",
  "properties": {
    "gn:admin1_code":"11",
    "gn:asciiname":"Wadiyah al `Ulya'",
    "gn:country_code":"OM",
    "gn:dem":163,
    "gn:feature_class":"P",
    "gn:feature_code":"PPL",
    "gn:name":"Wad\u012byah al \u2018Uly\u0101\u2019",
    "gn:population":0,
    "gn:timezone":"Asia/Muscat",
    "iso:country":"OM",
    "name:und_x_variant":[
        "Wad\u012byat al \u2018Uly\u0101\u2019",
        "Wad\u012byah al \u2018Uly\u0101\u2019"
    ],
    "wof:name":"Wadiyah al `Ulya'",
    "wof:placetype":"locality"
},
  "geometry": {"coordinates":[57.21842,23.65717],"type":"Point"}
}