{
  "type": "Feature",
  "properties": {
    "gn:admin1_code":"08",
    "gn:asciiname":"Afratm",
    "gn:country_code":"OM",
    "gn:dem":631,
    "gn:feature_class":"P",
    "gn:feature_code":"PPL",
    "gn:name":"Afr\u0101tm",
    "gn:population":0,
    "gn:timezone":"Asia/Muscat",
    "iso:country":"OM",
    "name:ara_x_preferred":[
        "Afr\u0101tm"
    ],
    "name:ara_x_variant":[
        "\u0623\u0641\u0631\u0648\u062a\u0645"
    ],
    "name:und_x_variant":[
        "Afr\u016btam"
    ],
    "wof:name":"Afratm",
    "wof:placetype":"locality"
},
  "geometry": {"coordinates":[54.37477,17.13434],"type":"Point"}
}