{
  "type": "Feature",
  "properties": {
    "gn:admin1_code":"01",
    "gn:asciiname":"Thina'",
    "gn:country_code":"OM",
    "gn:dem":393,
    "gn:feature_class":"P",
    "gn:feature_code":"PPL",
    "gn:name":"Thin\u0101\u2019",
    "gn:population":0,
    "gn:timezone":"Asia/Muscat",
    "iso:country":"OM",
    "name:ara_x_preferred":[
        "Thin\u0101\u2019"
    ],
    "wof:name":"Thina'",
    "wof:placetype":"locality"
},
  "geometry": {"coordinates":[58.09028000000001,23.25111],"type":"Point"}
}