{
  "type": "Feature",
  "properties": {
    "gn:admin1_code":"02",
    "gn:asciiname":"As Sawadi al Hakman",
    "gn:country_code":"OM",
    "gn:dem":11,
    "gn:feature_class":"P",
    "gn:feature_code":"PPL",
    "gn:name":"As Saw\u0101d\u012b al \u1e28akm\u0101n",
    "gn:population":0,
    "gn:timezone":"Asia/Muscat",
    "iso:country":"OM",
    "name:ara_x_preferred":[
        "Suw\u0101d\u012b \u2018Alw\u0101"
    ],
    "name:ara_x_variant":[
        "\u0627\u0644\u0633\u0651\u0648\u0627\u062f\u064a \u0627\u0644\u062d\u0643\u0645\u0627\u0646"
    ],
    "name:und_x_variant":[
        "As Saw\u0101d\u012b al \u1e28akm\u0101n",
        "As Saw\u0101d\u012b al \u1e24akm\u0101n"
    ],
    "wof:name":"As Sawadi al Hakman",
    "wof:placetype":"locality"
},
  "geometry": {"coordinates":[57.73565,23.73943],"type":"Point"}
}