{
  "type": "Feature",
  "properties": {
    "gn:admin1_code":"11",
    "gn:asciiname":"Hijari",
    "gn:country_code":"OM",
    "gn:dem":33,
    "gn:feature_class":"P",
    "gn:feature_code":"PPL",
    "gn:name":"Hij\u0101r\u012b",
    "gn:population":0,
    "gn:timezone":"Asia/Muscat",
    "iso:country":"OM",
    "name:ara_x_preferred":[
        "Hij\u0101r\u012b"
    ],
    "wof:name":"Hijari",
    "wof:placetype":"locality"
},
  "geometry": {"coordinates":[56.97759,24.00394],"type":"Point"}
}