{
  "type": "Feature",
  "properties": {
    "gn:admin1_code":"06",
    "gn:asciiname":"Mazra`at al Hatih",
    "gn:country_code":"OM",
    "gn:dem":156,
    "gn:feature_class":"P",
    "gn:feature_code":"PPL",
    "gn:name":"Mazra\u2018at al H\u0101tih",
    "gn:population":0,
    "gn:timezone":"Asia/Muscat",
    "iso:country":"OM",
    "name:und_x_variant":[
        "Mazra\u2018at al H\u0101tih"
    ],
    "wof:name":"Mazra`at al Hatih",
    "wof:placetype":"locality"
},
  "geometry": {"coordinates":[58.75165,23.27626],"type":"Point"}
}