{
  "type": "Feature",
  "properties": {
    "gn:admin1_code":"11",
    "gn:asciiname":"Abu Baqarah",
    "gn:country_code":"OM",
    "gn:dem":1,
    "gn:feature_class":"P",
    "gn:feature_code":"PPL",
    "gn:name":"Ab\u016b Baqarah",
    "gn:population":0,
    "gn:timezone":"Asia/Muscat",
    "iso:country":"OM",
    "name:ara_x_preferred":[
        "\u0623\u0628\u0648 \u0628\u0642\u0631\u0629"
    ],
    "name:und_x_variant":[
        "B\u016b Baqarah",
        "Ab\u016b Baqarah",
        "Ab\u016b Baqrah"
    ],
    "wof:name":"Abu Baqarah",
    "wof:placetype":"locality"
},
  "geometry": {"coordinates":[56.40387,24.86801],"type":"Point"}
}