{
  "type": "Feature",
  "properties": {
    "gn:admin1_code":"01",
    "gn:asciiname":"Al Habbi",
    "gn:country_code":"OM",
    "gn:dem":367,
    "gn:feature_class":"P",
    "gn:feature_code":"PPL",
    "gn:name":"Al \u1e28abb\u012b",
    "gn:population":0,
    "gn:timezone":"Asia/Muscat",
    "iso:country":"OM",
    "name:ara_x_preferred":[
        "Al \u1e28ub\u012b"
    ],
    "name:ara_x_variant":[
        "\u0627\u0644\u062d\u0628\u064a"
    ],
    "name:und_x_variant":[
        "Al \u1e28abb\u012b",
        "Al \u1e24abb\u012b"
    ],
    "wof:name":"Al Habbi",
    "wof:placetype":"locality"
},
  "geometry": {"coordinates":[57.33815,22.6475],"type":"Point"}
}