{
  "type": "Feature",
  "properties": {
    "gn:admin1_code":"08",
    "gn:asciiname":"Rism",
    "gn:country_code":"OM",
    "gn:dem":448,
    "gn:feature_class":"P",
    "gn:feature_code":"PPL",
    "gn:name":"Rism",
    "gn:population":0,
    "gn:timezone":"Asia/Muscat",
    "iso:country":"OM",
    "name:nno_x_preferred":[
        "Rism"
    ],
    "wof:name":"Rism",
    "wof:placetype":"locality"
},
  "geometry": {"coordinates":[54.09194,17.13611],"type":"Point"}
}