{
  "type": "Feature",
  "properties": {
    "gn:admin1_code":"11",
    "gn:asciiname":"Al Qulay`ah",
    "gn:country_code":"OM",
    "gn:dem":183,
    "gn:feature_class":"P",
    "gn:feature_code":"PPL",
    "gn:name":"Al Qulay\u2018ah",
    "gn:population":0,
    "gn:timezone":"Asia/Muscat",
    "iso:country":"OM",
    "name:ara_x_preferred":[
        "\u0627\u0644\u0642\u0644\u064a\u0639\u0629"
    ],
    "name:und_x_variant":[
        "Qulayyah",
        "Al Qulay\u2018ah"
    ],
    "wof:name":"Al Qulay`ah",
    "wof:placetype":"locality"
},
  "geometry": {"coordinates":[57.1165,23.75927],"type":"Point"}
}