{
  "type": "Feature",
  "properties": {
    "gn:admin1_code":"07",
    "gn:asciiname":"Khatr",
    "gn:country_code":"OM",
    "gn:dem":1088,
    "gn:feature_class":"P",
    "gn:feature_code":"PPL",
    "gn:name":"Khatr",
    "gn:population":0,
    "gn:timezone":"Asia/Muscat",
    "iso:country":"OM",
    "wof:name":"Khatr",
    "wof:placetype":"locality"
},
  "geometry": {"coordinates":[56.16639,25.66583],"type":"Point"}
}