{
  "type": "Feature",
  "properties": {
    "gn:admin1_code":"01",
    "gn:asciiname":"Al `Ayshi",
    "gn:country_code":"OM",
    "gn:dem":586,
    "gn:feature_class":"P",
    "gn:feature_code":"PPL",
    "gn:name":"Al \u2018Aysh\u012b",
    "gn:population":0,
    "gn:timezone":"Asia/Muscat",
    "iso:country":"OM",
    "name:ara_x_preferred":[
        "\u0627\u0644\u0639\u064a\u0634\u064a"
    ],
    "name:und_x_variant":[
        "Al \u2018Aysh",
        "Al \u2018Ayshah",
        "Al \u2018Aysh\u012b"
    ],
    "wof:name":"Al `Ayshi",
    "wof:placetype":"locality"
},
  "geometry": {"coordinates":[57.13511999999999,23.04035],"type":"Point"}
}