{
  "type": "Feature",
  "properties": {
    "gn:admin1_code":"11",
    "gn:asciiname":"At Tawi",
    "gn:country_code":"OM",
    "gn:dem":499,
    "gn:feature_class":"P",
    "gn:feature_code":"PPL",
    "gn:name":"A\u0163 \u0162aw\u012b",
    "gn:population":0,
    "gn:timezone":"Asia/Muscat",
    "iso:country":"OM",
    "name:ara_x_preferred":[
        "\u0627\u0644\u0637\u0651\u0648\u064a"
    ],
    "name:und_x_variant":[
        "\u0162aw\u012b al \u1e28ayl",
        "A\u0163 \u0162aw\u012b",
        "A\u1e6d \u1e6caw\u012b"
    ],
    "wof:name":"At Tawi",
    "wof:placetype":"locality"
},
  "geometry": {"coordinates":[56.31186,24.38389],"type":"Point"}
}