{
  "type": "Feature",
  "properties": {
    "gn:admin1_code":"08",
    "gn:asciiname":"Sakum",
    "gn:country_code":"OM",
    "gn:dem":925,
    "gn:feature_class":"P",
    "gn:feature_code":"PPL",
    "gn:name":"Sak\u016bm",
    "gn:population":0,
    "gn:timezone":"Asia/Muscat",
    "iso:country":"OM",
    "name:ara_x_preferred":[
        "\u0633\u0643\u0648\u0645"
    ],
    "name:und_x_variant":[
        "Sak\u016bm"
    ],
    "wof:name":"Sakum",
    "wof:placetype":"locality"
},
  "geometry": {"coordinates":[53.3445,16.80155],"type":"Point"}
}