{
  "type": "Feature",
  "properties": {
    "gn:admin1_code":"04",
    "gn:asciiname":"Taywah",
    "gn:country_code":"OM",
    "gn:dem":20,
    "gn:feature_class":"P",
    "gn:feature_code":"PPL",
    "gn:name":"Taywah",
    "gn:population":0,
    "gn:timezone":"Asia/Muscat",
    "iso:country":"OM",
    "name:ara_x_preferred":[
        "\u0162\u012bw\u012b"
    ],
    "name:ara_x_variant":[
        "\u0637\u064a\u0648\u064a"
    ],
    "name:und_x_variant":[
        "Taiwa",
        "Taywah",
        "Taiwi",
        "Tiwa",
        "\u1e6c\u012bw\u012b"
    ],
    "wof:name":"Taywah",
    "wof:placetype":"locality"
},
  "geometry": {"coordinates":[59.25796,22.82608],"type":"Point"}
}