{
  "type": "Feature",
  "properties": {
    "gn:admin1_code":"08",
    "gn:asciiname":"Kerral",
    "gn:country_code":"OM",
    "gn:dem":453,
    "gn:feature_class":"P",
    "gn:feature_code":"PPL",
    "gn:name":"Kerral",
    "gn:population":0,
    "gn:timezone":"Asia/Muscat",
    "iso:country":"OM",
    "name:ara_x_preferred":[
        "\u0643\u064a\u0631\u0644"
    ],
    "name:und_x_variant":[
        "K\u012bral"
    ],
    "wof:name":"Kerral",
    "wof:placetype":"locality"
},
  "geometry": {"coordinates":[54.50997,17.09305],"type":"Point"}
}