{
  "type": "Feature",
  "properties": {
    "gn:admin1_code":"04",
    "gn:asciiname":"Al Jawabi",
    "gn:country_code":"OM",
    "gn:dem":56,
    "gn:feature_class":"P",
    "gn:feature_code":"PPL",
    "gn:name":"Al Jaw\u0101b\u012b",
    "gn:population":0,
    "gn:timezone":"Asia/Muscat",
    "iso:country":"OM",
    "name:und_x_variant":[
        "Juwayb\u012b",
        "Juwaibi",
        "Al Jaw\u0101b\u012b"
    ],
    "wof:name":"Al Jawabi",
    "wof:placetype":"locality"
},
  "geometry": {"coordinates":[59.47872,22.03712],"type":"Point"}
}