{
  "type": "Feature",
  "properties": {
    "gn:admin1_code":"06",
    "gn:asciiname":"Munayzif",
    "gn:country_code":"OM",
    "gn:dem":207,
    "gn:feature_class":"P",
    "gn:feature_code":"PPL",
    "gn:name":"Munayzif",
    "gn:population":0,
    "gn:timezone":"Asia/Muscat",
    "iso:country":"OM",
    "wof:name":"Munayzif",
    "wof:placetype":"locality"
},
  "geometry": {"coordinates":[58.72028,23.25833],"type":"Point"}
}