{
  "type": "Feature",
  "properties": {
    "gn:country":"OM",
    "gn:fcode":"PPL",
    "gn:population":0,
    "iso:country":"OM",
    "name:ara_x_preferred":[
        "\u0631\u0648\u064a"
    ],
    "name:ara_x_variant":[
        "Ruw\u012b"
    ],
    "name:eng_x_preferred":[
        "Ruwi"
    ],
    "name:eng_x_variant":[
        "Ruw\u012b",
        "Ruwi"
    ],
    "qs:gn_adm0_cc":"OM",
    "qs:gn_fcode":"PPL",
    "qs:gn_local":287286,
    "qs:gn_nam_loc":"\u0645\u0633\u0642\u0637, \u0645\u0633\u0642\u0637, \u0645\u0633\u0642\u0637, OM",
    "qs:gn_namadm1":"06",
    "qs:gn_name":"Ruw\u012b",
    "qs:local_max":1860,
    "qs:local_sum":6504,
    "qs:localhoods":14,
    "qs:name":"\u0631\u0648\u064a",
    "qs:name_adm0":"\u0639\u0645\u0627\u0646",
    "qs:name_adm1":"\u0645\u0633\u0642\u0637",
    "qs:name_adm2":"\u0645\u0633\u0642\u0637",
    "qs:name_en":"Ruwi",
    "qs:name_local":"\u0645\u0633\u0642\u0637",
    "qs:photo_max":11,
    "qs:photo_sum":35,
    "qs:placetype":"Suburb",
    "qs:quad_count":8,
    "qs:woe_adm0":23424898,
    "qs:woe_adm1":2346260,
    "qs:woe_adm2":55927093,
    "qs:woe_lau":0,
    "qs:woe_local":2268284,
    "qs:woe_ver":"7.10.0",
    "qs_pg:aaroncc":"OM",
    "qs_pg:gn_country":"OM",
    "qs_pg:gn_fcode":"PPL",
    "qs_pg:gn_pop":0,
    "qs_pg:name":"\u0631\u0648\u064a",
    "qs_pg:name_adm0":"\u0639\u0645\u0627\u0646",
    "qs_pg:name_adm1":"\u0645\u0633\u0642\u0637",
    "qs_pg:photos":40,
    "qs_pg:photos_1k":8,
    "qs_pg:photos_9k":1,
    "qs_pg:photos_9r":2,
    "qs_pg:photos_all":40,
    "qs_pg:photos_sr":2,
    "qs_pg:pop_sr":0,
    "qs_pg:qs_pg_placetype":"neighbourhood",
    "qs_pg:qs_pg_placetype_gp":"Suburb",
    "qs_pg:woe_adm0":23424898,
    "wof:lang":[
        "ara"
    ],
    "wof:name":"\u0631\u0648\u064a",
    "wof:placetype":"neighbourhood"
},
  "geometry": {"coordinates":[58.547821,23.593075],"type":"Point"}
}