{
  "type": "Feature",
  "properties": {
    "gn:admin1_code":"10",
    "gn:asciiname":"Safwan",
    "gn:country_code":"OM",
    "gn:dem":336,
    "gn:feature_class":"P",
    "gn:feature_code":"PPL",
    "gn:name":"\u015eafw\u0101n",
    "gn:population":0,
    "gn:timezone":"Asia/Muscat",
    "iso:country":"OM",
    "name:ara_x_preferred":[
        "\u0635\u0641\u0648\u0627\u0646"
    ],
    "name:arz_x_preferred":[
        "\u0635\u0641\u0648\u0627\u0646"
    ],
    "name:pol_x_preferred":[
        "Safwan"
    ],
    "name:rus_x_preferred":[
        "\u0421\u0430\u0444\u0432\u0430\u043d"
    ],
    "name:spa_x_preferred":[
        "Safwan"
    ],
    "name:swe_x_preferred":[
        "Safwan"
    ],
    "name:und_x_variant":[
        "\u015eafw\u0101n",
        "\u1e62afw\u0101n"
    ],
    "name:urd_x_preferred":[
        "\u0635\u0641\u0648\u0627\u0646"
    ],
    "wof:name":"Safwan",
    "wof:placetype":"locality"
},
  "geometry": {"coordinates":[55.84158000000001,24.56037],"type":"Point"}
}