{
  "type": "Feature",
  "properties": {
    "gn:admin1_code":"08",
    "gn:asciiname":"South Sahnawt",
    "gn:country_code":"OM",
    "gn:dem":22,
    "gn:feature_class":"P",
    "gn:feature_code":"PPL",
    "gn:name":"South Sahnawt",
    "gn:population":0,
    "gn:timezone":"Asia/Muscat",
    "iso:country":"OM",
    "name:ara_x_preferred":[
        "\u0635\u062d\u0644\u0646\u0648\u062a \u0627\u0644\u062c\u0646\u0648\u0628\u064a\u0629"
    ],
    "name:und_x_variant":[
        "\u015ea\u1e29alnawt al Jan\u016bb\u012byah",
        "South Sahnawt"
    ],
    "wof:name":"South Sahnawt",
    "wof:placetype":"locality"
},
  "geometry": {"coordinates":[54.19425,17.05613],"type":"Point"}
}