{
  "type": "Feature",
  "properties": {
    "gn:admin1_code":"01",
    "gn:asciiname":"Mahbub",
    "gn:country_code":"OM",
    "gn:dem":354,
    "gn:feature_class":"P",
    "gn:feature_code":"PPL",
    "gn:name":"Ma\u1e29b\u016bb",
    "gn:population":0,
    "gn:timezone":"Asia/Muscat",
    "iso:country":"OM",
    "name:und_x_variant":[
        "Ma\u1e29b\u016bb"
    ],
    "wof:name":"Mahbub",
    "wof:placetype":"locality"
},
  "geometry": {"coordinates":[58.01917,23.31861],"type":"Point"}
}