{
  "type": "Feature",
  "properties": {
    "gn:admin1_code":"01",
    "gn:asciiname":"Al Ghubayrah",
    "gn:country_code":"OM",
    "gn:dem":702,
    "gn:feature_class":"P",
    "gn:feature_code":"PPL",
    "gn:name":"Al Ghubayrah",
    "gn:population":0,
    "gn:timezone":"Asia/Muscat",
    "iso:country":"OM",
    "name:ara_x_preferred":[
        "\u0627\u0644\u063a\u0628\u064a\u0631\u0629"
    ],
    "name:und_x_variant":[
        "Al Ghab\u012brah",
        "Al Ghubayrah"
    ],
    "wof:name":"Al Ghubayrah",
    "wof:placetype":"locality"
},
  "geometry": {"coordinates":[57.3736,23.24621],"type":"Point"}
}