{
  "type": "Feature",
  "properties": {
    "gn:admin1_code":"08",
    "gn:asciiname":"Shahab",
    "gn:country_code":"OM",
    "gn:dem":807,
    "gn:feature_class":"P",
    "gn:feature_code":"PPL",
    "gn:name":"Shahab",
    "gn:population":0,
    "gn:timezone":"Asia/Muscat",
    "iso:country":"OM",
    "name:ara_x_preferred":[
        "\u0634\u0647\u0628"
    ],
    "name:fas_x_preferred":[
        "\u0634\u0647\u0627\u0628"
    ],
    "name:ita_x_preferred":[
        "Shahab"
    ],
    "name:jpn_x_preferred":[
        "\u30b7\u30e3\u30cf\u30d6"
    ],
    "name:rus_x_preferred":[
        "\u0428\u0430\u0445\u0430\u0431"
    ],
    "name:swe_x_preferred":[
        "Shahab"
    ],
    "name:tur_x_preferred":[
        "\u015eahab"
    ],
    "wof:name":"Shahab",
    "wof:placetype":"locality"
},
  "geometry": {"coordinates":[54.22767,17.26067],"type":"Point"}
}