{
  "type": "Feature",
  "properties": {
    "gn:admin1_code":"06",
    "gn:asciiname":"Ash Sha`biyah",
    "gn:country_code":"OM",
    "gn:dem":176,
    "gn:feature_class":"P",
    "gn:feature_code":"PPL",
    "gn:name":"Ash Sha\u2018b\u012byah",
    "gn:population":0,
    "gn:timezone":"Asia/Muscat",
    "iso:country":"OM",
    "name:ara_x_preferred":[
        "\u0627\u0644\u0634\u0639\u0628\u064a\u0629"
    ],
    "name:und_x_variant":[
        "Ash Sha\u2018b\u012byah"
    ],
    "wof:name":"Ash Sha`biyah",
    "wof:placetype":"locality"
},
  "geometry": {"coordinates":[58.54995,23.35328],"type":"Point"}
}