{
  "type": "Feature",
  "properties": {
    "gn:admin1_code":"06",
    "gn:asciiname":"Fayq",
    "gn:country_code":"OM",
    "gn:dem":195,
    "gn:feature_class":"P",
    "gn:feature_code":"PPL",
    "gn:name":"Fayq",
    "gn:population":0,
    "gn:timezone":"Asia/Muscat",
    "iso:country":"OM",
    "name:ara_x_preferred":[
        "\u0641\u064a\u0642"
    ],
    "wof:name":"Fayq",
    "wof:placetype":"locality"
},
  "geometry": {"coordinates":[58.94641,23.04945],"type":"Point"}
}