{
  "type": "Feature",
  "properties": {
    "gn:admin1_code":"12",
    "gn:asciiname":"Al Wasil",
    "gn:country_code":"OM",
    "gn:dem":316,
    "gn:feature_class":"P",
    "gn:feature_code":"PPL",
    "gn:name":"Al W\u0101\u015fil",
    "gn:population":0,
    "gn:timezone":"Asia/Muscat",
    "iso:country":"OM",
    "name:ara_x_preferred":[
        "Al W\u0101\u015fil"
    ],
    "name:ara_x_variant":[
        "\u0627\u0644\u0648\u0627\u0635\u0644"
    ],
    "name:und_x_variant":[
        "W\u0101\u015fil",
        "S\u016bq Bad\u012byah",
        "Al W\u0101\u1e63il"
    ],
    "wof:name":"Al Wasil",
    "wof:placetype":"locality"
},
  "geometry": {"coordinates":[58.74287,22.50083],"type":"Point"}
}