{
  "type": "Feature",
  "properties": {
    "gn:admin1_code":"07",
    "gn:asciiname":"Subtan",
    "gn:country_code":"OM",
    "gn:dem":1325,
    "gn:feature_class":"P",
    "gn:feature_code":"PPL",
    "gn:name":"Sub\u0163\u0101n",
    "gn:population":0,
    "gn:timezone":"Asia/Muscat",
    "iso:country":"OM",
    "name:ara_x_preferred":[
        "Sub\u0163\u0101n"
    ],
    "name:und_x_variant":[
        "Sabtan"
    ],
    "wof:name":"Subtan",
    "wof:placetype":"locality"
},
  "geometry": {"coordinates":[56.24861,25.84389],"type":"Point"}
}