{
  "type": "Feature",
  "properties": {
    "gn:country":"OM",
    "gn:fcode":"PPLA",
    "gn:pop":17904,
    "iso:country":"OM",
    "name:ara_x_preferred":[
        "\u062e\u0635\u0628"
    ],
    "name:ara_x_variant":[
        "\u0648\u0644\u0627\u064a\u0629 \u062e\u0635\u0628"
    ],
    "name:ben_x_preferred":[
        "\u0995\u09be\u09b8\u09be\u09ac"
    ],
    "name:bul_x_preferred":[
        "\u041a\u0445\u0430\u0441\u0430\u0431"
    ],
    "name:ceb_x_preferred":[
        "Khasab"
    ],
    "name:ces_x_preferred":[
        "Chasab"
    ],
    "name:dan_x_preferred":[
        "Khasab"
    ],
    "name:deu_x_preferred":[
        "al-Chasab"
    ],
    "name:deu_x_variant":[
        "Al-Chasab"
    ],
    "name:ell_x_preferred":[
        "\u039a\u03b1\u03c3\u03ac\u03bc\u03c0"
    ],
    "name:eng_x_preferred":[
        "Khasab"
    ],
    "name:eng_x_variant":[
        "Kha\u015fab"
    ],
    "name:fas_x_preferred":[
        "\u062e\u0635\u0628"
    ],
    "name:fin_x_preferred":[
        "Khasab"
    ],
    "name:fra_x_preferred":[
        "Khasab"
    ],
    "name:fra_x_variant":[
        "Al-Khasab"
    ],
    "name:guj_x_preferred":[
        "\u0a96\u0ab8\u0aac"
    ],
    "name:hbs_x_preferred":[
        "Hasab"
    ],
    "name:heb_x_preferred":[
        "\u05d7'\u05e1\u05d0\u05d1"
    ],
    "name:hin_x_preferred":[
        "\u0916\u0938\u092c"
    ],
    "name:ind_x_preferred":[
        "Khasab"
    ],
    "name:ita_x_preferred":[
        "Khasab"
    ],
    "name:jpn_x_preferred":[
        "\u30cf\u30b5\u30d6"
    ],
    "name:kan_x_preferred":[
        "\u0c96\u0cb8\u0cbe\u0cac\u0ccd"
    ],
    "name:kor_x_preferred":[
        "\ud558\uc0ac\ube0c"
    ],
    "name:lav_x_preferred":[
        "\u010cabasa"
    ],
    "name:lit_x_preferred":[
        "Chasabas"
    ],
    "name:mar_x_preferred":[
        "\u0916\u0938\u092c"
    ],
    "name:msa_x_preferred":[
        "Khasab"
    ],
    "name:nld_x_preferred":[
        "Khasab"
    ],
    "name:nno_x_preferred":[
        "Khasab"
    ],
    "name:nob_x_preferred":[
        "Khasab"
    ],
    "name:pol_x_preferred":[
        "Chasab"
    ],
    "name:por_x_preferred":[
        "Cassapo"
    ],
    "name:rus_x_preferred":[
        "\u042d\u043b\u044c-\u0425\u0430\u0441\u0430\u0431"
    ],
    "name:sin_x_preferred":[
        "\u0d9b\u0dc3\u0db6\u0dca"
    ],
    "name:spa_x_preferred":[
        "Jasab"
    ],
    "name:swe_x_preferred":[
        "Khasab"
    ],
    "name:tam_x_preferred":[
        "\u0b9a\u0bc7\u0b95\u0bcc"
    ],
    "name:tel_x_preferred":[
        "\u0c16\u0c38\u0c2c\u0c4d"
    ],
    "name:tha_x_preferred":[
        "\u0e40\u0e04\u0e32\u0e30\u0e28\u0e47\u0e2d\u0e1a"
    ],
    "name:tur_x_preferred":[
        "Khasab"
    ],
    "name:ukr_x_preferred":[
        "\u0415\u043b\u044c-\u0425\u0430\u0441\u0430\u0431"
    ],
    "name:unk_x_variant":[
        "Al Kha\u015fab"
    ],
    "name:urd_x_preferred":[
        "\u062e\u0635\u0628\u060c \u0639\u0645\u0627\u0646"
    ],
    "name:urd_x_variant":[
        "\u062e\u0635\u0628"
    ],
    "name:vie_x_preferred":[
        "Khasab"
    ],
    "name:zho_x_preferred":[
        "\u6d77\u585e\u535c"
    ],
    "qs:name":"Kha\u015fab",
    "qs:photos_9r":0,
    "qs:photos_sr":0,
    "qs:pop_sr":"6",
    "wd:wordcount":648,
    "wof:name":"Kha\u015fab",
    "wof:placetype":"locality",
    "wof:population":17904
},
  "geometry": {"coordinates":[56.24774,26.17993],"type":"Point"}
}