{
  "type": "Feature",
  "properties": {
    "gn:admin1_code":"08",
    "gn:asciiname":"Raythathey",
    "gn:country_code":"OM",
    "gn:dem":646,
    "gn:feature_class":"P",
    "gn:feature_code":"PPL",
    "gn:name":"Raythathey",
    "gn:population":0,
    "gn:timezone":"Asia/Muscat",
    "iso:country":"OM",
    "wof:name":"Raythathey",
    "wof:placetype":"locality"
},
  "geometry": {"coordinates":[54.39972,17.13944],"type":"Point"}
}