{
  "type": "Feature",
  "properties": {
    "gn:admin1_code":"06",
    "gn:asciiname":"`Abayah",
    "gn:country_code":"OM",
    "gn:dem":169,
    "gn:feature_class":"P",
    "gn:feature_code":"PPL",
    "gn:name":"\u2018Ab\u0101yah",
    "gn:population":0,
    "gn:timezone":"Asia/Muscat",
    "iso:country":"OM",
    "name:ara_x_preferred":[
        "\u0639\u0628\u0627\u064a\u0629"
    ],
    "name:und_x_variant":[
        "\u2018Ab\u0101yah"
    ],
    "wof:name":"`Abayah",
    "wof:placetype":"locality"
},
  "geometry": {"coordinates":[58.81334,23.17166],"type":"Point"}
}