{
  "type": "Feature",
  "properties": {
    "gn:admin1_code":"07",
    "gn:asciiname":"`Amis",
    "gn:country_code":"OM",
    "gn:dem":27,
    "gn:feature_class":"P",
    "gn:feature_code":"PPL",
    "gn:name":"\u2018Am\u012bs",
    "gn:population":0,
    "gn:timezone":"Asia/Muscat",
    "iso:country":"OM",
    "name:ara_x_preferred":[
        "\u2018Am\u012bs"
    ],
    "name:und_x_variant":[
        "Aimus"
    ],
    "wof:name":"`Amis",
    "wof:placetype":"locality"
},
  "geometry": {"coordinates":[56.38833,26.03944],"type":"Point"}
}