{
  "type": "Feature",
  "properties": {
    "gn:admin1_code":"08",
    "gn:asciiname":"Dubah",
    "gn:cc2":"OM",
    "gn:country_code":"OM",
    "gn:dem":624,
    "gn:feature_class":"P",
    "gn:feature_code":"PPL",
    "gn:name":"D\u016bbah",
    "gn:population":0,
    "gn:timezone":"Asia/Muscat",
    "iso:country":"OM",
    "name:und_x_variant":[
        "Dabah",
        "D\u016bbah"
    ],
    "wof:name":"Dubah",
    "wof:placetype":"locality"
},
  "geometry": {"coordinates":[54.02194,17.15333],"type":"Point"}
}