{
  "type": "Feature",
  "properties": {
    "gn:admin1_code":"07",
    "gn:asciiname":"Lakayym",
    "gn:country_code":"OM",
    "gn:dem":559,
    "gn:feature_class":"P",
    "gn:feature_code":"PPL",
    "gn:name":"Lakayym",
    "gn:population":0,
    "gn:timezone":"Asia/Muscat",
    "iso:country":"OM",
    "wof:name":"Lakayym",
    "wof:placetype":"locality"
},
  "geometry": {"coordinates":[56.26111,25.77083],"type":"Point"}
}