{
  "type": "Feature",
  "properties": {
    "iso:country":"OM",
    "qs:gn_pop":0,
    "qs:name":"Awqad",
    "qs:name_adm0":"\u0639\u0645\u0627\u0646",
    "qs:name_adm1":"\u0638\u0641\u0627\u0631",
    "qs:photos":23,
    "qs:photos_1k":5,
    "qs:photos_9k":1,
    "qs:photos_9r":1,
    "qs:photos_all":23,
    "qs:photos_sr":1,
    "qs:placetype":"Town",
    "qs:pop_sr":"0",
    "qs:woe_adm0":23424898,
    "wof:name":"Awqad",
    "wof:placetype":"locality"
},
  "geometry": {"coordinates":[53.995998,16.964],"type":"Point"}
}