{
  "type": "Feature",
  "properties": {
    "gn:admin1_code":"01",
    "gn:asciiname":"Al Mazarah",
    "gn:country_code":"OM",
    "gn:dem":1588,
    "gn:feature_class":"P",
    "gn:feature_code":"PPL",
    "gn:name":"Al Maz\u0101rah",
    "gn:population":0,
    "gn:timezone":"Asia/Muscat",
    "iso:country":"OM",
    "name:und_x_variant":[
        "Al Maz\u0101rah"
    ],
    "wof:name":"Al Mazarah",
    "wof:placetype":"locality"
},
  "geometry": {"coordinates":[57.31833,23.17361],"type":"Point"}
}