{
  "type": "Feature",
  "properties": {
    "gn:admin1_code":"11",
    "gn:asciiname":"Al Hazirah",
    "gn:country_code":"OM",
    "gn:dem":3,
    "gn:feature_class":"P",
    "gn:feature_code":"PPL",
    "gn:name":"Al \u1e28az\u0327\u012brah",
    "gn:population":0,
    "gn:timezone":"Asia/Muscat",
    "iso:country":"OM",
    "name:ara_x_preferred":[
        "\u0627\u0644\u062d\u0638\u064a\u0631\u0629"
    ],
    "name:und_x_variant":[
        "\u1e28a\u1e11\u012brah",
        "Al \u1e28az\u0327\u012brah",
        "Al \u1e24a\u1e93\u012brah"
    ],
    "wof:name":"Al Hazirah",
    "wof:placetype":"locality"
},
  "geometry": {"coordinates":[56.743,24.37145],"type":"Point"}
}