{
  "type": "Feature",
  "properties": {
    "iso:country":"OM",
    "name:ara_x_preferred":[
        "\u0627\u0644\u0645\u063a\u0633\u064a\u0644"
    ],
    "name:eng_x_preferred":[
        "Al Mughsayl"
    ],
    "qs:gn_pop":0,
    "qs:name":"\u0627\u0644\u0645\u063a\u0633\u064a\u0644",
    "qs:name_adm0":"\u0639\u0645\u0627\u0646",
    "qs:name_adm1":"\u0638\u0641\u0627\u0631",
    "qs:photos":275,
    "qs:photos_1k":56,
    "qs:photos_9k":1,
    "qs:photos_9r":4,
    "qs:photos_all":275,
    "qs:photos_sr":5,
    "qs:placetype":"Town",
    "qs:pop_sr":"0",
    "qs:woe_adm0":23424898,
    "wof:name":"Al Mughsayl",
    "wof:placetype":"locality"
},
  "geometry": {"coordinates":[53.775329,16.879871],"type":"Point"}
}