{
  "type": "Feature",
  "properties": {
    "gn:admin1_code":"01",
    "gn:asciiname":"`Ilayat al Jarir",
    "gn:country_code":"OM",
    "gn:dem":1841,
    "gn:feature_class":"P",
    "gn:feature_code":"PPL",
    "gn:name":"\u2018Il\u0101yat al Jar\u012br",
    "gn:population":0,
    "gn:timezone":"Asia/Muscat",
    "iso:country":"OM",
    "name:ara_x_preferred":[
        "\u0639\u0644\u0627\u064a\u0629 \u0627\u0644\u062c\u0631\u064a\u0631"
    ],
    "name:und_x_variant":[
        "Al Ghar\u012br \u2018Al\u0101yah",
        "\u2018Il\u0101yat al Jar\u012br"
    ],
    "wof:name":"`Ilayat al Jarir",
    "wof:placetype":"locality"
},
  "geometry": {"coordinates":[57.5564,23.09788],"type":"Point"}
}