{
  "type": "Feature",
  "properties": {
    "gn:admin1_code":"12",
    "gn:asciiname":"As Sabal",
    "gn:country_code":"OM",
    "gn:dem":434,
    "gn:feature_class":"P",
    "gn:feature_code":"PPL",
    "gn:name":"A\u015f \u015eabal",
    "gn:population":0,
    "gn:timezone":"Asia/Muscat",
    "iso:country":"OM",
    "name:und_x_variant":[
        "A\u015f \u015eabal"
    ],
    "wof:name":"As Sabal",
    "wof:placetype":"locality"
},
  "geometry": {"coordinates":[58.53278,23.11917],"type":"Point"}
}