{
  "type": "Feature",
  "properties": {
    "gn:country":"OM",
    "gn:fcode":"PPL",
    "gn:population":50223,
    "iso:country":"OM",
    "name:und_x_variant":[
        "Khabura"
    ],
    "qs:name":"Al Kh\u0101b\u016brah",
    "qs:photos_9r":0,
    "qs:photos_sr":0,
    "qs:pop_sr":"8",
    "wof:name":"Al Kh\u0101b\u016brah",
    "wof:placetype":"locality",
    "wof:population":50223
},
  "geometry": {"coordinates":[57.09838,23.98864],"type":"Point"}
}