{
  "type": "Feature",
  "properties": {
    "gn:admin1_code":"08",
    "gn:asciiname":"Anjar",
    "gn:country_code":"OM",
    "gn:dem":840,
    "gn:feature_class":"P",
    "gn:feature_code":"PPL",
    "gn:name":"Anjar",
    "gn:population":0,
    "gn:timezone":"Asia/Muscat",
    "iso:country":"OM",
    "name:ara_x_preferred":[
        "\u0623\u0646\u062c\u0627\u0631"
    ],
    "name:cat_x_preferred":[
        "Anjar"
    ],
    "name:ceb_x_preferred":[
        "Anjar"
    ],
    "name:swe_x_preferred":[
        "Anjar"
    ],
    "name:und_x_variant":[
        "Anj\u0101r"
    ],
    "name:vie_x_preferred":[
        "Anjar"
    ],
    "wof:name":"Anjar",
    "wof:placetype":"locality"
},
  "geometry": {"coordinates":[53.95455,17.10126],"type":"Point"}
}