{
  "type": "Feature",
  "properties": {
    "gn:admin1_code":"08",
    "gn:asciiname":"Ghadit",
    "gn:country_code":"OM",
    "gn:dem":751,
    "gn:feature_class":"P",
    "gn:feature_code":"PPL",
    "gn:name":"Ghadit",
    "gn:population":0,
    "gn:timezone":"Asia/Muscat",
    "iso:country":"OM",
    "name:ara_x_preferred":[
        "\u063a\u062f\u064a\u062a"
    ],
    "name:und_x_variant":[
        "Ghudayt",
        "Ghadit"
    ],
    "wof:name":"Ghadit",
    "wof:placetype":"locality"
},
  "geometry": {"coordinates":[54.26161999999999,17.21381],"type":"Point"}
}