{
  "type": "Feature",
  "properties": {
    "gn:admin1_code":"07",
    "gn:asciiname":"Wa`ab al Laff",
    "gn:country_code":"OM",
    "gn:dem":40,
    "gn:feature_class":"P",
    "gn:feature_code":"PPL",
    "gn:name":"Wa\u2018ab al Laff",
    "gn:population":0,
    "gn:timezone":"Asia/Muscat",
    "iso:country":"OM",
    "name:ara_x_preferred":[
        "\u0648\u0639\u0628 \u0627\u0644\u0644\u0651\u0641"
    ],
    "name:und_x_variant":[
        "Wa\u2018ab al Lif",
        "Wa\u2018ab al Laff",
        "Wa\u2018b al Laf"
    ],
    "wof:name":"Wa`ab al Laff",
    "wof:placetype":"locality"
},
  "geometry": {"coordinates":[56.14957,26.10263],"type":"Point"}
}