{
  "type": "Feature",
  "properties": {
    "gn:admin1_code":"02",
    "gn:asciiname":"Sumaysim",
    "gn:country_code":"OM",
    "gn:dem":746,
    "gn:feature_class":"P",
    "gn:feature_code":"PPL",
    "gn:name":"Sumaysim",
    "gn:population":0,
    "gn:timezone":"Asia/Muscat",
    "iso:country":"OM",
    "name:ara_x_preferred":[
        "\u0633\u0645\u064a\u0633\u0645"
    ],
    "name:und_x_variant":[
        "Simaysim"
    ],
    "wof:name":"Sumaysim",
    "wof:placetype":"locality"
},
  "geometry": {"coordinates":[57.45565,23.21255],"type":"Point"}
}