{
  "type": "Feature",
  "properties": {
    "iso:country":"OM",
    "name:unk_x_variant":[
        "Bay\u2018ah"
    ],
    "qs:gn_country":"OM",
    "qs:gn_fcode":"PPL",
    "qs:gn_pop":0,
    "qs:name":"Bayah",
    "qs:name_adm0":"\u0639\u0645\u0627\u0646",
    "qs:name_adm1":"\u0645\u0633\u0646\u062f\u0645",
    "qs:photos":33,
    "qs:photos_1k":7,
    "qs:photos_9k":1,
    "qs:photos_9r":2,
    "qs:photos_all":33,
    "qs:photos_sr":2,
    "qs:placetype":"Town",
    "qs:pop_sr":"0",
    "qs:woe_adm0":23424898,
    "wd:wordcount":23,
    "wof:name":"Bayah",
    "wof:placetype":"locality"
},
  "geometry": {"coordinates":[56.26417,25.67444],"type":"Point"}
}