{
  "type": "Feature",
  "properties": {
    "gn:admin1_code":"01",
    "gn:asciiname":"Bilad ash Shuhum",
    "gn:country_code":"OM",
    "gn:dem":882,
    "gn:feature_class":"P",
    "gn:feature_code":"PPL",
    "gn:name":"Bil\u0101d ash Shuh\u016bm",
    "gn:population":0,
    "gn:timezone":"Asia/Muscat",
    "iso:country":"OM",
    "name:ara_x_preferred":[
        "\u0628\u0644\u0627\u062f \u0627\u0644\u0634\u0647\u0648\u0645"
    ],
    "name:und_x_variant":[
        "Bil\u0101d Shah\u016bm",
        "Bil\u0101d ash Shuh\u016bm"
    ],
    "wof:name":"Bilad ash Shuhum",
    "wof:placetype":"locality"
},
  "geometry": {"coordinates":[56.98846999999999,23.39634],"type":"Point"}
}