{
  "type": "Feature",
  "properties": {
    "gn:admin1_code":"11",
    "gn:asciiname":"Sur Yal Bu Rashid",
    "gn:country_code":"OM",
    "gn:dem":12,
    "gn:feature_class":"P",
    "gn:feature_code":"PPL",
    "gn:name":"S\u016br Y\u0101l B\u016b Rash\u012bd",
    "gn:population":0,
    "gn:timezone":"Asia/Muscat",
    "iso:country":"OM",
    "name:und_x_variant":[
        "S\u016br \u0100l B\u016b Rash\u012bd",
        "S\u016br Y\u0101l B\u016b Rash\u012bd"
    ],
    "wof:name":"Sur Yal Bu Rashid",
    "wof:placetype":"locality"
},
  "geometry": {"coordinates":[57.26229,23.87702],"type":"Point"}
}