{
  "type": "Feature",
  "properties": {
    "gn:admin1_code":"10",
    "gn:asciiname":"Hayl",
    "gn:country_code":"OM",
    "gn:dem":523,
    "gn:feature_class":"P",
    "gn:feature_code":"PPL",
    "gn:name":"\u1e28ayl",
    "gn:population":0,
    "gn:timezone":"Asia/Muscat",
    "iso:country":"OM",
    "name:und_x_variant":[
        "\u1e28ayl Bin Suwayd\u0101n",
        "Hail Bin-Suwaid\u0101n",
        "Hail",
        "\u1e28ayl"
    ],
    "wof:name":"Hayl",
    "wof:placetype":"locality"
},
  "geometry": {"coordinates":[56.24678,24.19893],"type":"Point"}
}