{
  "type": "Feature",
  "properties": {
    "gn:admin1_code":"08",
    "gn:asciiname":"Enhorelah",
    "gn:country_code":"OM",
    "gn:dem":450,
    "gn:feature_class":"P",
    "gn:feature_code":"PPL",
    "gn:name":"Enhorelah",
    "gn:population":0,
    "gn:timezone":"Asia/Muscat",
    "iso:country":"OM",
    "wof:name":"Enhorelah",
    "wof:placetype":"locality"
},
  "geometry": {"coordinates":[54.13306,17.17722],"type":"Point"}
}