{
  "type": "Feature",
  "properties": {
    "gn:admin1_code":"08",
    "gn:asciiname":"Tyakh",
    "gn:country_code":"OM",
    "gn:dem":825,
    "gn:feature_class":"P",
    "gn:feature_code":"PPL",
    "gn:name":"Tyakh",
    "gn:population":0,
    "gn:timezone":"Asia/Muscat",
    "iso:country":"OM",
    "name:ara_x_preferred":[
        "\u0637\u064a\u0627\u062e"
    ],
    "name:und_x_variant":[
        "\u0162iy\u0101kh",
        "Tyakh"
    ],
    "wof:name":"Tyakh",
    "wof:placetype":"locality"
},
  "geometry": {"coordinates":[54.43158,17.20416],"type":"Point"}
}