{
  "type": "Feature",
  "properties": {
    "gn:admin1_code":"10",
    "gn:asciiname":"Al `Ubaylah",
    "gn:country_code":"OM",
    "gn:dem":701,
    "gn:feature_class":"P",
    "gn:feature_code":"PPL",
    "gn:name":"Al \u2018Ubaylah",
    "gn:population":0,
    "gn:timezone":"Asia/Muscat",
    "iso:country":"OM",
    "name:und_x_variant":[
        "\u2018Ubaylah",
        "Abailah",
        "Al \u2018Ubaylah"
    ],
    "wof:name":"Al `Ubaylah",
    "wof:placetype":"locality"
},
  "geometry": {"coordinates":[56.16061,24.26494],"type":"Point"}
}