{
  "type": "Feature",
  "properties": {
    "gn:admin1_code":"11",
    "gn:asciiname":"Al Jall",
    "gn:country_code":"OM",
    "gn:dem":711,
    "gn:feature_class":"P",
    "gn:feature_code":"PPL",
    "gn:name":"Al Jall",
    "gn:population":0,
    "gn:timezone":"Asia/Muscat",
    "iso:country":"OM",
    "name:ara_x_preferred":[
        "\u0627\u0644\u062c\u0644"
    ],
    "name:und_x_variant":[
        "Al Jull",
        "Al Jall",
        "Al Jul"
    ],
    "wof:name":"Al Jall",
    "wof:placetype":"locality"
},
  "geometry": {"coordinates":[56.40964,23.92966],"type":"Point"}
}