{
  "type": "Feature",
  "properties": {
    "gn:admin1_code":"10",
    "gn:asciiname":"Rihani",
    "gn:country_code":"OM",
    "gn:dem":259,
    "gn:feature_class":"P",
    "gn:feature_code":"PPL",
    "gn:name":"Rihani",
    "gn:population":0,
    "gn:timezone":"Asia/Muscat",
    "iso:country":"OM",
    "name:ara_x_preferred":[
        "Ar R\u0101y\u1e29\u0101n\u012b"
    ],
    "name:ara_x_variant":[
        "\u0627\u0644\u0631\u064a\u062d\u0627\u0646\u064a"
    ],
    "name:und_x_variant":[
        "Ar R\u012b\u1e29\u0101n\u012b",
        "Ar R\u0101y\u1e25\u0101n\u012b"
    ],
    "wof:name":"Rihani",
    "wof:placetype":"locality"
},
  "geometry": {"coordinates":[55.95415,23.62087],"type":"Point"}
}