{
  "type": "Feature",
  "properties": {
    "gn:admin1_code":"12",
    "gn:asciiname":"Al Mu`tarid",
    "gn:country_code":"OM",
    "gn:dem":400,
    "gn:feature_class":"P",
    "gn:feature_code":"PPL",
    "gn:name":"Al Mu\u2018tari\u1e11",
    "gn:population":0,
    "gn:timezone":"Asia/Muscat",
    "iso:country":"OM",
    "name:ara_x_preferred":[
        "\u0627\u0644\u0645\u0639\u062a\u0631\u0636"
    ],
    "name:und_x_variant":[
        "Al Mu\u2018tarid",
        "Al Mu\u2018tari\u1e11",
        "Al Mu\u2018tru\u1e0d"
    ],
    "wof:name":"Al Mu`tarid",
    "wof:placetype":"locality"
},
  "geometry": {"coordinates":[58.65201,22.72462],"type":"Point"}
}