{
  "type": "Feature",
  "properties": {
    "gn:admin1_code":"06",
    "gn:asciiname":"Bamah",
    "gn:country_code":"OM",
    "gn:dem":7,
    "gn:feature_class":"P",
    "gn:feature_code":"PPL",
    "gn:name":"Bamah",
    "gn:population":0,
    "gn:timezone":"Asia/Muscat",
    "iso:country":"OM",
    "name:ara_x_preferred":[
        "\u0628\u0645\u0629"
    ],
    "name:und_x_variant":[
        "Bimma",
        "Bimah",
        "Bimmah",
        "Bamah"
    ],
    "wof:name":"Bamah",
    "wof:placetype":"locality"
},
  "geometry": {"coordinates":[59.13827,22.99],"type":"Point"}
}