{
  "type": "Feature",
  "properties": {
    "iso:country":"OM",
    "name:ara_x_preferred":[
        "\u0641\u0646\u0633"
    ],
    "name:und_x_variant":[
        "Fins"
    ],
    "qs:gn_country":"OM",
    "qs:gn_fcode":"PPL",
    "qs:gn_pop":0,
    "qs:name":"\u0641\u0627\u0646\u0633",
    "qs:name_adm0":"\u0639\u0645\u0627\u0646",
    "qs:name_adm1":"\u0645\u0633\u0642\u0637",
    "qs:photos":36,
    "qs:photos_1k":7,
    "qs:photos_9k":1,
    "qs:photos_9r":2,
    "qs:photos_all":36,
    "qs:photos_sr":2,
    "qs:placetype":"Town",
    "qs:pop_sr":"3",
    "qs:woe_adm0":23424898,
    "wof:name":"\u0641\u0627\u0646\u0633",
    "wof:placetype":"locality"
},
  "geometry": {"coordinates":[59.2115,22.92556],"type":"Point"}
}