{
  "type": "Feature",
  "properties": {
    "gn:admin1_code":"11",
    "gn:asciiname":"Al `Uwaynat",
    "gn:country_code":"OM",
    "gn:dem":1,
    "gn:feature_class":"P",
    "gn:feature_code":"PPL",
    "gn:name":"Al \u2018Uwayn\u0101t",
    "gn:population":0,
    "gn:timezone":"Asia/Muscat",
    "iso:country":"OM",
    "name:und_x_variant":[
        "Al \u2018Uwayn\u0101t"
    ],
    "wof:name":"Al `Uwaynat",
    "wof:placetype":"locality"
},
  "geometry": {"coordinates":[56.81481,24.27239],"type":"Point"}
}