{
  "type": "Feature",
  "properties": {
    "gn:admin1_code":"11",
    "gn:asciiname":"Al Baridah",
    "gn:country_code":"OM",
    "gn:dem":25,
    "gn:feature_class":"P",
    "gn:feature_code":"PPL",
    "gn:name":"Al B\u0101ridah",
    "gn:population":0,
    "gn:timezone":"Asia/Muscat",
    "iso:country":"OM",
    "name:ara_x_preferred":[
        "\u0627\u0644\u0628\u0627\u0631\u062f\u0629"
    ],
    "name:und_x_variant":[
        "Baridah",
        "Al B\u0101ridah",
        "Al B\u0101rdah"
    ],
    "wof:name":"Al Baridah",
    "wof:placetype":"locality"
},
  "geometry": {"coordinates":[57.49865,23.7858],"type":"Point"}
}