{
  "type": "Feature",
  "properties": {
    "gn:admin1_code":"01",
    "gn:asciiname":"An Nakhur",
    "gn:country_code":"OM",
    "gn:dem":946,
    "gn:feature_class":"P",
    "gn:feature_code":"PPL",
    "gn:name":"An Nakhur",
    "gn:population":0,
    "gn:timezone":"Asia/Muscat",
    "iso:country":"OM",
    "name:ara_x_preferred":[
        "\u0627\u0644\u0646\u062e\u0631"
    ],
    "name:und_x_variant":[
        "Nakhr",
        "An Nakhur",
        "An Nakhar"
    ],
    "wof:name":"An Nakhur",
    "wof:placetype":"locality"
},
  "geometry": {"coordinates":[57.21308000000001,23.20111],"type":"Point"}
}