{
  "type": "Feature",
  "properties": {
    "gn:admin1_code":"11",
    "gn:asciiname":"Mukhaylif",
    "gn:country_code":"OM",
    "gn:dem":3,
    "gn:feature_class":"P",
    "gn:feature_code":"PPL",
    "gn:name":"Mukhayl\u012bf",
    "gn:population":0,
    "gn:timezone":"Asia/Muscat",
    "iso:country":"OM",
    "name:und_x_variant":[
        "Al Mukhail\u012bf",
        "Makhail\u012bf",
        "Al Mukhayl\u012bf",
        "Muqay\u2018\u012bf",
        "Mukhayl\u012bf"
    ],
    "wof:name":"Mukhaylif",
    "wof:placetype":"locality"
},
  "geometry": {"coordinates":[56.93017,24.12272],"type":"Point"}
}