{
  "type": "Feature",
  "properties": {
    "gn:admin1_code":"07",
    "gn:asciiname":"Mina' Sitt",
    "gn:country_code":"OM",
    "gn:dem":15,
    "gn:feature_class":"P",
    "gn:feature_code":"PPL",
    "gn:name":"M\u012bn\u0101\u2019 Sitt",
    "gn:population":0,
    "gn:timezone":"Asia/Muscat",
    "iso:country":"OM",
    "name:ara_x_preferred":[
        "M\u012bn\u0101\u2019 Sitt"
    ],
    "wof:name":"Mina' Sitt",
    "wof:placetype":"locality"
},
  "geometry": {"coordinates":[56.35722,26.28056],"type":"Point"}
}