{
  "type": "Feature",
  "properties": {
    "gn:admin1_code":"08",
    "gn:asciiname":"Dahaq",
    "gn:country_code":"OM",
    "gn:dem":120,
    "gn:feature_class":"P",
    "gn:feature_code":"PPL",
    "gn:name":"Dahaq",
    "gn:population":0,
    "gn:timezone":"Asia/Muscat",
    "iso:country":"OM",
    "wof:name":"Dahaq",
    "wof:placetype":"locality"
},
  "geometry": {"coordinates":[54.17667,17.13859],"type":"Point"}
}