{
  "type": "Feature",
  "properties": {
    "gn:admin1_code":"07",
    "gn:asciiname":"Al Mahla",
    "gn:country_code":"OM",
    "gn:dem":435,
    "gn:feature_class":"P",
    "gn:feature_code":"PPL",
    "gn:name":"Al Ma\u1e29l\u00e1",
    "gn:population":0,
    "gn:timezone":"Asia/Muscat",
    "iso:country":"OM",
    "name:ara_x_preferred":[
        "\u0627\u0644\u0645\u062d\u0644\u0649"
    ],
    "name:und_x_variant":[
        "Muhal\u012b",
        "Al Ma\u1e29all\u012b",
        "Al Ma\u1e29l\u00e1",
        "Al Mi\u1e25lay"
    ],
    "wof:name":"Al Mahla",
    "wof:placetype":"locality"
},
  "geometry": {"coordinates":[56.32353000000001,25.84234],"type":"Point"}
}