{
  "type": "Feature",
  "properties": {
    "gn:admin1_code":"11",
    "gn:asciiname":"An Naqdah",
    "gn:country_code":"OM",
    "gn:dem":7,
    "gn:feature_class":"P",
    "gn:feature_code":"PPL",
    "gn:name":"An Naqdah",
    "gn:population":0,
    "gn:timezone":"Asia/Muscat",
    "iso:country":"OM",
    "wof:name":"An Naqdah",
    "wof:placetype":"locality"
},
  "geometry": {"coordinates":[56.58861,24.49556],"type":"Point"}
}