{
  "type": "Feature",
  "properties": {
    "gn:admin1_code":"06",
    "gn:asciiname":"Al Habubiyah",
    "gn:country_code":"OM",
    "gn:dem":159,
    "gn:feature_class":"P",
    "gn:feature_code":"PPL",
    "gn:name":"Al Hab\u016bb\u012byah",
    "gn:population":0,
    "gn:timezone":"Asia/Muscat",
    "iso:country":"OM",
    "name:ara_x_preferred":[
        "\u0627\u0644\u0647\u0628\u0648\u0628\u064a\u0651\u0629"
    ],
    "name:und_x_variant":[
        "\u1e28ab\u016bb\u012byah",
        "Al \u1e28ab\u016bb\u012byah",
        "Al Hab\u016bb\u012byah",
        "Al Hub\u016bbiyyah"
    ],
    "wof:name":"Al Habubiyah",
    "wof:placetype":"locality"
},
  "geometry": {"coordinates":[58.74671,23.27075],"type":"Point"}
}