{
  "type": "Feature",
  "properties": {
    "gn:admin1_code":"02",
    "gn:asciiname":"Al `Uqdah al Gharbiyah",
    "gn:country_code":"OM",
    "gn:dem":13,
    "gn:feature_class":"P",
    "gn:feature_code":"PPL",
    "gn:name":"Al \u2018Uqdah al Gharb\u012byah",
    "gn:population":0,
    "gn:timezone":"Asia/Muscat",
    "iso:country":"OM",
    "name:ara_x_preferred":[
        "\u0627\u0644\u0639\u0642\u062f\u0629 \u0627\u0644\u063a\u0631\u0628\u064a\u0651\u0629"
    ],
    "name:und_x_variant":[
        "\u2018Uqdah",
        "Al \u2018Uqdah al Gharb\u012byah",
        "Al Uqdah al Gharbiyyah"
    ],
    "wof:name":"Al `Uqdah al Gharbiyah",
    "wof:placetype":"locality"
},
  "geometry": {"coordinates":[57.79046,23.70841],"type":"Point"}
}