{
  "type": "Feature",
  "properties": {
    "gn:admin1_code":"02",
    "gn:asciiname":"Misin",
    "gn:country_code":"OM",
    "gn:dem":692,
    "gn:feature_class":"P",
    "gn:feature_code":"PPL",
    "gn:name":"Misin",
    "gn:population":0,
    "gn:timezone":"Asia/Muscat",
    "iso:country":"OM",
    "wof:name":"Misin",
    "wof:placetype":"locality"
},
  "geometry": {"coordinates":[57.83333,23.28333],"type":"Point"}
}