{
  "type": "Feature",
  "properties": {
    "gn:admin1_code":"12",
    "gn:asciiname":"Sumut",
    "gn:country_code":"OM",
    "gn:dem":486,
    "gn:feature_class":"P",
    "gn:feature_code":"PPL",
    "gn:name":"Sum\u016b\u0163",
    "gn:population":0,
    "gn:timezone":"Asia/Muscat",
    "iso:country":"OM",
    "name:ara_x_preferred":[
        "Sum\u016bt"
    ],
    "name:ara_x_variant":[
        "\u0633\u0645\u0648\u0637"
    ],
    "name:und_x_variant":[
        "Sum\u016b\u0163",
        "Sum\u016b\u1e6d"
    ],
    "wof:name":"Sumut",
    "wof:placetype":"locality"
},
  "geometry": {"coordinates":[58.56298,22.97241],"type":"Point"}
}