{
  "type": "Feature",
  "properties": {
    "gn:admin1_code":"08",
    "gn:asciiname":"Akharus",
    "gn:country_code":"OM",
    "gn:dem":649,
    "gn:feature_class":"P",
    "gn:feature_code":"PPL",
    "gn:name":"Akh\u0101rus",
    "gn:population":0,
    "gn:timezone":"Asia/Muscat",
    "iso:country":"OM",
    "name:ara_x_preferred":[
        "Akh\u0101rus"
    ],
    "name:ara_x_variant":[
        "\u0623\u062e\u0631\u0627\u0633"
    ],
    "name:und_x_variant":[
        "Akhr\u0101s"
    ],
    "wof:name":"Akharus",
    "wof:placetype":"locality"
},
  "geometry": {"coordinates":[54.35273000000001,17.13758],"type":"Point"}
}