{
  "type": "Feature",
  "properties": {
    "gn:admin1_code":"11",
    "gn:asciiname":"Al Khaza'in",
    "gn:country_code":"OM",
    "gn:dem":8,
    "gn:feature_class":"P",
    "gn:feature_code":"PPL",
    "gn:name":"Al Khaz\u0101\u2019in",
    "gn:population":0,
    "gn:timezone":"Asia/Muscat",
    "iso:country":"OM",
    "name:und_x_variant":[
        "Al Khaz\u0101\u2019in"
    ],
    "wof:name":"Al Khaza'in",
    "wof:placetype":"locality"
},
  "geometry": {"coordinates":[56.83167,24.22222],"type":"Point"}
}