{
  "type": "Feature",
  "properties": {
    "gn:admin1_code":"02",
    "gn:asciiname":"Huwayl as Safil",
    "gn:country_code":"OM",
    "gn:dem":385,
    "gn:feature_class":"P",
    "gn:feature_code":"PPL",
    "gn:name":"\u1e28uwayl as S\u0101fil",
    "gn:population":0,
    "gn:timezone":"Asia/Muscat",
    "iso:country":"OM",
    "name:ara_x_preferred":[
        "\u062d\u0648\u064a\u0644 \u0627\u0644\u0633\u0627\u0641\u0644"
    ],
    "name:und_x_variant":[
        "Al Huwayl",
        "\u1e28uwayl as S\u0101fil",
        "\u1e24uwayl as S\u0101fil"
    ],
    "wof:name":"Huwayl as Safil",
    "wof:placetype":"locality"
},
  "geometry": {"coordinates":[57.30911999999999,23.46729],"type":"Point"}
}