{
  "type": "Feature",
  "properties": {
    "gn:admin1_code":"10",
    "gn:asciiname":"Tawi `Aqdah",
    "gn:country_code":"OM",
    "gn:dem":321,
    "gn:feature_class":"P",
    "gn:feature_code":"PPL",
    "gn:name":"\u0162aw\u012b \u2018Aqdah",
    "gn:population":0,
    "gn:timezone":"Asia/Muscat",
    "iso:country":"OM",
    "name:und_x_variant":[
        "\u0162aw\u012b \u2018Aqdah"
    ],
    "wof:name":"Tawi `Aqdah",
    "wof:placetype":"locality"
},
  "geometry": {"coordinates":[55.84806,24.25194],"type":"Point"}
}