{
  "type": "Feature",
  "properties": {
    "gn:admin1_code":"01",
    "gn:asciiname":"Sayfam",
    "gn:country_code":"OM",
    "gn:dem":530,
    "gn:feature_class":"P",
    "gn:feature_code":"PPL",
    "gn:name":"Sayfam",
    "gn:population":0,
    "gn:timezone":"Asia/Muscat",
    "iso:country":"OM",
    "name:ara_x_preferred":[
        "\u0633\u064a\u0641\u0645"
    ],
    "wof:name":"Sayfam",
    "wof:placetype":"locality"
},
  "geometry": {"coordinates":[57.13271,22.972],"type":"Point"}
}