{
  "type": "Feature",
  "properties": {
    "gn:admin1_code":"10",
    "gn:asciiname":"As Sunaynah",
    "gn:country_code":"OM",
    "gn:dem":257,
    "gn:feature_class":"P",
    "gn:feature_code":"PPL",
    "gn:name":"As Sunaynah",
    "gn:population":0,
    "gn:timezone":"Asia/Muscat",
    "iso:country":"OM",
    "name:ara_x_preferred":[
        "\u0627\u0644\u0633\u0646\u064a\u0646\u0629"
    ],
    "name:und_x_variant":[
        "Sunainah",
        "Sunaynah"
    ],
    "wof:name":"As Sunaynah",
    "wof:placetype":"locality"
},
  "geometry": {"coordinates":[55.95448,23.6065],"type":"Point"}
}