{
  "type": "Feature",
  "properties": {
    "gn:admin1_code":"01",
    "gn:asciiname":"Al Bulaydah",
    "gn:country_code":"OM",
    "gn:dem":793,
    "gn:feature_class":"P",
    "gn:feature_code":"PPL",
    "gn:name":"Al Bulaydah",
    "gn:population":0,
    "gn:timezone":"Asia/Muscat",
    "iso:country":"OM",
    "name:ara_x_preferred":[
        "\u0627\u0644\u0628\u0644\u064a\u062f\u0629"
    ],
    "name:und_x_variant":[
        "Bulaydah",
        "Al Bulaydah"
    ],
    "wof:name":"Al Bulaydah",
    "wof:placetype":"locality"
},
  "geometry": {"coordinates":[56.92012,23.3842],"type":"Point"}
}