{
  "type": "Feature",
  "properties": {
    "gn:admin1_code":"02",
    "gn:asciiname":"Halban",
    "gn:country_code":"OM",
    "gn:dem":93,
    "gn:feature_class":"P",
    "gn:feature_code":"PPL",
    "gn:name":"\u1e28alb\u0101n",
    "gn:population":0,
    "gn:timezone":"Asia/Muscat",
    "iso:country":"OM",
    "name:ara_x_preferred":[
        "\u062d\u0644\u0628\u0627\u0646"
    ],
    "name:und_x_variant":[
        "\u1e28alb\u0101n",
        "\u1e24alb\u0101n"
    ],
    "wof:name":"Halban",
    "wof:placetype":"locality"
},
  "geometry": {"coordinates":[58.03829,23.58138],"type":"Point"}
}