{
  "type": "Feature",
  "properties": {
    "gn:admin1_code":"09",
    "gn:asciiname":"Umm Sulb",
    "gn:country_code":"OM",
    "gn:dem":339,
    "gn:feature_class":"P",
    "gn:feature_code":"PPL",
    "gn:name":"Umm \u015eulb",
    "gn:population":0,
    "gn:timezone":"Asia/Muscat",
    "iso:country":"OM",
    "name:ara_x_preferred":[
        "\u0623\u0645 \u0635\u0644\u0628"
    ],
    "name:und_x_variant":[
        "Umm \u015eulb",
        "Umm S\u0304alib",
        "Um \u1e62ulb"
    ],
    "wof:name":"Umm Sulb",
    "wof:placetype":"locality"
},
  "geometry": {"coordinates":[56.3807,23.34162],"type":"Point"}
}