{
  "type": "Feature",
  "properties": {
    "gn:admin1_code":"02",
    "gn:asciiname":"Al Husayn",
    "gn:country_code":"OM",
    "gn:dem":260,
    "gn:feature_class":"P",
    "gn:feature_code":"PPL",
    "gn:name":"Al \u1e28u\u015fayn",
    "gn:population":0,
    "gn:timezone":"Asia/Muscat",
    "iso:country":"OM",
    "name:ara_x_preferred":[
        "\u0627\u0644\u062d\u0635\u064a\u0646"
    ],
    "name:und_x_variant":[
        "Al \u1e28asan",
        "Al \u1e28as\u012bn",
        "Al \u1e28u\u015fayn",
        "Al \u1e24u\u1e63ayn"
    ],
    "wof:name":"Al Husayn",
    "wof:placetype":"locality"
},
  "geometry": {"coordinates":[57.63278,23.44583],"type":"Point"}
}