{
  "type": "Feature",
  "properties": {
    "gn:admin1_code":"06",
    "gn:asciiname":"`Aynayn",
    "gn:country_code":"OM",
    "gn:dem":8,
    "gn:feature_class":"P",
    "gn:feature_code":"PPL",
    "gn:name":"\u2018Aynayn",
    "gn:population":0,
    "gn:timezone":"Asia/Muscat",
    "iso:country":"OM",
    "name:und_x_variant":[
        "\u2018Aynayn"
    ],
    "wof:name":"`Aynayn",
    "wof:placetype":"locality"
},
  "geometry": {"coordinates":[58.88898,23.26071],"type":"Point"}
}