{
  "type": "Feature",
  "properties": {
    "gn:admin1_code":"02",
    "gn:asciiname":"Al Jufar",
    "gn:country_code":"OM",
    "gn:dem":717,
    "gn:feature_class":"P",
    "gn:feature_code":"PPL",
    "gn:name":"Al Jufar",
    "gn:population":0,
    "gn:timezone":"Asia/Muscat",
    "iso:country":"OM",
    "name:ara_x_preferred":[
        "\u0627\u0644\u062c\u0641\u0631"
    ],
    "wof:name":"Al Jufar",
    "wof:placetype":"locality"
},
  "geometry": {"coordinates":[57.39814000000001,23.26684],"type":"Point"}
}