{
  "type": "Feature",
  "properties": {
    "gn:admin1_code":"07",
    "gn:asciiname":"Bayt al Buwayd",
    "gn:country_code":"OM",
    "gn:dem":982,
    "gn:feature_class":"P",
    "gn:feature_code":"PPL",
    "gn:name":"Bayt al Buway\u1e11",
    "gn:population":0,
    "gn:timezone":"Asia/Muscat",
    "iso:country":"OM",
    "name:ara_x_preferred":[
        "\u0628\u064a\u062a \u0627\u0644\u0628\u0648\u064a\u0636"
    ],
    "name:und_x_variant":[
        "Bayt al Buwaydh",
        "Bayt al Buway\u1e11",
        "Bayt al Buway\u1e0d"
    ],
    "wof:name":"Bayt al Buwayd",
    "wof:placetype":"locality"
},
  "geometry": {"coordinates":[56.18457,26.09342],"type":"Point"}
}