{
  "type": "Feature",
  "properties": {
    "gn:admin1_code":"01",
    "gn:asciiname":"Zuwayhir",
    "gn:country_code":"OM",
    "gn:dem":592,
    "gn:feature_class":"P",
    "gn:feature_code":"PPL",
    "gn:name":"Z\u0327uwayhir",
    "gn:population":0,
    "gn:timezone":"Asia/Muscat",
    "iso:country":"OM",
    "name:und_x_variant":[
        "Z\u0327uwayhir"
    ],
    "wof:name":"Zuwayhir",
    "wof:placetype":"locality"
},
  "geometry": {"coordinates":[57.15111,23.42139],"type":"Point"}
}