{
  "type": "Feature",
  "properties": {
    "gn:admin1_code":"01",
    "gn:asciiname":"Ghul",
    "gn:country_code":"OM",
    "gn:dem":739,
    "gn:feature_class":"P",
    "gn:feature_code":"PPL",
    "gn:name":"Gh\u016bl",
    "gn:population":0,
    "gn:timezone":"Asia/Muscat",
    "iso:country":"OM",
    "name:ara_x_preferred":[
        "Gh\u016bl"
    ],
    "wof:name":"Ghul",
    "wof:placetype":"locality"
},
  "geometry": {"coordinates":[57.21021999999999,23.14507],"type":"Point"}
}