{
  "type": "Feature",
  "properties": {
    "gn:admin1_code":"11",
    "gn:asciiname":"Al Furdah",
    "gn:country_code":"OM",
    "gn:dem":90,
    "gn:feature_class":"P",
    "gn:feature_code":"PPL",
    "gn:name":"Al Fur\u1e11ah",
    "gn:population":0,
    "gn:timezone":"Asia/Muscat",
    "iso:country":"OM",
    "name:ara_x_preferred":[
        "\u0627\u0644\u0641\u0631\u0636\u0629"
    ],
    "name:und_x_variant":[
        "Far\u1e11ah",
        "Al Fur\u1e11ah",
        "Al Far\u1e0dah"
    ],
    "wof:name":"Al Furdah",
    "wof:placetype":"locality"
},
  "geometry": {"coordinates":[57.12029,23.82002],"type":"Point"}
}