{
  "type": "Feature",
  "properties": {
    "gn:admin1_code":"10",
    "gn:asciiname":"Bu Baqarah",
    "gn:country_code":"OM",
    "gn:dem":288,
    "gn:feature_class":"P",
    "gn:feature_code":"PPL",
    "gn:name":"B\u016b Baqarah",
    "gn:population":0,
    "gn:timezone":"Asia/Muscat",
    "iso:country":"OM",
    "name:und_x_variant":[
        "Bu Baqara",
        "B\u016b Baqarah"
    ],
    "wof:name":"Bu Baqarah",
    "wof:placetype":"locality"
},
  "geometry": {"coordinates":[55.83044,23.9743],"type":"Point"}
}