{
  "type": "Feature",
  "properties": {
    "gn:admin1_code":"12",
    "gn:asciiname":"Al Ghallaji",
    "gn:country_code":"OM",
    "gn:dem":361,
    "gn:feature_class":"P",
    "gn:feature_code":"PPL",
    "gn:name":"Al Ghall\u0101j\u012b",
    "gn:population":0,
    "gn:timezone":"Asia/Muscat",
    "iso:country":"OM",
    "name:ara_x_preferred":[
        "Ghul\u0101y"
    ],
    "name:ara_x_variant":[
        "\u0627\u0644\u063a\u0644\u0627\u062c\u064a"
    ],
    "name:und_x_variant":[
        "Al Ghall\u0101j\u012b"
    ],
    "wof:name":"Al Ghallaji",
    "wof:placetype":"locality"
},
  "geometry": {"coordinates":[58.66144,22.64278],"type":"Point"}
}