{
  "type": "Feature",
  "properties": {
    "gn:admin1_code":"06",
    "gn:asciiname":"Bawshar Bani `Umran",
    "gn:country_code":"OM",
    "gn:dem":81,
    "gn:feature_class":"P",
    "gn:feature_code":"PPL",
    "gn:name":"Bawshar Ban\u012b \u2018Umr\u0101n",
    "gn:population":0,
    "gn:timezone":"Asia/Muscat",
    "iso:country":"OM",
    "name:ara_x_preferred":[
        "Bin \u2018Umr\u0101n"
    ],
    "name:ara_x_variant":[
        "\u0628\u0648\u0634\u0631 \u0628\u0646\u064a \u0639\u0645\u0631\u0627\u0646"
    ],
    "name:nno_x_preferred":[
        "Bin `Umran"
    ],
    "name:und_x_variant":[
        "Bawshar Ban\u012b \u2018Umr\u0101n"
    ],
    "wof:name":"Bawshar Bani `Umran",
    "wof:placetype":"locality"
},
  "geometry": {"coordinates":[58.39633000000001,23.5344],"type":"Point"}
}