{
  "type": "Feature",
  "properties": {
    "iso:country":"OM",
    "name:ara_x_preferred":[
        "\u0645\u0642\u0631\u0629"
    ],
    "name:eng_x_preferred":[
        "Magra"
    ],
    "qs:gn_pop":0,
    "qs:name":"\u0645\u0642\u0631\u0629",
    "qs:name_adm0":"\u0639\u0645\u0627\u0646",
    "qs:name_adm1":"\u0638\u0641\u0627\u0631",
    "qs:photos":143,
    "qs:photos_1k":29,
    "qs:photos_9k":1,
    "qs:photos_9r":3,
    "qs:photos_all":143,
    "qs:photos_sr":3,
    "qs:placetype":"Town",
    "qs:pop_sr":"0",
    "qs:woe_adm0":23424898,
    "wof:name":"Magra",
    "wof:placetype":"locality"
},
  "geometry": {"coordinates":[53.475365,16.772658],"type":"Point"}
}