{
  "type": "Feature",
  "properties": {
    "gn:admin1_code":"09",
    "gn:asciiname":"Al Mashaqisah",
    "gn:country_code":"OM",
    "gn:dem":437,
    "gn:feature_class":"P",
    "gn:feature_code":"PPL",
    "gn:name":"Al Mash\u0101qi\u015fah",
    "gn:population":0,
    "gn:timezone":"Asia/Muscat",
    "iso:country":"OM",
    "name:ara_x_preferred":[
        "\u0627\u0644\u0645\u0634\u0627\u0642\u0635\u0629"
    ],
    "name:und_x_variant":[
        "Mush\u0101qa\u015fah",
        "Al Mash\u0101qi\u015fah",
        "Al Mash\u0101q\u1e63ah"
    ],
    "wof:name":"Al Mashaqisah",
    "wof:placetype":"locality"
},
  "geometry": {"coordinates":[56.60859,23.31286],"type":"Point"}
}