{
  "type": "Feature",
  "properties": {
    "gn:admin1_code":"08",
    "gn:asciiname":"Raghb",
    "gn:country_code":"OM",
    "gn:dem":537,
    "gn:feature_class":"P",
    "gn:feature_code":"PPL",
    "gn:name":"Raghb",
    "gn:population":0,
    "gn:timezone":"Asia/Muscat",
    "iso:country":"OM",
    "name:ara_x_preferred":[
        "\u0631\u063a\u0628"
    ],
    "name:und_x_variant":[
        "Raghab",
        "Raghb"
    ],
    "wof:name":"Raghb",
    "wof:placetype":"locality"
},
  "geometry": {"coordinates":[54.1294,17.20664],"type":"Point"}
}