{
  "type": "Feature",
  "properties": {
    "gn:admin1_code":"01",
    "gn:asciiname":"Jaylah",
    "gn:country_code":"OM",
    "gn:dem":357,
    "gn:feature_class":"P",
    "gn:feature_code":"PPL",
    "gn:name":"Jaylah",
    "gn:population":0,
    "gn:timezone":"Asia/Muscat",
    "iso:country":"OM",
    "name:und_x_variant":[
        "Al Qaylah",
        "Qaylah",
        "Jaylah"
    ],
    "wof:name":"Jaylah",
    "wof:placetype":"locality"
},
  "geometry": {"coordinates":[58.01747,23.3517],"type":"Point"}
}