{
  "type": "Feature",
  "properties": {
    "gn:admin1_code":"08",
    "gn:asciiname":"Naid",
    "gn:country_code":"OM",
    "gn:dem":423,
    "gn:feature_class":"P",
    "gn:feature_code":"PPL",
    "gn:name":"Naid",
    "gn:population":0,
    "gn:timezone":"Asia/Muscat",
    "iso:country":"OM",
    "wof:name":"Naid",
    "wof:placetype":"locality"
},
  "geometry": {"coordinates":[54.50861,17.08611],"type":"Point"}
}