{
  "type": "Feature",
  "properties": {
    "gn:admin1_code":"07",
    "gn:asciiname":"Ghabina",
    "gn:country_code":"OM",
    "gn:dem":9,
    "gn:feature_class":"P",
    "gn:feature_code":"PPL",
    "gn:name":"Ghabina",
    "gn:population":0,
    "gn:timezone":"Asia/Muscat",
    "iso:country":"OM",
    "wof:name":"Ghabina",
    "wof:placetype":"locality"
},
  "geometry": {"coordinates":[56.36889,26.24778],"type":"Point"}
}