{
  "type": "Feature",
  "properties": {
    "gn:admin1_code":"06",
    "gn:asciiname":"Al Mu`baylah ash Shamaliyah",
    "gn:country_code":"OM",
    "gn:dem":17,
    "gn:feature_class":"P",
    "gn:feature_code":"PPL",
    "gn:name":"Al Mu\u2018baylah ash Sham\u0101l\u012byah",
    "gn:population":0,
    "gn:timezone":"Asia/Muscat",
    "iso:country":"OM",
    "name:ara_x_preferred":[
        "\u0627\u0644\u0645\u0639\u0628\u064a\u0644\u0629 \u0627\u0644\u0634\u0651\u0645\u0627\u0644\u064a\u0651\u0629"
    ],
    "name:und_x_variant":[
        "Al Ma\u2019balla",
        "Ma\u2018\u0101b\u012blah",
        "Al Mu\u2018baylah ash Sham\u0101l\u012byah",
        "Al Mubaylah ash Shamaliyah",
        "Al Mu\u2018baylah ash Sham\u0101liyyah"
    ],
    "wof:name":"Al Mu`baylah ash Shamaliyah",
    "wof:placetype":"locality"
},
  "geometry": {"coordinates":[58.13551999999999,23.67773],"type":"Point"}
}