{
  "type": "Feature",
  "properties": {
    "gn:admin1_code":"11",
    "gn:asciiname":"Falara",
    "gn:country_code":"OM",
    "gn:dem":4,
    "gn:feature_class":"P",
    "gn:feature_code":"PPL",
    "gn:name":"Falara",
    "gn:population":0,
    "gn:timezone":"Asia/Muscat",
    "iso:country":"OM",
    "wof:name":"Falara",
    "wof:placetype":"locality"
},
  "geometry": {"coordinates":[56.46666999999999,24.75],"type":"Point"}
}