{
  "type": "Feature",
  "properties": {
    "gn:admin1_code":"12",
    "gn:asciiname":"Al Yahmadi",
    "gn:country_code":"OM",
    "gn:dem":484,
    "gn:feature_class":"P",
    "gn:feature_code":"PPL",
    "gn:name":"Al Ya\u1e29mad\u012b",
    "gn:population":0,
    "gn:timezone":"Asia/Muscat",
    "iso:country":"OM",
    "name:ara_x_preferred":[
        "\u0627\u0644\u064a\u062d\u0645\u062f\u064a"
    ],
    "name:und_x_variant":[
        "Al A\u1e29mad\u012b",
        "Al Ya\u1e29mad\u012b",
        "Al Ya\u1e25mad\u012b"
    ],
    "wof:name":"Al Yahmadi",
    "wof:placetype":"locality"
},
  "geometry": {"coordinates":[58.50126,22.76726],"type":"Point"}
}