{
  "type": "Feature",
  "properties": {
    "gn:admin1_code":"11",
    "gn:asciiname":"Aswad",
    "gn:country_code":"OM",
    "gn:dem":61,
    "gn:feature_class":"P",
    "gn:feature_code":"PPL",
    "gn:name":"Aswad",
    "gn:population":0,
    "gn:timezone":"Asia/Muscat",
    "iso:country":"OM",
    "name:ara_x_preferred":[
        "\u0623\u0633\u0648\u062f"
    ],
    "name:deu_x_preferred":[
        "Aswad"
    ],
    "name:fra_x_preferred":[
        "Aswad"
    ],
    "name:hat_x_preferred":[
        "Aswad"
    ],
    "name:jpn_x_preferred":[
        "\u30a2\u30b9\u30ef\u30c9"
    ],
    "name:nld_x_preferred":[
        "Aswad"
    ],
    "name:pol_x_preferred":[
        "Aswad"
    ],
    "name:por_x_preferred":[
        "Aswad"
    ],
    "name:ron_x_preferred":[
        "Aswad"
    ],
    "name:rus_x_preferred":[
        "Aswad"
    ],
    "name:spa_x_preferred":[
        "Aswad"
    ],
    "name:swe_x_preferred":[
        "Aswad"
    ],
    "wof:name":"Aswad",
    "wof:placetype":"locality"
},
  "geometry": {"coordinates":[56.32471,24.86981],"type":"Point"}
}