{
  "type": "Feature",
  "properties": {
    "gn:admin1_code":"11",
    "gn:asciiname":"Aswad",
    "gn:country_code":"OM",
    "gn:dem":61,
    "gn:feature_class":"P",
    "gn:feature_code":"PPL",
    "gn:name":"Aswad",
    "gn:population":0,
    "gn:timezone":"Asia/Muscat",
    "iso:country":"OM",
    "name:ara_x_preferred":[
        "\u0623\u0633\u0648\u062f"
    ],
    "wof:name":"Aswad",
    "wof:placetype":"locality"
},
  "geometry": {"coordinates":[56.32471,24.86981],"type":"Point"}
}