{
  "type": "Feature",
  "properties": {
    "gn:admin1_code":"02",
    "gn:asciiname":"Al Mahyul",
    "gn:country_code":"OM",
    "gn:dem":315,
    "gn:feature_class":"P",
    "gn:feature_code":"PPL",
    "gn:name":"Al Ma\u1e29y\u016bl",
    "gn:population":0,
    "gn:timezone":"Asia/Muscat",
    "iso:country":"OM",
    "name:ara_x_preferred":[
        "\u0627\u0644\u0645\u062d\u064a\u0648\u0644"
    ],
    "name:und_x_variant":[
        "Ma\u1e29y\u016bl",
        "Al Ma\u1e29y\u016bl",
        "Al Ma\u1e25y\u016bl"
    ],
    "wof:name":"Al Mahyul",
    "wof:placetype":"locality"
},
  "geometry": {"coordinates":[57.59471,23.48293],"type":"Point"}
}