{
  "type": "Feature",
  "properties": {
    "gn:admin1_code":"07",
    "gn:asciiname":"Al Mabyaq",
    "gn:country_code":"OM",
    "gn:dem":982,
    "gn:feature_class":"P",
    "gn:feature_code":"PPL",
    "gn:name":"Al Mabyaq",
    "gn:population":0,
    "gn:timezone":"Asia/Muscat",
    "iso:country":"OM",
    "name:ara_x_preferred":[
        "\u0627\u0644\u0645\u0628\u064a\u0642"
    ],
    "name:und_x_variant":[
        "Mabyak",
        "Mubayq",
        "Al Mabyaq"
    ],
    "wof:name":"Al Mabyaq",
    "wof:placetype":"locality"
},
  "geometry": {"coordinates":[56.24829,25.80939],"type":"Point"}
}