{
  "type": "Feature",
  "properties": {
    "gn:admin1_code":"06",
    "gn:asciiname":"Haramil",
    "gn:country_code":"OM",
    "gn:dem":5,
    "gn:feature_class":"P",
    "gn:feature_code":"PPL",
    "gn:name":"\u1e28ar\u0101mil",
    "gn:population":0,
    "gn:timezone":"Asia/Muscat",
    "iso:country":"OM",
    "name:ara_x_preferred":[
        "\u062d\u0631\u0627\u0645\u0644"
    ],
    "name:und_x_variant":[
        "\u1e28ar\u0101mil",
        "Haramil",
        "\u1e24ar\u0101mil"
    ],
    "wof:name":"Haramil",
    "wof:placetype":"locality"
},
  "geometry": {"coordinates":[58.60181,23.59372],"type":"Point"}
}