{
  "type": "Feature",
  "properties": {
    "gn:admin1_code":"08",
    "gn:asciiname":"Shadhrir",
    "gn:country_code":"OM",
    "gn:dem":680,
    "gn:feature_class":"P",
    "gn:feature_code":"PPL",
    "gn:name":"Sha\u1e11hrir",
    "gn:population":0,
    "gn:timezone":"Asia/Muscat",
    "iso:country":"OM",
    "name:ara_x_preferred":[
        "\u0634\u0636\u0631\u064a\u0631"
    ],
    "name:und_x_variant":[
        "Sha\u1e11hrir",
        "Sha\u1e11r\u012br"
    ],
    "wof:name":"Shadhrir",
    "wof:placetype":"locality"
},
  "geometry": {"coordinates":[54.38799,17.14477999999999],"type":"Point"}
}